Workbook

Sheet Readme
A1: ADC Performance Survey 1997-2025
A2: Boris Murmann, University of Hawaii, bmurmann@hawaii.edu
A4: The purpose of this data collection is to help identify trends and limits in the power efficiency of A/D converters. In an ideal world, everyone would use the same metrics and conditions to specify the power dissipation, bandwidth and resolution of their designs. Unfortunately, in this world, different authors use different metrics and interpretations. Having said this, it is clear that the tabulated data in this document must be read with a grain of salt. Clearly, each data point could be shifted up/down, left/right based on your very own interpretation. Note, however, that this will have little impact on the overall objective, i.e. track general trends and performance envelopes.
A6: For use in publications and presentations please cite this data collection as follows:
A7: B. Murmann, "ADC Performance Survey 1997-2024," [Online]. Available: https://github.com/bmurmann/ADC-survey.
A9: Notes on the primary (raw data) columns:
A11: Power (P) - Taken as specified by the authors. Sometimes this number includes power for clocks, references, etc.; sometimes it doesn't. For delta-sigma modulators, the power for the decimation filter is not included. This is fair since the Nyquist converter data also does not include any power typically needed for anti-alias filtering.
A12: fsnyq - Nyquist sampling rate, equal to the sampling rate (fs) divided by the oversampling ratio (OSR). Note that for a complex delta-sigma modulator, the OSR is given by 2*fs/fsnyq.
A13: SNDR_hf, SNR, THD, SFDR are tabulated as the values measured near fsnyq/2 for a Nyquist converter. When this data was not available, data for lower input frequencies is used instead. Fortunately, in recent years, most Nyquist converters are properly evaluated up to fsnyq/2. Only older data points (before ~2003) tend to suffer from "low frequency only" issues. Multi-GHz converters tend to roll off for frequencies much lower than fs/2. For these designs, the SNDR at the highest reasonable/usable fin is used (example: ISSCC 2003, paper 18.2., fs=20GHz, SNDR measured at fin=6GHz).
A14: fin_hf - This is the frequency at which SNDR_hf was measured. For Nyquist ADCs, fin_hf is typically taken equal to fsnyq/2 where justified, i.e. the listed SNDR is also measured at fsnyq/2. Exceptions include designs that roll off below Nyquist (example: ISSCC 2003, paper 18.2., fs=20GHz, SNDR measured up to fin=6GHz ==>fin_hf=6GHz). This column is therefore useful primarily to capture these exceptions, which also tend to be the designs that push the envelope on aperture bandwidth. (Note: this column was called "BW_plot" in earlier versions of this survey.
A15: SNDR_lf - SNDR measured at low input frequencies. The sinusoidal SNDR near Nyquist (SNDR_hf) is not always a meaningful metric. Consider for example recent high-speed converters that are designed for broadband inputs (high speed links, cable TV tuners, etc.), where the signal power is spread rather than being concentrated in one tone. In this case, the low frequency SNDR is actually a better (less pessimistic, perhaps somewhat optimistic) number to consider for system design.
A16: DR is the measured "instantaneous dynamic range" of the converter, i.e. this metric does not contain any extra dBs obtained through variable gain.
... A96: 20250721: Update VLSI 2025

Sheet ISSCC
A1: YEAR | B1: ID | C1: TYPE | D1: ARCHITECTURE | E1: TECHNOLOGY | F1: TITLE | G1: ABSTRACT | H1: AUTHORS | I1: DOI | J1: LINK | K1: COMMENTS | L1: VSUP1 [V] | M1: VSUP2 [V] | N1: VSUP3 [V] | O1: Csamp [pF] | P1: AREA [mm^2] | Q1: SNDR_lf [dB] | R1: fin_hf [Hz] | S1: SNDR_hf [dB] | T1: SNR [dB] | U1: DR [dB] | V1: -THD [dB] | W1: SFDR [dB] | X1: SNDR_plot [dB] | Y1: P [W] | Z1: fs [Hz] | AA1: OSR | AB1: fsnyq [Hz] | AC1: fcenter [Hz] | AD1: P/fsnyq [pJ] | AE1: FOMW_lf [fJ/conv-step] | AF1: FOMW_hf [fJ/conv-step] | AG1: FOMS_lf [dB] | AH1: FOMS_hf [dB] | AI1: FOMW_hf/fsnyq | AJ1: FOMS,hf+10log(fsnyq)
A2: 1997 | B2: 8.1 | C2: NQ | D2: SAR | E2: 1 | F2: A MOSFET-only, 10 b, 200 ksample/s A/D converter capable of 12 b untrimmed linearity | G2: The linearity of a successive approximation (SA) A/D converter is typically limited by its passive network. Published converters based on capacitive arrays or resistive ladders are limited to around 10 b if no trimming or calibration is used. Although static measurements show that MOS transistors are capable of excellent matching, few MOSFET-only converters achieved more than 10 b accuracy without self-calibration. This A/D converter adopts the current division ladder network based on MOSFETs. Extensive measurements on the MOSFET ladders with different resolutions and geometry establish the achievable linearity | H2: C. Hammerschmied, Q. Huang | I2: 10.1109/ISSCC.1997.585301 | J2: =IF(I2<>"?", HYPERLINK(CONCATENATE("https://doi.org/",I2)), "") -> https://doi.org/10.1109/ISSCC.1997.585301 | L2: 5 | P2: 2.155 | R2: =Z2/2 -> 100000 | S2: =9.1*6.02+1.76 -> 56.542 | X2: =+IF(ISNUMBER($S2),$S2,MIN($V2,$T2,$U2,$W2)) -> 56.542 | Y2: =0.0024*5 -> 0.012 | Z2: 200000 | AA2: 1 | AB2: =Z2/AA2 -> 200000 | AD2: =Y2/AB2*1000000000000 -> 60000 | AE2: =IF(ISNUMBER($Q2), $AD2*1000/2^(($Q2-1.76)/6.02), "") | AF2: =$AD2*1000/2^(($X2-1.76)/6.02) -> 109339.8 | AG2: =IF(ISNUMBER($Q2), $Q2+10*LOG10($AB2/2/$Y2), "") | AH2: =$X2+10*LOG10($AB2/2/$Y2) -> 125.75019 | AI2: =AF2/AB2 -> 0.54669902 | AJ2: =AH2+10*LOG10(AB2) -> 178.76049
A3: 1997 | B3: 8.2 | C3: NQ | D3: Folding | E3: 1.00 BiCMOS | F3: A 12 b 50 M sample/s cascaded folding and interpolating ADC | G3: The architecture of this 12 b ADC is based on a three-stage conversion, using cascaded folding and interpolating techniques. Compared to other multi-stage ADC architectures, folding and interpolating ADCs are based on non-linear analog pre-processing. This architecture is an attractive solution for high-resolution ADCs, as extremely linear circuit topologies are not required. To increase the resolution of folding and interpolating ADCs above the published 8 b examples, without raising the number of parallel input stages or the number of comparators in the fine-comparator, a cascaded folding and interpolating architecture is introduced. The ADC achieves 64 dB signal-to-noise ratio (SNR) and 75 dB spurious-free dynamic range (SFDR), while quantizing a 15 MHz full-scale input signal at 50 MSample/s. The 7.0 mm² ADC is fabricated in a 13 GHz, 1 μm BiCMOS process and dissipates 300 mW from a single 5.0 V supply. The device is mounted in a standard 44-pin plastic package | H3: P. Vorenkamp, R. Roovers | I3: 10.1109/ISSCC.1997.585303 | J3: =IF(I3<>"?", HYPERLINK(CONCATENATE("https://doi.org/",I3)), "") -> https://doi.org/10.1109/ISSCC.1997.585303 | L3: 5 | P3: 7 | R3: =Z3/2 -> 25000000 | T3: 64 | W3: 75 | X3: =+IF(ISNUMBER($S3),$S3,MIN($V3,$T3,$U3,$W3)) -> 64 | Y3: 0.3 | Z3: 50000000 | AA3: 1 | AB3: =Z3/AA3 -> 50000000 | AD3: =Y3/AB3*1000000000000 -> 6000 | AE3: =IF(ISNUMBER($Q3), $AD3*1000/2^(($Q3-1.76)/6.02), "") | AF3: =$AD3*1000/2^(($X3-1.76)/6.02) -> 4632.7742 | AG3: =IF(ISNUMBER($Q3), $Q3+10*LOG10($AB3/2/$Y3), "") | AH3: =$X3+10*LOG10($AB3/2/$Y3) -> 143.20819 | AI3: =AF3/AB3 -> 9.2655483e-05 | AJ3: =AH3+10*LOG10(AB3) -> 220.19789
A4: 1997 | B4: 8.3 | C4: NQ | D4: Folding | E4: 0.5 | F4: A 170 mW 10 b 50 Msample/s CMOS ADC in 1 mm² | G4: This 10 b AD-converter at a sample rate of 5O MSample/s, embedded in 50mm² of digital circuitry, shows 8.7 effective bits. A straight flash-architecture would need 1023 accurate fast comparators. With a 2 V input range, a comparator offset voltage of no more than 1 mV can be tolerated. Taking into account that the 1 mV is a 3-6 sigma value, leads to a large chip. If, however, the signals to the comparator are amplified before the critical decision, simple small comparators would suffice. To cope with the dynamic offset caused by the clocking and latch action of the comparator itself, the architecture must tolerate comparator offsets of up to 60-80 mV. Hence, a gain of at least 30 is necessary. A single amplifier however, could not handle this, as the input range of 2 V would be amplified to 60 V. The approach here is to use a distributed amplifier | H4: K. Bult, A. Buchwald, J. Laskowski | I4: 10.1109/ISSCC.1997.585303 | J4: =IF(I4<>"?", HYPERLINK(CONCATENATE("https://doi.org/",I4)), "") -> https://doi.org/10.1109/ISSCC.1997.585303 | L4: 5 | P4: 1 | R4: =Z4/2 -> 25000000 | S4: =1.76+8.6*6.02 -> 53.532 | X4: =+IF(ISNUMBER($S4),$S4,MIN($V4,$T4,$U4,$W4)) -> 53.532 | Y4: 0.17 | Z4: 50000000 | AA4: 1 | AB4: =Z4/AA4 -> 50000000 | AD4: =Y4/AB4*1000000000000 -> 3400 | AE4: =IF(ISNUMBER($Q4), $AD4*1000/2^(($Q4-1.76)/6.02), "") | AF4: =$AD4*1000/2^(($X4-1.76)/6.02) -> 8762.3572 | AG4: =IF(ISNUMBER($Q4), $Q4+10*LOG10($AB4/2/$Y4), "") | AH4: =$X4+10*LOG10($AB4/2/$Y4) -> 135.20691 | AI4: =AF4/AB4 -> 0.00017524714 | AJ4: =AH4+10*LOG10(AB4) -> 212.19661
A5: 1997 | B5: 8.4 | C5: NQ | D5: Two-step | E5: Bipolar | F5: A 12 b 128 MSample/s ADC with 0.05 LSB DNL | G5: This analog-to-digital converter uses integrated dither, dynamic element matching, and output data scrambling to achieve SFDR of 85dB and DNL below 0.05LSB at l28MSample/s. This compares to about 0.5LSB DNL for slower 12b converters. The basic two-step flash architecture is shown. The ±0.25V input is amplified to ±1V and held in the track-and-hold circuit when the input clock rises. The 32 comparators in ADC1 produce an approximation that switches the 32 matched current sources in the main DAC. The residue is formed and amplified in the summer to ±0.5V and is converted by ADC2, an 8b folding-and-interpolating flash ADC. To allow low clock rates, there is no analog pipelining, and all analog settling from the track-to-hold transition to latching the result in ADC2 takes only 4.4ns. The ADC1 and ADC2 results added together form the 12b output. The total signal-to-data-output delay is slightly more than two cycles due to digital pipelining | H5: R. Jewett, K. Poulton, K.-C. Hsieh, J. Doernberg | I5: 10.1109/ISSCC.1997.585305 | J5: =IF(I5<>"?", HYPERLINK(CONCATENATE("https://doi.org/",I5)), "") -> https://doi.org/10.1109/ISSCC.1997.585305 | L5: 5 | N5: -4.5 | R5: =Z5/2 -> 64000000 | T5: 58.4 | X5: =+IF(ISNUMBER($S5),$S5,MIN($V5,$T5,$U5,$W5)) -> 58.4 | Y5: 5.7 | Z5: 128000000 | AA5: 1 | AB5: =Z5/AA5 -> 128000000 | AD5: =Y5/AB5*1000000000000 -> 44531.25 | AE5: =IF(ISNUMBER($Q5), $AD5*1000/2^(($Q5-1.76)/6.02), "") | AF5: =$AD5*1000/2^(($X5-1.76)/6.02) -> 65521.324 | AG5: =IF(ISNUMBER($Q5), $Q5+10*LOG10($AB5/2/$Y5), "") | AH5: =$X5+10*LOG10($AB5/2/$Y5) -> 128.90305 | AI5: =AF5/AB5 -> 0.00051188535 | AJ5: =AH5+10*LOG10(AB5) -> 209.97515
A6: 1997 | B6: 8.8 | C6: NQ | D6: Pipe | E6: 1.4 | F6: A 15 b 5 MSample/s low-spurious CMOS ADC | G6: This 15b CMOS ADC at 5MSample/s has four stages with 5, 5, 5, and 6b each. The number of bits resolved per stage is set higher to achieve the same resolution with less accurate components. Resolving more bits per stage greatly simplifies op amp design and reduces the initial capacitor matching requirement. Furthermore, residue amplifiers with low feedback factors are less sensitive to summing-node parasitics. The first two 5b stages are calibrated using the remaining part of the ADC. Two stages are selected for calibration. The gain ofthe 5b residue amplifier is set to 16 to make room for digital correction. After digital correction, the chip has an 18b output. Performance up to 16b level can be tested after removing 2 LSBs corrupted by digital processing. System partitioning and multi-stage calibration solve two fundamental problems of capacitor matching and finite opamp gain | H6: S.-U. Kwak, B.-S. Song, K. Bacrania | I6: 10.1109/ISSCC.1997.585309 | J6: =IF(I6<>"?", HYPERLINK(CONCATENATE("https://doi.org/",I6)), "") -> https://doi.org/10.1109/ISSCC.1997.585309 | K6: Power includes digital (addtl. 70mW) | L6: 5 | P6: 27.28 | R6: =Z6/2 -> 2500000 | S6: 84.9 | T6: 86.9 | W6: 93 | X6: =+IF(ISNUMBER($S6),$S6,MIN($V6,$T6,$U6,$W6)) -> 84.9 | Y6: 0.13 | Z6: 5000000 | AA6: 1 | AB6: =Z6/AA6 -> 5000000 | AD6: =Y6/AB6*1000000000000 -> 26000 | AE6: =IF(ISNUMBER($Q6), $AD6*1000/2^(($Q6-1.76)/6.02), "") | AF6: =$AD6*1000/2^(($X6-1.76)/6.02) -> 1809.5021 | AG6: =IF(ISNUMBER($Q6), $Q6+10*LOG10($AB6/2/$Y6), "") | AH6: =$X6+10*LOG10($AB6/2/$Y6) -> 157.73997 | AI6: =AF6/AB6 -> 0.00036190042 | AJ6: =AH6+10*LOG10(AB6) -> 224.72967
A7: 1997 | B7: 13.1 | C7: OS | D7: SDSC, Pipe | E7: 0.6 | F7: A 16b ΣΔ pipeline ADC with 2.5 MHz output data-rate | G7: A 16b 2.5 MHz A/D converter in 0.6 μm CMOS addresses the need for wide dynamic range A/D converters with bandwidths in excess of 1 MHz in multi-tone communication. This A/D converter combines the advantages of ΣΔ and pipeline A/D conversion techniques to provide wide dynamic range at a low-oversampling ratio. The device operates at a 20 MHz clock rate, 2.5 MHz output rate (8× oversampling), and provides 89 dB SNR over a 1.25 MHz input bandwidth | H7: T.L Brooks, D.H. Robertson, D.F. Kelly, A. Del Muro, S.W. Harston | I7: 10.1109/ISSCC.1997.585335 | J7: =IF(I7<>"?", HYPERLINK(CONCATENATE("https://doi.org/",I7)), "") -> https://doi.org/10.1109/ISSCC.1997.585335 | P7: 31.8 | R7: 1250000 | T7: 89 | W7: 97 | X7: =+IF(ISNUMBER($S7),$S7,MIN($V7,$T7,$U7,$W7)) -> 89 | Y7: 0.55 | Z7: 20000000 | AA7: 8 | AB7: =Z7/AA7 -> 2500000 | AD7: =Y7/AB7*1000000000000 -> 220000 | AE7: =IF(ISNUMBER($Q7), $AD7*1000/2^(($Q7-1.76)/6.02), "") | AF7: =$AD7*1000/2^(($X7-1.76)/6.02) -> 9549.6618 | AG7: =IF(ISNUMBER($Q7), $Q7+10*LOG10($AB7/2/$Y7), "") | AH7: =$X7+10*LOG10($AB7/2/$Y7) -> 152.56547 | AI7: =AF7/AB7 -> 0.0038198647 | AJ7: =AH7+10*LOG10(AB7) -> 216.54487
A8: 1997 | B8: 13.2 | C8: OS | D8: SDSC | E8: 0.5 | F8: Low-voltage double-sampled ΣΔ converters | G8: In theory, double-sampling in second-order ΣΔ analog-to-digital converters (ADC) can enhance the signal-to-noise ratio (SNR) by 15 dB. In practice however, the SNR performance is usually severely degraded because of mismatches occurring in switched-capacitors (SC). This paper introduces a simple method to solve this problem. Regarding ΣΔ digital-to-analog converters (DAC), in addition to double-sampling, the accompanying use of internal decimation helps to relax the bandwidth requirements of the opamps. Both circuitries are to be operational to supply voltages as low as 1.5 V by using clock bootstrapping. Chip implementation is in double-poly, 2-metal technology featuring 0.5 μm minimum channel lengths | H8: Senderowicz, D.; Nicollini, G.; Pernici, S.; Nagari, A.; Confalonieri, P.; Dallavalle, C. | I8: 10.1109/ISSCC.1997.585336 | J8: =IF(I8<>"?", HYPERLINK(CONCATENATE("https://doi.org/",I8)), "") -> https://doi.org/10.1109/ISSCC.1997.585336 | L8: 1.5 | P8: 0.39 | R8: 1000 | S8: 81 | U8: 88 | X8: =+IF(ISNUMBER($S8),$S8,MIN($V8,$T8,$U8,$W8)) -> 81 | Y8: 0.00055 | Z8: 1000000 | AA8: 500 | AB8: =Z8/AA8 -> 2000 | AD8: =Y8/AB8*1000000000000 -> 275000 | AE8: =IF(ISNUMBER($Q8), $AD8*1000/2^(($Q8-1.76)/6.02), "") | AF8: =$AD8*1000/2^(($X8-1.76)/6.02) -> 29987.335 | AG8: =IF(ISNUMBER($Q8), $Q8+10*LOG10($AB8/2/$Y8), "") | AH8: =$X8+10*LOG10($AB8/2/$Y8) -> 143.59637 | AI8: =AF8/AB8 -> 14.993667 | AJ8: =AH8+10*LOG10(AB8) -> 176.60667
A9: 1997 | B9: 13.3 | C9: OS | D9: SDSC, TI, BP | E9: 0.6 | F9: A two-path bandpass ΣΔ modulator for digital IF extraction at 20 MHz | G9: There is expanding interest in the possibility of moving the intermediate frequency (IF) signal processing in radio receivers and radio test equipment from the analog domain into the digital domain. Digitization of IF processing confers several important advantages, including greater reliability, potentially lower power consumption, and improved performance as technology scales. Unfortunately, as analog signal processing is eliminated and the A/D conversion is moved away from baseband, the signal that must be digitized has a larger dynamic range, and the converter must operate at a higher sampling rate. This work introduces a two-path, switched-capacitor architecture for a bandpass ΣΔ modulator that is suited to digitizing narrowband radio signals with large dynamic range. A fourth-order bandpass modulator is implemented in a standard 0.6 μm, single-poly, triple-metal CMOS process. Operating from a single 3.3 V supply, the modulator digitizes a 200 kHz signal centered at an IF of 20 MHz with an extrapolated dynamic range of 75 dB | H9: Ong, A.K.; Wooley, B.A. | I9: 10.1109/ISSCC.1997.585337 | J9: =IF(I9<>"?", HYPERLINK(CONCATENATE("https://doi.org/",I9)), "") -> https://doi.org/10.1109/ISSCC.1997.585337 | K9: IF=20MHz | L9: 3.3 | P9: 2.73 | R9: 200000 | S9: 75 | U9: 75 | X9: =+IF(ISNUMBER($S9),$S9,MIN($V9,$T9,$U9,$W9)) -> 75 | Y9: 0.072 | Z9: 40000000 | AA9: 100 | AB9: =Z9/AA9 -> 400000 | AC9: 20000000 | AD9: =Y9/AB9*1000000000000 -> 180000 | AE9: =IF(ISNUMBER($Q9), $AD9*1000/2^(($Q9-1.76)/6.02), "") | AF9: =$AD9*1000/2^(($X9-1.76)/6.02) -> 39165.852 | AG9: =IF(ISNUMBER($Q9), $Q9+10*LOG10($AB9/2/$Y9), "") | AH9: =$X9+10*LOG10($AB9/2/$Y9) -> 139.43697 | AI9: =AF9/AB9 -> 0.097914629 | AJ9: =AH9+10*LOG10(AB9) -> 195.45757
A10: 1997 | B10: 13.4 | C10: OS | D10: SDCT, BP | E10: HBT | F10: A bandpass ΣΔ modulator with 92 dB SNR and center frequency continuously programmable from 0 to 70 MHz | G10: Use of a bandpass ΣΔ modulator permits direct conversion of an analog signal to digital form at IF frequencies. This allows the ADC to be moved closer to the receiver front end. Moving the digital interface closer to the antenna reduces receiver analog circuit complexity, eliminates DC-offset cancellation, inphase/quadrature (I/Q) gain calibration, dual I/Q mixers and improves system robustness as mixing is in the digital domain. This second-order bandpass ΣΔ modulator is targeted for an airborne radar system but is also expected to find use in a variety of communications applications. Measurements yield signal to noise+distortion ratio (SNR) from 92 dB (15 b) in narrowband ( 366 kHz) to 44 dB (7 b) in broadband (62.6 MHz) about a center frequency of 55.5 MHz. Modulator sampling rate is 4 GHz and it is implemented in AlInAs-InGaAs HBT technology. The performance represents an improvement of approximately a factor of 10 in bandwidth, resolution and center frequency over other reported bandpass modulators | H10: Raghavan, G.; Jensen, J.F.; Walden, R.H.; Posey, W.P. | I10: 10.1109/ISSCC.1997.585338 | J10: =IF(I10<>"?", HYPERLINK(CONCATENATE("https://doi.org/",I10)), "") -> https://doi.org/10.1109/ISSCC.1997.585338 | K10: Data taken for max. BW, IF=55MHz | P10: 0.5625 | R10: 62600000 | S10: 44.1 | X10: =+IF(ISNUMBER($S10),$S10,MIN($V10,$T10,$U10,$W10)) -> 44.1 | Y10: 1.4 | Z10: 4000000000 | AA10: 31.948882 | AB10: =Z10/AA10 -> 125200000 | AC10: 55000000 | AD10: =Y10/AB10*1000000000000 -> 11182.109 | AE10: =IF(ISNUMBER($Q10), $AD10*1000/2^(($Q10-1.76)/6.02), "") | AF10: =$AD10*1000/2^(($X10-1.76)/6.02) -> 85371.466 | AG10: =IF(ISNUMBER($Q10), $Q10+10*LOG10($AB10/2/$Y10), "") | AH10: =$X10+10*LOG10($AB10/2/$Y10) -> 120.60446 | AI10: =AF10/AB10 -> 0.00068188072 | AJ10: =AH10+10*LOG10(AB10) -> 201.58051
A11: 1997 | B11: 13.5 | C11: OS | D11: SDCT, Complex, BP | E11: 0.8 | F11: A quadrature bandpass ΣΔ modulator for digital radio | G11: In a bandpass ΣΔ modulator, bandpass filtering and feedback around a low-resolution quantizer shape the noise spectrum, facilitating accurate A/D conversion on narrow-band input signals. This is extended to the quadrature, or complex, case if a complex filter - having complex-valued coefficients and thus not restricted to a symmetrical frequency response - is placed in a ΣΔ loop. The modulator performs a “complex” A/D conversion on the pair of analog inputs, that are in phase-quadrature, and it has two high-speed bit stream outputs: one represents the real output; the other the imaginary output. When combined, these outputs form a complex signal that accurately represents the complex input within a narrow frequency band. This quadrature modulator is useful in architectures for a single-chip digital-radio receiver. The receiver ideally has no image response, and thus the bulky narrow-band image-rejection filter in the RF stage of a single-path receiver can be replaced with a broadband one. The architecture alleviates many problems of the direct-conversion receiver, often considered for single-chip implementations, since the input signal is mixed to a non-zero IF where 1/f noise and DC offsets cause no problem and self-interference is not an issue because oscillator frequency is offset from the carrier frequency. The quadrature modulator IC uses standard fully-differential switched-capacitor circuit techniques and is implemented in 0.8 μm CMOS technology | H11: Jantzi, S.; Martin, K.; Sedra, A. | I11: 10.1109/ISSCC.1997.585339 | J11: =IF(I11<>"?", HYPERLINK(CONCATENATE("https://doi.org/",I11)), "") -> https://doi.org/10.1109/ISSCC.1997.585339 | K11: Data taken for max. BW, IF=3.75MHz | P11: 4.32 | R11: 200000 | S11: 62 | U11: 67 | X11: =+IF(ISNUMBER($S11),$S11,MIN($V11,$T11,$U11,$W11)) -> 62 | Y11: 0.13 | Z11: 10000000 | AA11: 25 | AB11: =Z11/AA11 -> 400000 | AC11: 3750000 | AD11: =Y11/AB11*1000000000000 -> 325000 | AE11: =IF(ISNUMBER($Q11), $AD11*1000/2^(($Q11-1.76)/6.02), "") | AF11: =$AD11*1000/2^(($X11-1.76)/6.02) -> 315924.43 | AG11: =IF(ISNUMBER($Q11), $Q11+10*LOG10($AB11/2/$Y11), "") | AH11: =$X11+10*LOG10($AB11/2/$Y11) -> 123.87087 | AI11: =AF11/AB11 -> 0.78981106 | AJ11: =AH11+10*LOG10(AB11) -> 179.89147
A12: 1997 | B12: 13.6 | C12: OS | D12: SDSC | E12: 0.8 | F12: A 5 V, 118 dB ΣΔ analog-to digital converter for wideband digital audio | G12: Digital signal processing can replace analog signal processing in professional audio equipment only when analog-to-digital converter dynamic ranges approach 120 dB. Super-high-end audio applications extend the audio band beyond 30 kHz and require 96 kHz sampling frequency. This paper describes a multi-bit ΣΔ modulator developed for high-end digital audio. The modulator is a single-loop, seventh-order type with a 3-level quantizer. The modulator samples the analog input at 6.144 MHz and has 140 dB signal-to-quantization noise in a 48 kHz bandwidth. The device is fabricated in a double-poly, double-metal, 0.8 μm CMOS process | H12: Leung, K.Y.; Swanson, E.J.; Kafai Leung; Zhu, S.S. | I12: 10.1109/ISSCC.1997.585340 | J12: =IF(I12<>"?", HYPERLINK(CONCATENATE("https://doi.org/",I12)), "") -> https://doi.org/10.1109/ISSCC.1997.585340 | P12: 25 | R12: 48000 | S12: 110 | U12: 118 | X12: =+IF(ISNUMBER($S12),$S12,MIN($V12,$T12,$U12,$W12)) -> 110 | Y12: 0.76 | Z12: 6144000 | AA12: 64 | AB12: =Z12/AA12 -> 96000 | AD12: =Y12/AB12*1000000000000 -> 7916666.7 | AE12: =IF(ISNUMBER($Q12), $AD12*1000/2^(($Q12-1.76)/6.02), "") | AF12: =$AD12*1000/2^(($X12-1.76)/6.02) -> 30619.848 | AG12: =IF(ISNUMBER($Q12), $Q12+10*LOG10($AB12/2/$Y12), "") | AH12: =$X12+10*LOG10($AB12/2/$Y12) -> 158.00428 | AI12: =AF12/AB12 -> 0.31895675 | AJ12: =AH12+10*LOG10(AB12) -> 207.82699
A13: 1997 | B13: 13.7 | C13: OS | D13: SDCT | E13: 0.5 | F13: A 2.3 mW CMOS ΣΔ modulator for audio applications | G13: This audio-quality CMOS ΣΔ modulator operates from a 3.3 V supply with 2.3 mW power consumption. The dynamic range is 96 dB over a 20-20000 Hz bandwidth and THD for a 1 kHz maximum input signal is -104 dB. A modulator with power consumption increased to 6.6 mW at the same supply voltage has 10l dB dynamic range and THD<-110 dB, proving the tradeoff between power consumption and performance | H13: van der Zwan, E.J. | I13: 10.1109/ISSCC.1997.585345 | J13: =IF(I13<>"?", HYPERLINK(CONCATENATE("https://doi.org/",I13)), "") -> https://doi.org/10.1109/ISSCC.1997.585345 | L13: 3.3 | P13: 0.4 | R13: 20000 | U13: 96 | V13: 104 | X13: =+IF(ISNUMBER($S13),$S13,MIN($V13,$T13,$U13,$W13)) -> 96 | Y13: 0.0023 | Z13: 5644800 | AA13: 141.12 | AB13: =Z13/AA13 -> 40000 | AD13: =Y13/AB13*1000000000000 -> 57500 | AE13: =IF(ISNUMBER($Q13), $AD13*1000/2^(($Q13-1.76)/6.02), "") | AF13: =$AD13*1000/2^(($X13-1.76)/6.02) -> 1114.8034 | AG13: =IF(ISNUMBER($Q13), $Q13+10*LOG10($AB13/2/$Y13), "") | AH13: =$X13+10*LOG10($AB13/2/$Y13) -> 165.39302 | AI13: =AF13/AB13 -> 0.027870085 | AJ13: =AH13+10*LOG10(AB13) -> 211.41362
A14: 1998 | B14: 4.4 | C14: OS | D14: SDSC | E14: 0.6 | F14: A 100 kHz 9.6 mW multi bit ΔΣ DAC and ADC using noise shaping dynamic elements matching with tree structure | G14: A multi-bit ΔΣ modulator (ΔΣM) is an attractive means for realizing a high-speed low-power data converter. A loss in dynamic range occurs if stabilization of the feedback loop for a higher-order DSM uses a 1b feedback signal. The classical 1b ADC and/or DAC do not follow the theoretical SNR of (8+6 N)L(dB), where N is the order of the DSM, and 2L is the oversampling ratio. In contrast, multi-bit feedback stabilizes a higher-order DSM with little loss of dynamic range. As the internal signal swing is reduced with increase in number of feedback signal bits, the multi-bit DSM requires a lower slew rate and thus less power for analog circuits than the 1b case. There is an increase in SNR due to use of a multi-bit internal DAC to reduce the oversampling ratio and hence to reduce power consumption of the analog portion | H14: Yasuda, A.; Tanimoto, H.; Lida, T. | I14: 10.1109/ISSCC.1998.672377 | J14: =IF(I14<>"?", HYPERLINK(CONCATENATE("https://doi.org/",I14)), "") -> https://doi.org/10.1109/ISSCC.1998.672377 | R14: 100000 | U14: 79 | V14: 75 | X14: =+IF(ISNUMBER($S14),$S14,MIN($V14,$T14,$U14,$W14)) -> 75 | Y14: 0.0096 | Z14: 5000000 | AA14: 25 | AB14: =Z14/AA14 -> 200000 | AD14: =Y14/AB14*1000000000000 -> 48000 | AE14: =IF(ISNUMBER($Q14), $AD14*1000/2^(($Q14-1.76)/6.02), "") | AF14: =$AD14*1000/2^(($X14-1.76)/6.02) -> 10444.227 | AG14: =IF(ISNUMBER($Q14), $Q14+10*LOG10($AB14/2/$Y14), "") | AH14: =$X14+10*LOG10($AB14/2/$Y14) -> 145.17729 | AI14: =AF14/AB14 -> 0.052221136 | AJ14: =AH14+10*LOG10(AB14) -> 198.18759
A15: 1998 | B15: 4.6 | C15: OS | D15: SDSC, SwOpAmp | E15: 0.5 | F15: A 900 mV 40 μW switched opamp ΔΣ modulator with 77 dB dynamic range | G15: Portable electronic systems require low-voltage low-power building blocks. An important building block is an A/D converter. ΔΣ ADCs provide an efficient way of trading off speed for resolution. The switched op amp (SO) technique allows design of switched-capacitor (SC) circuits at very low supply voltage without the use of multithreshold technologies or voltage multipliers to drive the switches. The basic idea of it is to leave out the switches connected to the output of the amplifier in a SC integrator, because those are the ones that fail to conduct when the supply voltage is low. Switches can only be connected to well-chosen reference voltages. In this implementation the differential modified SO integrator cell is used, so the reference voltages are VSS and VDD. This allows maximum overdrive of VDD-VSS for the switches | H15: Peluso, V.; Vancorenland, P.; Marques, A.; Steyaert, M.; Sansen, W. | I15: 10.1109/ISSCC.1998.672379 | J15: =IF(I15<>"?", HYPERLINK(CONCATENATE("https://doi.org/",I15)), "") -> https://doi.org/10.1109/ISSCC.1998.672379 | P15: 0.85 | R15: 16000 | S15: 62 | U15: 77 | X15: =+IF(ISNUMBER($S15),$S15,MIN($V15,$T15,$U15,$W15)) -> 62 | Y15: 4e-05 | Z15: 1538000 | AA15: 48.0625 | AB15: =Z15/AA15 -> 32000 | AD15: =Y15/AB15*1000000000000 -> 1250 | AE15: =IF(ISNUMBER($Q15), $AD15*1000/2^(($Q15-1.76)/6.02), "") | AF15: =$AD15*1000/2^(($X15-1.76)/6.02) -> 1215.0939 | AG15: =IF(ISNUMBER($Q15), $Q15+10*LOG10($AB15/2/$Y15), "") | AH15: =$X15+10*LOG10($AB15/2/$Y15) -> 148.0206 | AI15: =AF15/AB15 -> 0.037971686 | AJ15: =AH15+10*LOG10(AB15) -> 193.0721
A16: 1998 | B16: 9.1 | C16: NQ | D16: Pipe | E16: 0.7 | F16: A single-ended 12b 20Msample/s self-calibrating pipeline A/D converter | G16: This single-ended 12b 20 MSample/s pipeline ADC has good performance for Nyquist frequency inputs. Architecture and calibration algorithms minimize digital correction circuitry and noise crosstalk. The single-ended performance is achieved with a novel input common-mode feedback technique in the S/H stage. The total power dissipation is only 250 mW from a single 5 V supply | H16: I. Opris, L. Lewicki, and B. Wong | I16: 10.1109/ISSCC.1998.672406 | J16: =IF(I16<>"?", HYPERLINK(CONCATENATE("https://doi.org/",I16)), "") -> https://doi.org/10.1109/ISSCC.1998.672406 | L16: 5 | P16: 9 | R16: 10000000 | T16: 65.4 | V16: 70.6 | X16: =+IF(ISNUMBER($S16),$S16,MIN($V16,$T16,$U16,$W16)) -> 65.4 | Y16: 0.25 | Z16: 20000000 | AA16: 1 | AB16: =Z16/AA16 -> 20000000 | AD16: =Y16/AB16*1000000000000 -> 12500 | AE16: =IF(ISNUMBER($Q16), $AD16*1000/2^(($Q16-1.76)/6.02), "") | AF16: =$AD16*1000/2^(($X16-1.76)/6.02) -> 8214.7229 | AG16: =IF(ISNUMBER($Q16), $Q16+10*LOG10($AB16/2/$Y16), "") | AH16: =$X16+10*LOG10($AB16/2/$Y16) -> 141.4206 | AI16: =AF16/AB16 -> 0.00041073614 | AJ16: =AH16+10*LOG10(AB16) -> 214.4309
A17: 1998 | B17: 9.2 | C17: NQ | D17: Pipe, TI | E17: 1 | F17: Digital background calibration of a 10b 40Msample/s parallel pipelined ADC | G17: This time-interleaved pipelined ADC uses monolithic digital background calibration to overcome the effects of the offset and gain mismatches between channels. The contributions here are use of digital background calibration to overcome these mismatches and implementation of these techniques in conjunction with the ADCs on one CMOS IC. Background calibration is done by adding a calibration signal to the ADC input and processing both simultaneously. A potential advantage of this approach is that the calibration signal acts as dither and improves the linearity of the system | H17: D. Fu, K. Dyer, S. Lewis, and P. Hurst, | I17: 10.1109/ISSCC.1998.672407 | J17: =IF(I17<>"?", HYPERLINK(CONCATENATE("https://doi.org/",I17)), "") -> https://doi.org/10.1109/ISSCC.1998.672407 | P17: 22 | R17: 20000000 | S17: 55 | U17: 55 | W17: 72 | X17: =+IF(ISNUMBER($S17),$S17,MIN($V17,$T17,$U17,$W17)) -> 55 | Y17: 0.565 | Z17: 40000000 | AA17: 1 | AB17: =Z17/AA17 -> 40000000 | AD17: =Y17/AB17*1000000000000 -> 14125 | AE17: =IF(ISNUMBER($Q17), $AD17*1000/2^(($Q17-1.76)/6.02), "") | AF17: =$AD17*1000/2^(($X17-1.76)/6.02) -> 30741.367 | AG17: =IF(ISNUMBER($Q17), $Q17+10*LOG10($AB17/2/$Y17), "") | AH17: =$X17+10*LOG10($AB17/2/$Y17) -> 130.48982 | AI17: =AF17/AB17 -> 0.00076853418 | AJ17: =AH17+10*LOG10(AB17) -> 206.51042
A18: 1998 | B18: 9.3 | C18: NQ | D18: Pipe, TI | E18: 1 | F18: Analog background calibration of a 10b 40Msample/s parallel pipelined ADC | G18: The sampling rate of an ADC often limits speed of a signal processing system. Sampling rate at the A/D interface can be increased by using multiple component ADCs that are time interleaved. Mismatches in offsets, gains, and sampling times among the component ADCs limit the performance of the ADC system. Previous time-interleaved ADC arrays use careful layout, foreground calibration and/or digital filters to minimize the effects of these mismatches. The presented time-interleaved ADC uses monolithic analog background calibration to match the gains and offsets of the component pipelined ADCs. The contributions are an expandible adaptive background calibration technique for parallel ADCs and a calibration loop that uses a mixed-signal integrator. The fully-differential prototype is fabricated in a 1.0 μm CMOS single-poly process with poly-thin-oxide-diffusion capacitors. It includes 3 pipelined ADCs, one algorithmic ADC, the calibration signal generator, channel control logic, and 6 mixed-signal integrators, each followed by a unity-gain buffer that supplies the offset or reference correction voltage to one of the pipelined ADCs. The SC integrator and ADC stages use telescopic opamps with source followers at the input | H18: K. Dyer, D. Fu, S. Lewis, and P. Hurst, | I18: 10.1109/ISSCC.1998.672408 | J18: =IF(I18<>"?", HYPERLINK(CONCATENATE("https://doi.org/",I18)), "") -> https://doi.org/10.1109/ISSCC.1998.672408 | P18: 42 | R18: 20000000 | S18: 58 | X18: =+IF(ISNUMBER($S18),$S18,MIN($V18,$T18,$U18,$W18)) -> 58 | Y18: 0.65 | Z18: 40000000 | AA18: 1 | AB18: =Z18/AA18 -> 40000000 | AD18: =Y18/AB18*1000000000000 -> 16250 | AE18: =IF(ISNUMBER($Q18), $AD18*1000/2^(($Q18-1.76)/6.02), "") | AF18: =$AD18*1000/2^(($X18-1.76)/6.02) -> 25036.473 | AG18: =IF(ISNUMBER($Q18), $Q18+10*LOG10($AB18/2/$Y18), "") | AH18: =$X18+10*LOG10($AB18/2/$Y18) -> 132.88117 | AI18: =AF18/AB18 -> 0.00062591181 | AJ18: =AH18+10*LOG10(AB18) -> 208.90177
A19: 1998 | B19: 9.4 | C19: NQ | D19: Pipe | E19: 0.5 | F19: A continuously-calibrated 10Msample/s 12b 3.3V ADC | G19: Continuous calibration allows a converter to function continuously in the presence of environmental fluctuations and supply variations by periodically correcting for errors without interrupting the ADC output. This paper introduces a technique for continuously calibrating a pipelined A/D converter. Calibration is performed in the analog domain so as to avoid high-linearity calibration hardware or complex signal processing. A 10 MS ample/s, 12b converter implemented in a conventional 0.5 μm, single-poly, four-metal, CMOS technology operates from a 3.3V supply. This experimental circuit digitizes a 4.8 MHz signal with a peak SNDR of 67 dB | H19: Joseph Ingino Jr. and Bruce Wooley | I19: 10.1109/ISSCC.1998.672409 | J19: =IF(I19<>"?", HYPERLINK(CONCATENATE("https://doi.org/",I19)), "") -> https://doi.org/10.1109/ISSCC.1998.672409 | L19: 3.3 | P19: 14.5 | R19: 5000000 | S19: 67 | X19: =+IF(ISNUMBER($S19),$S19,MIN($V19,$T19,$U19,$W19)) -> 67 | Y19: 0.265 | Z19: 10000000 | AA19: 1 | AB19: =Z19/AA19 -> 10000000 | AD19: =Y19/AB19*1000000000000 -> 26500 | AE19: =IF(ISNUMBER($Q19), $AD19*1000/2^(($Q19-1.76)/6.02), "") | AF19: =$AD19*1000/2^(($X19-1.76)/6.02) -> 14485.077 | AG19: =IF(ISNUMBER($Q19), $Q19+10*LOG10($AB19/2/$Y19), "") | AH19: =$X19+10*LOG10($AB19/2/$Y19) -> 139.75724 | AI19: =AF19/AB19 -> 0.0014485077 | AJ19: =AH19+10*LOG10(AB19) -> 209.75724
A20: 1998 | B20: 9.5 | C20: NQ | D20: Pipe, TI | E20: 0.5 | F20: 8b 75Msample/s 70mW parallel pipelined ADC incorporating double sampling | G20: This 8b pipelined analog-to-digital converter (ADC) incorporates double sampling into the residue signal path of a 1.5b-per-stage architecture to effectively double the throughput of the ADC for a given analog power consumption. Residue amplifiers and sub-ADC comparators are shared between two time-interleaved channels and the sampling capacitors in the second stage are scaled in order to reduce power consumption. The ADC presented here achieves 75 MSamples/s while consuming 70 mW. The converter measures 5.5 mm² and is fabricated in a 3.3 V 0.5 μm digital CMOS process with four levels of metal and no special mask layers for passive components | H20: W. Bright | I20: 10.1109/ISSCC.1998.672410 | J20: =IF(I20<>"?", HYPERLINK(CONCATENATE("https://doi.org/",I20)), "") -> https://doi.org/10.1109/ISSCC.1998.672410 | P20: 5.5 | R20: 37500000 | S20: 43.3 | T20: 46.3 | U20: 47 | W20: 51 | X20: =+IF(ISNUMBER($S20),$S20,MIN($V20,$T20,$U20,$W20)) -> 43.3 | Y20: 0.07 | Z20: 75000000 | AA20: 1 | AB20: =Z20/AA20 -> 75000000 | AD20: =Y20/AB20*1000000000000 -> 933.33333 | AE20: =IF(ISNUMBER($Q20), $AD20*1000/2^(($Q20-1.76)/6.02), "") | AF20: =$AD20*1000/2^(($X20-1.76)/6.02) -> 7813.2154 | AG20: =IF(ISNUMBER($Q20), $Q20+10*LOG10($AB20/2/$Y20), "") | AH20: =$X20+10*LOG10($AB20/2/$Y20) -> 130.58933 | AI20: =AF20/AB20 -> 0.00010417621 | AJ20: =AH20+10*LOG10(AB20) -> 209.33994
A21: 1998 | B21: 9.6 | C21: NQ | D21: Flash | E21: 0.35 BiCMOS | F21: A 5.75b 350Msample/s or 6.75b 150Msample/s reconfigurable flash ADC for a PRML read channel | G21: A reconfigurable flash analog-to-digital converter (ADC), is suited for use in a partial response maximum likelihood (PRML) read channel with digital servo. A 5V version is integrated in a read channel with digital servo using BiCMOS technology | H21: P. Setty, J. Barner, J. Plany, H. Burger, and J. Sonntag | I21: 10.1109/ISSCC.1998.672411 | J21: =IF(I21<>"?", HYPERLINK(CONCATENATE("https://doi.org/",I21)), "") -> https://doi.org/10.1109/ISSCC.1998.672411 | P21: 0.75 | R21: 175000000 | S21: 31 | X21: =+IF(ISNUMBER($S21),$S21,MIN($V21,$T21,$U21,$W21)) -> 31 | Y21: 0.225 | Z21: 350000000 | AA21: 1 | AB21: =Z21/AA21 -> 350000000 | AD21: =Y21/AB21*1000000000000 -> 642.85714 | AE21: =IF(ISNUMBER($Q21), $AD21*1000/2^(($Q21-1.76)/6.02), "") | AF21: =$AD21*1000/2^(($X21-1.76)/6.02) -> 22180.37 | AG21: =IF(ISNUMBER($Q21), $Q21+10*LOG10($AB21/2/$Y21), "") | AH21: =$X21+10*LOG10($AB21/2/$Y21) -> 119.90856 | AI21: =AF21/AB21 -> 6.3372485e-05 | AJ21: =AH21+10*LOG10(AB21) -> 205.34924
A22: 1998 | B22: 9.7 | C22: NQ | D22: Folding | E22: 0.50 BiCMOS | F22: A 400Msample/s 6b CMOS folding and interpolating ADC | G22: A 6b 400 MSample/s folding and interpolating CMOS ADC uses a low-impedance current-mode approach. Current division interpolation in the folders allows fast low-voltage operation. This interpolation together with a short aperture comparator, gives good performance for high-frequency inputs, without using a sample-and-hold. The ADC uses a single clock and its complement. The 0.6 mm² CMOS converter, fabricated in a 0.5 μm BiCMOS process dissipates 200 mW from a 3.2 V supply | H22: M. Flynn, B. Sheahan | I22: 10.1109/ISSCC.1998.672412 | J22: =IF(I22<>"?", HYPERLINK(CONCATENATE("https://doi.org/",I22)), "") -> https://doi.org/10.1109/ISSCC.1998.672412 | L22: 3.2 | P22: 0.6 | R22: 200000000 | S22: 29.2 | V22: 33.6 | X22: =+IF(ISNUMBER($S22),$S22,MIN($V22,$T22,$U22,$W22)) -> 29.2 | Y22: 0.2 | Z22: 400000000 | AA22: 1 | AB22: =Z22/AA22 -> 400000000 | AD22: =Y22/AB22*1000000000000 -> 500 | AE22: =IF(ISNUMBER($Q22), $AD22*1000/2^(($Q22-1.76)/6.02), "") | AF22: =$AD22*1000/2^(($X22-1.76)/6.02) -> 21224.295 | AG22: =IF(ISNUMBER($Q22), $Q22+10*LOG10($AB22/2/$Y22), "") | AH22: =$X22+10*LOG10($AB22/2/$Y22) -> 119.2 | AI22: =AF22/AB22 -> 5.3060738e-05 | AJ22: =AH22+10*LOG10(AB22) -> 205.2206
A23: 1999 | B23: 3.1 | C23: OS | D23: SDSC | E23: 0.5 | F23: A 1.5 V 1.0 mW audio ΔΣ modulator with 98 dB dynamic range | G23: This audio-quality switched-capacitor (SC) ΔΣ modulator operates from a single 1.5 V supply and dissipates 1.0 mW. When clocked at 2.82 MHz, it achieves 98.2 dB dynamic range (DR) in a 20 kHz bandwidth. The peak SNR and SNDR are 90 dB and 88 dB, respectively. The fully-differential experimental circuit has been integrated in a 0.5 μm triple-metal single-poly CMOS n-well process with metal-to-poly capacitors. | H23: A.L. Coban, P.E. Allen | I23: 10.1109/ISSCC.1999.759091 | J23: =IF(I23<>"?", HYPERLINK(CONCATENATE("https://doi.org/",I23)), "") -> https://doi.org/10.1109/ISSCC.1999.759091 | L23: 1.5 | P23: 0.53 | R23: 20000 | S23: 88 | T23: 90 | U23: 98.2 | X23: =+IF(ISNUMBER($S23),$S23,MIN($V23,$T23,$U23,$W23)) -> 88 | Y23: =0.00067*1.5 -> 0.001005 | Z23: 2822400 | AA23: 70.56 | AB23: =Z23/AA23 -> 40000 | AD23: =Y23/AB23*1000000000000 -> 25125 | AE23: =IF(ISNUMBER($Q23), $AD23*1000/2^(($Q23-1.76)/6.02), "") | AF23: =$AD23*1000/2^(($X23-1.76)/6.02) -> 1223.704 | AG23: =IF(ISNUMBER($Q23), $Q23+10*LOG10($AB23/2/$Y23), "") | AH23: =$X23+10*LOG10($AB23/2/$Y23) -> 160.98864 | AI23: =AF23/AB23 -> 0.030592599 | AJ23: =AH23+10*LOG10(AB23) -> 207.00924
A24: 1999 | B24: 3.2 | C24: OS | D24: SDCT | E24: 0.35 | F24: A 1.8 mW CMOS ΣΔ modulator with integrated mixer for A/D conversion of IF signals | G24: This CMOS IFΣΔ modulator combines the functions of an IF mixer and an anti-aliasing filter with a continuous-time (CT) baseband ΣΔ modulator for A/D conversion of IF signals in radio receivers. Advantage is taken of the high linearity and low-power of the CT baseband ΣΔ modulator. The resulting IFΣΔ modulator consumes 1.8 mW and has +36 dBV IP3. The IF ΣΔ modulator of this paper is for mobile phones (GSM specification), and is promising for application in other types of receivers | H24: Breems, L.J.; van de Zwan, E.J.; Dijkmans, E.C.; Huijsing, J.H. | I24: 10.1109/ISSCC.1999.759363 | J24: =IF(I24<>"?", HYPERLINK(CONCATENATE("https://doi.org/",I24)), "") -> https://doi.org/10.1109/ISSCC.1999.759363 | P24: 0.2 | R24: 100000 | S24: 84 | U24: 86 | X24: =+IF(ISNUMBER($S24),$S24,MIN($V24,$T24,$U24,$W24)) -> 84 | Y24: 0.0018 | Z24: 13000000 | AA24: 65 | AB24: =Z24/AA24 -> 200000 | AD24: =Y24/AB24*1000000000000 -> 9000 | AE24: =IF(ISNUMBER($Q24), $AD24*1000/2^(($Q24-1.76)/6.02), "") | AF24: =$AD24*1000/2^(($X24-1.76)/6.02) -> 694.75669 | AG24: =IF(ISNUMBER($Q24), $Q24+10*LOG10($AB24/2/$Y24), "") | AH24: =$X24+10*LOG10($AB24/2/$Y24) -> 161.44727 | AI24: =AF24/AB24 -> 0.0034737834 | AJ24: =AH24+10*LOG10(AB24) -> 214.45757
A25: 1999 | B25: 3.3 | C25: OS | D25: SDSC, Pipe | E25: 1.2 | F25: A Nyquist-rate pipelined oversampling A/D converter | G25: Oversampling and noise-shaping techniques, such as ΣΔ modulation, have an inherent tradeoff between accuracy and speed, whereby resolution in amplitude is at the expense of resolution in time. Because their internal circuits must operate over many clock cycles to produce a single result, they have limited data rates and power dissipation is a concern. Much attention has been focused on improving the speed and power of ΣΔ analog-to-digital converters (ADCs) by use of higher-order modulators, multi-bit feedback, and multi-bit architectures with single-bit feedback. However, data rates remain limited to less than a few MHz and are not easily extended. A pipelined oversampling architecture circumvents this speed-resolution tradeoff by performing spatial, rather than temporal, oversampling. It combines the high resolution of Σδ techniques with the high speed of pipelined converters so that both of these attributes are simultaneously achievable | H25: Paul, S.; Hae-Seung Lee; Goodrich, J.; Alailima, T.; Santiago, D. | I25: 10.1109/ISSCC.1999.759092 | J25: =IF(I25<>"?", HYPERLINK(CONCATENATE("https://doi.org/",I25)), "") -> https://doi.org/10.1109/ISSCC.1999.759092 | P25: 47 | R25: 9000000 | S25: 71 | T25: 74 | U25: 78 | W25: 78 | X25: =+IF(ISNUMBER($S25),$S25,MIN($V25,$T25,$U25,$W25)) -> 71 | Y25: 0.324 | Z25: 18000000 | AA25: 1 | AB25: =Z25/AA25 -> 18000000 | AD25: =Y25/AB25*1000000000000 -> 18000 | AE25: =IF(ISNUMBER($Q25), $AD25*1000/2^(($Q25-1.76)/6.02), "") | AF25: =$AD25*1000/2^(($X25-1.76)/6.02) -> 6207.654 | AG25: =IF(ISNUMBER($Q25), $Q25+10*LOG10($AB25/2/$Y25), "") | AH25: =$X25+10*LOG10($AB25/2/$Y25) -> 145.43697 | AI25: =AF25/AB25 -> 0.00034486967 | AJ25: =AH25+10*LOG10(AB25) -> 217.9897
A26: 1999 | B26: 3.4 | C26: OS | D26: SDCT, BP | E26: 0.5 | F26: A 6th-order continuous-time bandpass ΣΔ modulator for digital radio IF | G26: A bandpass SD Modulator (SDM) ADC uses negative feedback of a bandpass-filtered error-signal and a high oversampling ratio to reduce the in-band errors of a low-resolution quantizer. As high-order (>4) bandpass SDMs exhibit signal-dependent stability, multibit quantizers are often used to lower the quantization noise of a 2nd or 4th order SDM. However, the accuracy required of the intermediate quantizer levels is high as mismatch affects the overall SDM performance. A 6th-order SDM has a single-bit quantizer for digitizing IF signals of 10.7 MHz | H26: van Engalen, J.; van de Plassche, R.; Sokvoort, E.; Venes, A. | I26: 10.1109/ISSCC.1999.759093 | J26: =IF(I26<>"?", HYPERLINK(CONCATENATE("https://doi.org/",I26)), "") -> https://doi.org/10.1109/ISSCC.1999.759093 | K26: Data for 10.7MHZ IF, BW=200kHz | P26: 0.36 | R26: 200000 | S26: 63.5 | U26: 67 | X26: =+IF(ISNUMBER($S26),$S26,MIN($V26,$T26,$U26,$W26)) -> 63.5 | Y26: 0.06 | Z26: 80000000 | AA26: 200 | AB26: =Z26/AA26 -> 400000 | AC26: 10700000 | AD26: =Y26/AB26*1000000000000 -> 150000 | AE26: =IF(ISNUMBER($Q26), $AD26*1000/2^(($Q26-1.76)/6.02), "") | AF26: =$AD26*1000/2^(($X26-1.76)/6.02) -> 122682.79 | AG26: =IF(ISNUMBER($Q26), $Q26+10*LOG10($AB26/2/$Y26), "") | AH26: =$X26+10*LOG10($AB26/2/$Y26) -> 128.72879 | AI26: =AF26/AB26 -> 0.30670696 | AJ26: =AH26+10*LOG10(AB26) -> 184.74939
A27: 1999 | B27: 3.7 | C27: OS | D27: SDCT | E27: 0.80 BiCMOS | F27: A 400 MHz 12 b 18 mW IF digitizer with mixer inside a ΣΔ modulator loop | G27: One method of IF digitization consists of a down-conversion mixer followed by a lowpass ΣΔ modulator. However, as one moves to high IF, the down conversion mixer's distortion deteriorates rapidly and more power has to be dissipated to restore the mixer's distortion to an acceptable level. In order to achieve low-distortion while maintaining low power dissipation, a new digitizer that suppresses this mixer distortion by placing the mixer inside a modified ΣΔ feedback loop, and capable of operating at 400 MHz, is presented | H27: Namdar, A.; Laung, B.H. | I27: 10.1109/ISSCC.1999.759096 | J27: =IF(I27<>"?", HYPERLINK(CONCATENATE("https://doi.org/",I27)), "") -> https://doi.org/10.1109/ISSCC.1999.759096 | P27: 1.5 | R27: 40000 | S27: 66 | U27: 72 | X27: =+IF(ISNUMBER($S27),$S27,MIN($V27,$T27,$U27,$W27)) -> 66 | Y27: 0.018 | Z27: 20000000 | AA27: 250 | AB27: =Z27/AA27 -> 80000 | AD27: =Y27/AB27*1000000000000 -> 225000 | AE27: =IF(ISNUMBER($Q27), $AD27*1000/2^(($Q27-1.76)/6.02), "") | AF27: =$AD27*1000/2^(($X27-1.76)/6.02) -> 137994.71 | AG27: =IF(ISNUMBER($Q27), $Q27+10*LOG10($AB27/2/$Y27), "") | AH27: =$X27+10*LOG10($AB27/2/$Y27) -> 129.46787 | AI27: =AF27/AB27 -> 1.7249338 | AJ27: =AH27+10*LOG10(AB27) -> 178.49877
A28: 1999 | B28: 18.1 | C28: NQ | D28: Algorithmic | E28: 1.5 | F28: A 12 b digital-background-calibrated algorithmic ADC with -90dB THD | G28: The linearity of analog-to-digital converters (ADCs) is often limited by component mismatches. Trimming can be used to achieve high linearity but cannot track variations over time caused by component aging or by temperature and power-supply changes. Background calibration overcomes this limitation. However, previous background-calibration methods require complicated post processing, occupy some of the range of the analog signal under conversion, or are tailored for a specific type of converter. This ADC uses a queue-based architecture for creating calibration time slots without disturbing the sampling of the input signal. The digital background calibration uses an adaptive algorithm to improve linearity. The queue-based architecture for generating the calibration time slots and the digital-background-calibration method are independent and can be used separately | H28: Ozan E. Erdogan, Paul J. Hurst, and Stephen H. Lewis | I28: 10.1109/ISSCC.1999.759266 | J28: =IF(I28<>"?", HYPERLINK(CONCATENATE("https://doi.org/",I28)), "") -> https://doi.org/10.1109/ISSCC.1999.759266 | P28: 5.94 | R28: 62500 | S28: 71 | V28: 90 | W28: 95 | X28: =+IF(ISNUMBER($S28),$S28,MIN($V28,$T28,$U28,$W28)) -> 71 | Y28: 0.016 | Z28: 125000 | AA28: 1 | AB28: =Z28/AA28 -> 125000 | AD28: =Y28/AB28*1000000000000 -> 128000 | AE28: =IF(ISNUMBER($Q28), $AD28*1000/2^(($Q28-1.76)/6.02), "") | AF28: =$AD28*1000/2^(($X28-1.76)/6.02) -> 44143.318 | AG28: =IF(ISNUMBER($Q28), $Q28+10*LOG10($AB28/2/$Y28), "") | AH28: =$X28+10*LOG10($AB28/2/$Y28) -> 136.9176 | AI28: =AF28/AB28 -> 0.35314654 | AJ28: =AH28+10*LOG10(AB28) -> 187.8867
A29: 1999 | B29: 18.2 | C29: NQ | D29: Two-Step | E29: 0.35 | F29: A 3.3V 10b 25Msample/s two-step ADC in 0.35µm CMOS | G29: System-on-chip for video, QAM and VSB applications requires analog-to-digital converters (ADC) in state-of-the-art CMOS technology. The untrimmed ADC is realized in standard single poly 0.35 μm CMOS technology with 3.3 V supply voltage, dissipates 195 mW and measures 0.8 mm², including track-and-hold and clock-generation circuits. This ADC achieves 9.3 ENOB with an effective resolution bandwidth of 14 MHz at 16 MSample/s sample frequency. The ADC is based on a two-step architecture, which combines a high sampling rate with a limited number of comparators. This ADC operates at 3.3 V supply voltage by using a floating ladder structure, full differential dual residue signal processing with improved switching and offset-compensated residue amplifiers. Latency is kept at a minimum of 2 cycles | H29: Hendrik van der Ploeg and Robert Remmers, | I29: 10.1109/ISSCC.1999.759267 | J29: =IF(I29<>"?", HYPERLINK(CONCATENATE("https://doi.org/",I29)), "") -> https://doi.org/10.1109/ISSCC.1999.759267 | K29: Fig. 18.2.6.a shows 7.8 ENOB at fin=12.5 MHz | L29: 3.3 | P29: 0.8 | R29: 12500000 | S29: =7.8*6.02+1.76 -> 48.716 | T29: 59.6 | V29: 62.8 | W29: 72 | X29: =+IF(ISNUMBER($S29),$S29,MIN($V29,$T29,$U29,$W29)) -> 48.716 | Y29: 0.195 | Z29: 25000000 | AA29: 1 | AB29: =Z29/AA29 -> 25000000 | AD29: =Y29/AB29*1000000000000 -> 7800 | AE29: =IF(ISNUMBER($Q29), $AD29*1000/2^(($Q29-1.76)/6.02), "") | AF29: =$AD29*1000/2^(($X29-1.76)/6.02) -> 34999.403 | AG29: =IF(ISNUMBER($Q29), $Q29+10*LOG10($AB29/2/$Y29), "") | AH29: =$X29+10*LOG10($AB29/2/$Y29) -> 126.78475 | AI29: =AF29/AB29 -> 0.0013999761 | AJ29: =AH29+10*LOG10(AB29) -> 200.76415
A30: 1999 | B30: 18.3 | C30: NQ | D30: Folding | E30: 0.60 BiCMOS | F30: A 65 mW 10 b 40 Msample/s BiCMOS Nyquist ADC in 0.8 mm 2 | G30: This ADC is to be embedded in video-signal-processing ICs. Because this integration is mixed-signal, focus during architectural and circuit design is on low power, low area consumption and low substrate noise sensitivity and generation. The 10 b ADC is based on a cascaded folding and interpolating architecture. Folding and interpolating factors are optimized for low power and low area. The circuit fully exploits the available 5 V supply by means of stacked folding topologies and dimensioning is based on balancing trade-off parameters for the various devices and stages. The untrimmed ADC achieves Nyquist performance at 40 MSample/s: the input frequency, where half an effective bit is lost compared to low input frequency performance, is 20 MHz. The low input frequency performance is 9.2 effective bits. The 0.8 mm² ADC is in 7 GHz, 0.6 μm BiCMOS and dissipates 65 mW from a single 5 V supply | H30: Gian Hoogzaad and Raf Roovers | I30: 10.1109/ISSCC.1999.759268 | J30: =IF(I30<>"?", HYPERLINK(CONCATENATE("https://doi.org/",I30)), "") -> https://doi.org/10.1109/ISSCC.1999.759268 | K30: Fig. 18.3.6.a shows 8.7 ENOB at fin=20 MHz | L30: 5 | P30: 0.8 | R30: 20000000 | S30: =8.7*6.02+1.76 -> 54.134 | T30: 59 | V30: 62 | W30: 67 | X30: =+IF(ISNUMBER($S30),$S30,MIN($V30,$T30,$U30,$W30)) -> 54.134 | Y30: 0.065 | Z30: 40000000 | AA30: 1 | AB30: =Z30/AA30 -> 40000000 | AD30: =Y30/AB30*1000000000000 -> 1625 | AE30: =IF(ISNUMBER($Q30), $AD30*1000/2^(($Q30-1.76)/6.02), "") | AF30: =$AD30*1000/2^(($X30-1.76)/6.02) -> 3907.4408 | AG30: =IF(ISNUMBER($Q30), $Q30+10*LOG10($AB30/2/$Y30), "") | AH30: =$X30+10*LOG10($AB30/2/$Y30) -> 139.01517 | AI30: =AF30/AB30 -> 9.7686019e-05 | AJ30: =AH30+10*LOG10(AB30) -> 215.03577
A31: 1999 | B31: 18.4 | C31: NQ | D31: Two-Step | E31: 0.5 | F31: A 75mW 10b 20MSample/s CMOS subranging ADC with 59dB SNDR | G31: In a two-step CMOS subranging ADC (CSA), a coarse comparator bank determines which subset of fine reference taps from a resistor ladder should be passed (without amplification or subtraction from the ADC input) to a fine comparator bank by an analog multiplexer (AMUX). This CSA provides advantages over previously-reported variations of this architecture. These advantages include absolute value signal processing, an extended settling period for the fine references, a fully differential topology, and a front-end sample-and-hold amplifier (SHA). As a result of these features, this ADC achieves 9.5 ENOB Nyquist performance at 75 mW and two-clock-cycle conversion latency | H31: Brian Brandt and Joseph Lutsky | I31: 10.1109/ISSCC.1999.759270 | J31: =IF(I31<>"?", HYPERLINK(CONCATENATE("https://doi.org/",I31)), "") -> https://doi.org/10.1109/ISSCC.1999.759270 | P31: 1.6 | R31: 10000000 | S31: 58.7 | T31: 60.5 | V31: 64 | W31: 64 | X31: =+IF(ISNUMBER($S31),$S31,MIN($V31,$T31,$U31,$W31)) -> 58.7 | Y31: 0.075 | Z31: 20000000 | AA31: 1 | AB31: =Z31/AA31 -> 20000000 | AD31: =Y31/AB31*1000000000000 -> 3750 | AE31: =IF(ISNUMBER($Q31), $AD31*1000/2^(($Q31-1.76)/6.02), "") | AF31: =$AD31*1000/2^(($X31-1.76)/6.02) -> 5330.2497 | AG31: =IF(ISNUMBER($Q31), $Q31+10*LOG10($AB31/2/$Y31), "") | AH31: =$X31+10*LOG10($AB31/2/$Y31) -> 139.94939 | AI31: =AF31/AB31 -> 0.00026651249 | AJ31: =AH31+10*LOG10(AB31) -> 212.95969
A32: 1999 | B32: 18.5 | C32: NQ | D32: Flash | E32: 0.4 | F32: A CMOS 6b 500MSample/s ADC for a hard disk drive read channel | G32: High-speed A/D converters (ADCs) are essential for improving the transfer rate of hard disk drives. This CMOS 6 b 500 MSample/s full-flash ADC for a read channel has 5.5 effective number of bits (ENOB) for a 125 MHz input signal (which is one quarter of the sampling rate). The ADC occupies 2.4 mm² and power consumption is 400 mW for a 3.3 V supply. 0.4 μm CMOS technology is used | H32: Yuko Tamba and Kazuo Yamakido | I32: 10.1109/ISSCC.1999.759272 | J32: =IF(I32<>"?", HYPERLINK(CONCATENATE("https://doi.org/",I32)), "") -> https://doi.org/10.1109/ISSCC.1999.759272 | L32: 3.3 | P32: 2.4 | R32: 250000000 | S32: =5.5*6.02+1.76 -> 34.87 | X32: =+IF(ISNUMBER($S32),$S32,MIN($V32,$T32,$U32,$W32)) -> 34.87 | Y32: 0.4 | Z32: 500000000 | AA32: 1 | AB32: =Z32/AA32 -> 500000000 | AD32: =Y32/AB32*1000000000000 -> 800 | AE32: =IF(ISNUMBER($Q32), $AD32*1000/2^(($Q32-1.76)/6.02), "") | AF32: =$AD32*1000/2^(($X32-1.76)/6.02) -> 17677.67 | AG32: =IF(ISNUMBER($Q32), $Q32+10*LOG10($AB32/2/$Y32), "") | AH32: =$X32+10*LOG10($AB32/2/$Y32) -> 122.8288 | AI32: =AF32/AB32 -> 3.5355339e-05 | AJ32: =AH32+10*LOG10(AB32) -> 209.8185
A33: 1999 | B33: 18.6 | C33: NQ | D33: Flash | E33: 0.6 | F33: A 6b 500MSample/s CMOS flash ADC with a background interpolated auto-zeroing technique | G33: A 6 b 500 MSample/s Flash ADC employs interpolated auto-zeroing carried out in background mode. To improve the ADC differential nonlinearity characteristic, a resistor network with its inherent error averaging property is employed for interpolation | H33: Kwangho Yoon, Sungkyung Park, and Wonchan Kim | I33: 10.1109/ISSCC.1999.759274 | J33: =IF(I33<>"?", HYPERLINK(CONCATENATE("https://doi.org/",I33)), "") -> https://doi.org/10.1109/ISSCC.1999.759274 | P33: 5.25 | Q33: 33.2 | R33: 100000000 | S33: 27.5 | X33: =+IF(ISNUMBER($S33),$S33,MIN($V33,$T33,$U33,$W33)) -> 27.5 | Y33: 0.33 | Z33: 500000000 | AA33: 1 | AB33: =Z33/AA33 -> 500000000 | AD33: =Y33/AB33*1000000000000 -> 660 | AE33: =IF(ISNUMBER($Q33), $AD33*1000/2^(($Q33-1.76)/6.02), "") -> 17676.134 | AF33: =$AD33*1000/2^(($X33-1.76)/6.02) -> 34073.416 | AG33: =IF(ISNUMBER($Q33), $Q33+10*LOG10($AB33/2/$Y33), "") -> 121.99426 | AH33: =$X33+10*LOG10($AB33/2/$Y33) -> 116.29426 | AI33: =AF33/AB33 -> 6.8146833e-05 | AJ33: =AH33+10*LOG10(AB33) -> 203.28396
A34: 2000 | B34: 2.1 | C34: NQ | D34: Folding | E34: Bipolar | F34: A 14b 100Msample/s 3-stage A/D converter | G34: A 14b three-stage ADC uses a complementary bipolar process to achieve a 100MSample/s encode rate with a SFDR of >90 dB and an SNR of 75 dB. While the design is based on a traditional multi-stage architecture, the three encoder stages use serial-ripple converters. Unlike the typical N-bit flash converter which requires 2-N-1 comparators, the serial-ripple converter has only N comparators. The result is a smaller die area and lower power dissipation than flash. This design uses a total of 16 comparators, and at the full sample rate consumes 1250 mW. It is fabricated in a 0.8 μm double-poly complementary bipolar process | H34: Carl Moreland, Michael Elliott, Frank Murden, Joe Young, Mike Hensley, and Russ Stop | I34: 10.1109/ISSCC.2000.839679 | J34: =IF(I34<>"?", HYPERLINK(CONCATENATE("https://doi.org/",I34)), "") -> https://doi.org/10.1109/ISSCC.2000.839679 | P34: 261 | R34: 50000000 | T34: 75 | X34: =+IF(ISNUMBER($S34),$S34,MIN($V34,$T34,$U34,$W34)) -> 75 | Y34: 1.25 | Z34: 100000000 | AA34: 1 | AB34: =Z34/AA34 -> 100000000 | AD34: =Y34/AB34*1000000000000 -> 12500 | AE34: =IF(ISNUMBER($Q34), $AD34*1000/2^(($Q34-1.76)/6.02), "") | AF34: =$AD34*1000/2^(($X34-1.76)/6.02) -> 2719.8508 | AG34: =IF(ISNUMBER($Q34), $Q34+10*LOG10($AB34/2/$Y34), "") | AH34: =$X34+10*LOG10($AB34/2/$Y34) -> 151.0206 | AI34: =AF34/AB34 -> 2.7198508e-05 | AJ34: =AH34+10*LOG10(AB34) -> 231.0206
A35: 2000 | B35: 2.2 | C35: NQ | D35: Folding | E35: 0.5 | F35: A 13b 40Msample/s CMOS pipelined folding ADC with background offset trimming | G35: The folding/interpolating ADC exhibits a distinct trait attributed by folder zero-crossing error and gain mismatch, which appear in general as an INL error. It is of paramount interest to control the zero-crossings accurately so that they can be spaced evenly to cover the whole conversion range. The folder zero-crossing errors collectively result from folder offset, reference error, tail-current mismatch, interpolation error, etc. In CMOS, the poor offset of the differential pair as well as other process uncertainty have resulted in the performance much poorer than the bipolar counterpart. This CMOS folding/interpolating ADC operates with 13 b linearity at bipolar folder speed | H35: Myung-Jun Choe, Bang-Sup Song, and Kantilal Bacrania, | I35: 10.1109/ISSCC.2000.839680 | J35: =IF(I35<>"?", HYPERLINK(CONCATENATE("https://doi.org/",I35)), "") -> https://doi.org/10.1109/ISSCC.2000.839680 | P35: 8.7 | R35: 20000000 | T35: 66 | W35: 82 | X35: =+IF(ISNUMBER($S35),$S35,MIN($V35,$T35,$U35,$W35)) -> 66 | Y35: 0.8 | Z35: 40000000 | AA35: 1 | AB35: =Z35/AA35 -> 40000000 | AD35: =Y35/AB35*1000000000000 -> 20000 | AE35: =IF(ISNUMBER($Q35), $AD35*1000/2^(($Q35-1.76)/6.02), "") | AF35: =$AD35*1000/2^(($X35-1.76)/6.02) -> 12266.196 | AG35: =IF(ISNUMBER($Q35), $Q35+10*LOG10($AB35/2/$Y35), "") | AH35: =$X35+10*LOG10($AB35/2/$Y35) -> 139.9794 | AI35: =AF35/AB35 -> 0.00030665491 | AJ35: =AH35+10*LOG10(AB35) -> 216
A36: 2000 | B36: 2.3 | C36: NQ | D36: Pipe | E36: 0.5 | F36: A 12b 65Msample/s CMOS ADC with 82dB SFDR at 120MHz | G36: A recent trend in cellular basestation design is to digitize multiple channels with a single ADC, often at the intermediate frequency (IF). This requires an ADC with wide dynamic range, particularly SFDR above 80 dB and SNR better than 70 dB, even when sampling input frequencies above 70 MHz. This 12b, 65MSample/s (MSPS) ADC incorporates a wide-bandwidth, low-distortion input stage coupled with a digitally-calibrated, multibit pipeline architecture optimized for low power consumption | H36: Larry Singer, Stacy Ho, Mike Timko, and Dan Kelly | I36: 10.1109/ISSCC.2000.839681 | J36: =IF(I36<>"?", HYPERLINK(CONCATENATE("https://doi.org/",I36)), "") -> https://doi.org/10.1109/ISSCC.2000.839681 | P36: 10 | R36: 32500000 | S36: 70 | T36: 70 | X36: =+IF(ISNUMBER($S36),$S36,MIN($V36,$T36,$U36,$W36)) -> 70 | Y36: 0.43 | Z36: 65000000 | AA36: 1 | AB36: =Z36/AA36 -> 65000000 | AD36: =Y36/AB36*1000000000000 -> 6615.3846 | AE36: =IF(ISNUMBER($Q36), $AD36*1000/2^(($Q36-1.76)/6.02), "") | AF36: =$AD36*1000/2^(($X36-1.76)/6.02) -> 2559.8533 | AG36: =IF(ISNUMBER($Q36), $Q36+10*LOG10($AB36/2/$Y36), "") | AH36: =$X36+10*LOG10($AB36/2/$Y36) -> 148.78415 | AI36: =AF36/AB36 -> 3.9382359e-05 | AJ36: =AH36+10*LOG10(AB36) -> 226.91328
A37: 2000 | B37: 2.4 | C37: NQ | D37: Folding | E37: 0.6 | F37: A 3.3V, 12b, 50Msample/s A/D converter in 0.6µm CMOS with over 80dB SFDR | G37: Modern wireless base stations digitize the entire received frequency band, and separate individual channels with digital filters. This requires an A/D converter (ADC) with an effective resolution bandwidth of 20 MHz or more, and a spurious-free dynamic range (SFDR) greater than 85 dB to avoid confusion of a weak received channel with spurious tones. To date, only bipolar ADCs have met these specifications. This high-SFDR wideband ADC implemented in 0.6 μm CMOS on a 3M1P epi substrate requires no trimming, calibration or dithering | H37: Hui Pan, Masahiro Segami, Michael Choi, Jing Cao, Fumitoshi Hatori, and Asad Abidi | I37: 10.1109/ISSCC.2000.839682 | J37: =IF(I37<>"?", HYPERLINK(CONCATENATE("https://doi.org/",I37)), "") -> https://doi.org/10.1109/ISSCC.2000.839682 | P37: 16 | R37: 25000000 | S37: 64 | W37: 82 | X37: =+IF(ISNUMBER($S37),$S37,MIN($V37,$T37,$U37,$W37)) -> 64 | Y37: 0.85 | Z37: 50000000 | AA37: 1 | AB37: =Z37/AA37 -> 50000000 | AD37: =Y37/AB37*1000000000000 -> 17000 | AE37: =IF(ISNUMBER($Q37), $AD37*1000/2^(($Q37-1.76)/6.02), "") | AF37: =$AD37*1000/2^(($X37-1.76)/6.02) -> 13126.193 | AG37: =IF(ISNUMBER($Q37), $Q37+10*LOG10($AB37/2/$Y37), "") | AH37: =$X37+10*LOG10($AB37/2/$Y37) -> 138.68521 | AI37: =AF37/AB37 -> 0.00026252387 | AJ37: =AH37+10*LOG10(AB37) -> 215.67491
A38: 2000 | B38: 2.5 | C38: NQ | D38: Pipe | E38: 0.5 | F38: An 8b 80Msample/s pipelined ADC with background calibration | G38: Conventional pipelined ADCs with redundancy and digital correction have linearity limited by the gain accuracy of the interstage amplifiers or the linearity of the D/A subconversions. With a fully differential 1.5 b/stage architecture, the D/A subconverters can in principle be inherently linear, and the main limitation stems from the interstage gain accuracy. Besides the error caused by finite-op-amp gain and capacitor mismatch, the linear portion of the incomplete op-amp settling can also be modeled as an interstage gain error. One way to compensate for interstage gain errors is to adjust the reference voltage from each stage to the next so that the ratio of the reference in one stage to the corresponding value in the previous stage is equal to 1+&epsi;, where &epsi; is the gain error between the stages. This pipelined ADC uses monolithic calibration to adjust the reference voltages of the first two stages in the background during normal ADC operation to compensate for gain errors in the first two interstage amplifiers. Calibration is potentially useful even at an 8b level because it allows the use of small capacitors and low op-amp gain, reducing power dissipation and the minimum required supply voltage and increasing the maximum speed in a given technology. The key contributions here are the use of background calibration to improve the linearity of a pipelined ADC and the implementation of these techniques with the ADC on one CMOS IC | H38: Jun Ming and Stephen H. Lewis | I38: 10.1109/ISSCC.2000.839683 | J38: =IF(I38<>"?", HYPERLINK(CONCATENATE("https://doi.org/",I38)), "") -> https://doi.org/10.1109/ISSCC.2000.839683 | P38: 10.3 | R38: 40000000 | S38: 44.3 | V38: 54.9 | W38: 59.3 | X38: =+IF(ISNUMBER($S38),$S38,MIN($V38,$T38,$U38,$W38)) -> 44.3 | Y38: 0.25 | Z38: 80000000 | AA38: 1 | AB38: =Z38/AA38 -> 80000000 | AD38: =Y38/AB38*1000000000000 -> 3125 | AE38: =IF(ISNUMBER($Q38), $AD38*1000/2^(($Q38-1.76)/6.02), "") | AF38: =$AD38*1000/2^(($X38-1.76)/6.02) -> 23315.142 | AG38: =IF(ISNUMBER($Q38), $Q38+10*LOG10($AB38/2/$Y38), "") | AH38: =$X38+10*LOG10($AB38/2/$Y38) -> 126.3412 | AI38: =AF38/AB38 -> 0.00029143927 | AJ38: =AH38+10*LOG10(AB38) -> 205.3721
A39: 2000 | B39: 2.7 | C39: NQ | D39: Pipe | E39: 0.5 | F39: A 14b 20MSample/s CMOS pipelined ADC | G39: The performance of high-resolution pipelined ADCs is limited by the residue amplifier gain and settling accuracy. In typical implementations, error sources are capacitor ratio mismatch, op-amp gain, and residue settling. All these affect ADC performance adversely, specifically in high-speed ADCs. Capacitor matching improves as capacitor size increases, but the trend is towards shrinking capacitor size for high-speed conversion. Many innovations to overcome this such as ratio-independent techniques are reported. Among them, capacitor error-averaging offers an advantage of achieving both INL and DNL improvements over that achievable by capacitor matching, but it requires three clock phases-one extra clock phase for averaging capacitor errors. In this work, the one extra clock phase is used advantageously for comparison | H39: Hsin-Shu Chen, Kantilal Bacrania, and Bang-Sup Song | I39: 10.1109/ISSCC.2000.839685 | J39: =IF(I39<>"?", HYPERLINK(CONCATENATE("https://doi.org/",I39)), "") -> https://doi.org/10.1109/ISSCC.2000.839685 | P39: 10.8 | R39: 10000000 | T39: 73.1 | U39: 83.1 | V39: 80.3 | X39: =+IF(ISNUMBER($S39),$S39,MIN($V39,$T39,$U39,$W39)) -> 73.1 | Y39: 0.72 | Z39: 20000000 | AA39: 1 | AB39: =Z39/AA39 -> 20000000 | AD39: =Y39/AB39*1000000000000 -> 36000 | AE39: =IF(ISNUMBER($Q39), $AD39*1000/2^(($Q39-1.76)/6.02), "") | AF39: =$AD39*1000/2^(($X39-1.76)/6.02) -> 9748.7074 | AG39: =IF(ISNUMBER($Q39), $Q39+10*LOG10($AB39/2/$Y39), "") | AH39: =$X39+10*LOG10($AB39/2/$Y39) -> 144.52668 | AI39: =AF39/AB39 -> 0.00048743537 | AJ39: =AH39+10*LOG10(AB39) -> 217.53697
A40: 2000 | B40: 20.2 | C40: OS | D40: SDSC | E40: 0.65 | F40: A 2.5 MSample/s multi-bit ΔΣ CMOS ADC with 95 dB SNR | G40: ΔΣ A/D converters combine high resolution and high speed. A significant improvement in performance is achieved by employing a multi-bit quantizer. However, the linearity requirements for the DAC in the feedback loop are severe. To relax these requirements, dynamic element matching (DEM) techniques such as data weighted averaging (DWA) are used, converting noise and distortion introduced by the non-ideal DAC into a noise shaped error. These DEM techniques require an additional digital block in the feedback loop of the converter to scramble the used unity elements in each clock period. The delay introduced in the feedback loop by this block imposes a limit on the maximum clock frequency of the converter. Here, implementation of the DWA algorithm is optimized for high-speed converters, resulting in a 2.5MSample/s 16b A/D converter in a 0.65 μm CMOS technology operating at 60 MHz clock speed | H40: Geerts, Y.; Steyaert, M.; Sansen, W. | I40: 10.1109/ISSCC.2000.839805 | J40: =IF(I40<>"?", HYPERLINK(CONCATENATE("https://doi.org/",I40)), "") -> https://doi.org/10.1109/ISSCC.2000.839805 | P40: 5.3436 | R40: 1250000 | S40: 89 | T40: 95 | U40: 97 | V40: 97 | X40: =+IF(ISNUMBER($S40),$S40,MIN($V40,$T40,$U40,$W40)) -> 89 | Y40: 0.295 | Z40: 60000000 | AA40: 24 | AB40: =Z40/AA40 -> 2500000 | AD40: =Y40/AB40*1000000000000 -> 118000 | AE40: =IF(ISNUMBER($Q40), $AD40*1000/2^(($Q40-1.76)/6.02), "") | AF40: =$AD40*1000/2^(($X40-1.76)/6.02) -> 5122.0913 | AG40: =IF(ISNUMBER($Q40), $Q40+10*LOG10($AB40/2/$Y40), "") | AH40: =$X40+10*LOG10($AB40/2/$Y40) -> 155.27088 | AI40: =AF40/AB40 -> 0.0020488365 | AJ40: =AH40+10*LOG10(AB40) -> 219.25028
A41: 2000 | B41: 20.3 | C41: OS | D41: SDSC | E41: 0.5 | F41: A 90 dB SNR, 2.5 MHz output rate ADC using cascaded multibit ΔΣ modulation at 8x oversampling ratio | G41: This 16b, 2.5 MHz output rate ADC is intended for xDSL and high-speed instrumentation applications. A fourth-order cascaded ΔΣ modulator (ΔΣM) operating at 20 MHz employs multibit quantization and dynamic element matching (DEM) to make all quantization noise contributions negligible at an oversampling ratio (OSR) of eight. The ADC achieves 90 dB signal-to-noise ratio (SNR) in a 1.25 MHz bandwidth, and 102 dB spurious free dynamic range (SFDR) with 270 mW dissipation | H41: Fujimori, I.; Longo, L.; Hairapetian, A.; Seiyama, K.; Kosic, S.; Cao, J.; Shu-Iap Chan | I41: 10.1109/ISSCC.2000.839806 | J41: =IF(I41<>"?", HYPERLINK(CONCATENATE("https://doi.org/",I41)), "") -> https://doi.org/10.1109/ISSCC.2000.839806 | P41: 26.24 | R41: 1250000 | S41: 84 | T41: 90 | U41: 90 | W41: 102 | X41: =+IF(ISNUMBER($S41),$S41,MIN($V41,$T41,$U41,$W41)) -> 84 | Y41: 0.27 | Z41: 20000000 | AA41: 8 | AB41: =Z41/AA41 -> 2500000 | AD41: =Y41/AB41*1000000000000 -> 108000 | AE41: =IF(ISNUMBER($Q41), $AD41*1000/2^(($Q41-1.76)/6.02), "") | AF41: =$AD41*1000/2^(($X41-1.76)/6.02) -> 8337.0802 | AG41: =IF(ISNUMBER($Q41), $Q41+10*LOG10($AB41/2/$Y41), "") | AH41: =$X41+10*LOG10($AB41/2/$Y41) -> 150.65546 | AI41: =AF41/AB41 -> 0.0033348321 | AJ41: =AH41+10*LOG10(AB41) -> 214.63486
A42: 2000 | B42: 20.4 | C42: OS | D42: SDCT, BP | E42: 0.35 | F42: A 10.7 MHz IF-to-baseband ΣΔ A/D conversion system for AM/FM radio receivers | G42: This analog-to-digital converter digitizes a radio signal at a 10.7 MHz intermediate frequency (IF) using integrated quadrature mixing and ΣΔ modulation. The paper shows a block diagram of a highly-integrated AM/FM radio receiver. The IF A/D conversion and digital filtering, demodulation and further signal processing can be integrated on a single CMOS IC. The radio front-end mixes both AM and FM signals to 10.7 MHz IF, so that the A/D conversion is shared. A single channel filter is used, selecting one 200 kHz FM channel. For AM, over 20 channels pass through this filter, resulting in high dynamic range of the IF signal. When the radio is tuned to a weak AM radio station, strong neighboring channels should not introduce disturbance of the weak signal. This multi-channel aspect for AM puts severe requirements on the automatic gain control (AGC) amplifier and A/D converter in terms of noise, intermodulation and crossmodulation distortion | H42: van der Zwan, E.; Philips, K.; Bastiaansen, C. | I42: 10.1109/ISSCC.2000.839807 | J42: =IF(I42<>"?", HYPERLINK(CONCATENATE("https://doi.org/",I42)), "") -> https://doi.org/10.1109/ISSCC.2000.839807 | P42: 0.6 | R42: 200000 | T42: 77 | U42: 80 | X42: =+IF(ISNUMBER($S42),$S42,MIN($V42,$T42,$U42,$W42)) -> 77 | Y42: 0.01 | Z42: 21070000 | AA42: 52.675 | AB42: =Z42/AA42 -> 400000 | AC42: 10700000 | AD42: =Y42/AB42*1000000000000 -> 25000 | AE42: =IF(ISNUMBER($Q42), $AD42*1000/2^(($Q42-1.76)/6.02), "") | AF42: =$AD42*1000/2^(($X42-1.76)/6.02) -> 4320.8094 | AG42: =IF(ISNUMBER($Q42), $Q42+10*LOG10($AB42/2/$Y42), "") | AH42: =$X42+10*LOG10($AB42/2/$Y42) -> 150.0103 | AI42: =AF42/AB42 -> 0.010802024 | AJ42: =AH42+10*LOG10(AB42) -> 206.0309
A43: 2000 | B43: 20.5 | C43: OS | D43: SDSC, BP | E43: 0.25 | F43: A two-path bandpass ΣΔ modulator with extended noise shaping | G43: The proliferation of communications applications stimulates interest in digitizing bandpass signals with bandwidths of several MHz at intermediate frequencies above 10 MHz. This multistage oversampling modulator combines lowpass and bandpass stages to achieve an extended dynamic range at low oversampling ratios. An experimental prototype of the architecture integrated in 0.25 μm CMOS achieves 75 dB dynamic range for 2 MHz signal bandwidth at 16 MHz IF | H43: Tabatabaei, A.; Kaviani, K.; Wooley, B. | I43: 10.1109/ISSCC.2000.839808 | J43: =IF(I43<>"?", HYPERLINK(CONCATENATE("https://doi.org/",I43)), "") -> https://doi.org/10.1109/ISSCC.2000.839808 | P43: 2.8 | R43: 2000000 | S43: 70 | U43: 75 | X43: =+IF(ISNUMBER($S43),$S43,MIN($V43,$T43,$U43,$W43)) -> 70 | Y43: 0.11 | Z43: 64000000 | AA43: 16 | AB43: =Z43/AA43 -> 4000000 | AC43: 16000000 | AD43: =Y43/AB43*1000000000000 -> 27500 | AE43: =IF(ISNUMBER($Q43), $AD43*1000/2^(($Q43-1.76)/6.02), "") | AF43: =$AD43*1000/2^(($X43-1.76)/6.02) -> 10641.251 | AG43: =IF(ISNUMBER($Q43), $Q43+10*LOG10($AB43/2/$Y43), "") | AH43: =$X43+10*LOG10($AB43/2/$Y43) -> 142.59637 | AI43: =AF43/AB43 -> 0.0026603127 | AJ43: =AH43+10*LOG10(AB43) -> 208.61697
A44: 2001 | B44: 3.1 | C44: OS | D44: SDSC | E44: 0.25 | F44: A 13.5mW, 185 MSample/s ΔΣ-modulator for UMTS/GSM dual-standard IF reception | G44: To accommodate drastically different symbol rates, signal bandwidth and SNR requirements between WCDMA and GSM, the IF frequency, sample-rate and converter architecture are optimized for a dual-standard ΣΔ modulator. In the system and circuit design, attention is given to low power consumption to achieve 13.5 mW at 18 MSample/s. Measured dynamic range is 53 dB for WCDMA and 84 dB for GSM | H44: Burger, T.; Qiuting Hueng | I44: 10.1109/ISSCC.2001.912538 | J44: =IF(I44<>"?", HYPERLINK(CONCATENATE("https://doi.org/",I44)), "") -> https://doi.org/10.1109/ISSCC.2001.912538 | K44: Data for WCDMA | P44: 0.36 | R44: 5000000 | S44: 51 | T44: 52 | U44: 53 | V44: 58 | X44: =+IF(ISNUMBER($S44),$S44,MIN($V44,$T44,$U44,$W44)) -> 51 | Y44: 0.0135 | Z44: 138240000 | AA44: 13.824 | AB44: =Z44/AA44 -> 10000000 | AD44: =Y44/AB44*1000000000000 -> 1350 | AE44: =IF(ISNUMBER($Q44), $AD44*1000/2^(($Q44-1.76)/6.02), "") | AF44: =$AD44*1000/2^(($X44-1.76)/6.02) -> 4656.809 | AG44: =IF(ISNUMBER($Q44), $Q44+10*LOG10($AB44/2/$Y44), "") | AH44: =$X44+10*LOG10($AB44/2/$Y44) -> 136.68636 | AI44: =AF44/AB44 -> 0.0004656809 | AJ44: =AH44+10*LOG10(AB44) -> 206.68636
A45: 2001 | B45: 3.2 | C45: OS | D45: SDSC | E45: 0.35 BiCMOS | F45: A 5 mW ΣΔ modulator with 84 dB dynamic range for GSM/EDGE | G45: A ΣΔ modulator in 0.35 μm technology for GSM/EDGE applications has 13 MHz clock. Frequency is 13 MHz. The modulator achieves 84 dB dynamic range and 82 dB peak SNDR over 180 kHz bandwidth. Power dissipation is 5 mW from 1.8/2.4 V supplies. Active area is 0.4 mm 2 | H45: Oliaei, O.; Clement, P.; Gorisse, P. | I45: 10.1109/ISSCC.2001.912539 | J45: =IF(I45<>"?", HYPERLINK(CONCATENATE("https://doi.org/",I45)), "") -> https://doi.org/10.1109/ISSCC.2001.912539 | P45: 0.4 | R45: 189000 | S45: 84 | U45: 84 | X45: =+IF(ISNUMBER($S45),$S45,MIN($V45,$T45,$U45,$W45)) -> 84 | Y45: 0.005 | Z45: 13000000 | AA45: 34.391534 | AB45: =Z45/AA45 -> 378000 | AD45: =Y45/AB45*1000000000000 -> 13227.513 | AE45: =IF(ISNUMBER($Q45), $AD45*1000/2^(($Q45-1.76)/6.02), "") | AF45: =$AD45*1000/2^(($X45-1.76)/6.02) -> 1021.1004 | AG45: =IF(ISNUMBER($Q45), $Q45+10*LOG10($AB45/2/$Y45), "") | AH45: =$X45+10*LOG10($AB45/2/$Y45) -> 159.77492 | AI45: =AF45/AB45 -> 0.0027013237 | AJ45: =AH45+10*LOG10(AB45) -> 215.54984
A46: 2001 | B46: 3.4 | C46: OS | D46: SDSC | E46: 0.5 | F46: A 2.5 V broadband multi-bit ΣΔ modulator with 95 dB dynamic range | G46: A cascaded multi-bit ΣΔ modulator uses double sampling to achieve a conversion rate of at least 4 MSample/s at an oversampling ratio of 16. Partitioned data-weighted averaging extends the dynamic range to 95 dB. The circuit, integrated in 0.5 μm CMOS, dissipates 150 mW from a 2.5 V supply | H46: Vleugels, K.; Rabii, S.; Wooley, B.A. | I46: 10.1109/ISSCC.2001.912541 | J46: =IF(I46<>"?", HYPERLINK(CONCATENATE("https://doi.org/",I46)), "") -> https://doi.org/10.1109/ISSCC.2001.912541 | L46: 2.5 | R46: 2000000 | S46: 87 | T46: 90 | U46: 95 | X46: =+IF(ISNUMBER($S46),$S46,MIN($V46,$T46,$U46,$W46)) -> 87 | Y46: 0.15 | Z46: 64000000 | AA46: 16 | AB46: =Z46/AA46 -> 4000000 | AD46: =Y46/AB46*1000000000000 -> 37500 | AE46: =IF(ISNUMBER($Q46), $AD46*1000/2^(($Q46-1.76)/6.02), "") | AF46: =$AD46*1000/2^(($X46-1.76)/6.02) -> 2049.3047 | AG46: =IF(ISNUMBER($Q46), $Q46+10*LOG10($AB46/2/$Y46), "") | AH46: =$X46+10*LOG10($AB46/2/$Y46) -> 158.24939 | AI46: =AF46/AB46 -> 0.00051232619 | AJ46: =AH46+10*LOG10(AB46) -> 224.26999
A47: 2001 | B47: 8.1 | C47: NQ | D47: Flash | E47: 0.35 | F47: A 6b 1.3Gsample/s A/D converter in 0.35µm CMOS | G47: Using array averaging and a wideband track-and-hold, a 6 b flash ADC achieves better than 5.5 effective bits for input frequencies to 600 MHz at 1 GSample/s, and 5 effective bits for 650 MHz input at 1.3 GSample/s. It consumes 500 mW from 3.3 V and occupies 0.8 mm² in 0.35 μm CMOS | H47: Michael Choi and Asad A. Abidi, | I47: 10.1109/ISSCC.2001.912571 | J47: =IF(I47<>"?", HYPERLINK(CONCATENATE("https://doi.org/",I47)), "") -> https://doi.org/10.1109/ISSCC.2001.912571 | P47: 0.8 | R47: 650000000 | S47: 35 | W47: 44 | X47: =+IF(ISNUMBER($S47),$S47,MIN($V47,$T47,$U47,$W47)) -> 35 | Y47: 0.545 | Z47: 1300000000 | AA47: 1 | AB47: =Z47/AA47 -> 1300000000 | AD47: =Y47/AB47*1000000000000 -> 419.23077 | AE47: =IF(ISNUMBER($Q47), $AD47*1000/2^(($Q47-1.76)/6.02), "") | AF47: =$AD47*1000/2^(($X47-1.76)/6.02) -> 9126.1484 | AG47: =IF(ISNUMBER($Q47), $Q47+10*LOG10($AB47/2/$Y47), "") | AH47: =$X47+10*LOG10($AB47/2/$Y47) -> 125.76517 | AI47: =AF47/AB47 -> 7.0201141e-06 | AJ47: =AH47+10*LOG10(AB47) -> 216.9046
A48: 2001 | B48: 8.2 | C48: NQ | D48: Flash | E48: 0.35 | F48: A 6b 1.1Gsample/s CMOS A/D converter | G48: High-speed ADCs are key elements in the read channel of optical and magnetic data storage systems. The required resolution is about 6 b while the sampling rate (Fs) and effective resolution bandwidth (ERBW) requirements increase with each generation of storage system. Sample rates up to 800 MSample/s have been reported with ERBW=200 MHz. The ADC presented here achieves a maximum sample rate of 1.1 GSample/s and an EBBW of 450 MHz. This result is obtained with full flash interpolating/averaging architecture with distributed track-and-hold (T/H) in a standard 0.35 μm single-poly five-metal 3.3 V digital CMOS process. Chip area is 0.35 mm² and power consumption is 300 mW | H48: Govert Geelen | I48: 10.1109/ISSCC.2001.912572 | J48: =IF(I48<>"?", HYPERLINK(CONCATENATE("https://doi.org/",I48)), "") -> https://doi.org/10.1109/ISSCC.2001.912572 | P48: 0.35 | R48: 550000000 | S48: =5.65*6.02+1.76 -> 35.773 | X48: =+IF(ISNUMBER($S48),$S48,MIN($V48,$T48,$U48,$W48)) -> 35.773 | Y48: 0.3 | Z48: 1100000000 | AA48: 1 | AB48: =Z48/AA48 -> 1100000000 | AD48: =Y48/AB48*1000000000000 -> 272.72727 | AE48: =IF(ISNUMBER($Q48), $AD48*1000/2^(($Q48-1.76)/6.02), "") | AF48: =$AD48*1000/2^(($X48-1.76)/6.02) -> 5431.3663 | AG48: =IF(ISNUMBER($Q48), $Q48+10*LOG10($AB48/2/$Y48), "") | AH48: =$X48+10*LOG10($AB48/2/$Y48) -> 128.40541 | AI48: =AF48/AB48 -> 4.9376057e-06 | AJ48: =AH48+10*LOG10(AB48) -> 218.81934
A49: 2001 | B49: 8.3 | C49: NQ | D49: Pipe | E49: 0.18 | F49: A 10b 100Msample/s CMOS pipelined ADC with 1.8V power supply | G49: A 100 MHz ADC for low-power applications uses a 0.18 μm digital CMOS process. The design achieves 9.4 ENOB for a 50 MHz input at full sampling rate, and consumes a total of 180 mW with 2.5 mm² core in a single 1.8 V power supply | H49: Yong-In Park, S. Karthikeyan, Frank Tsay, and Eduardo Bartolome | I49: 10.1109/ISSCC.2001.912573 | J49: =IF(I49<>"?", HYPERLINK(CONCATENATE("https://doi.org/",I49)), "") -> https://doi.org/10.1109/ISSCC.2001.912573 | L49: 1.8 | P49: 2.5 | R49: 50000000 | S49: 57.12 | T49: 58.39 | W49: 63.95 | X49: =+IF(ISNUMBER($S49),$S49,MIN($V49,$T49,$U49,$W49)) -> 57.12 | Y49: 0.18 | Z49: 100000000 | AA49: 1 | AB49: =Z49/AA49 -> 100000000 | AD49: =Y49/AB49*1000000000000 -> 1800 | AE49: =IF(ISNUMBER($Q49), $AD49*1000/2^(($Q49-1.76)/6.02), "") | AF49: =$AD49*1000/2^(($X49-1.76)/6.02) -> 3068.9984 | AG49: =IF(ISNUMBER($Q49), $Q49+10*LOG10($AB49/2/$Y49), "") | AH49: =$X49+10*LOG10($AB49/2/$Y49) -> 141.55697 | AI49: =AF49/AB49 -> 3.0689984e-05 | AJ49: =AH49+10*LOG10(AB49) -> 221.55697
A50: 2001 | B50: 8.4 | C50: NQ | D50: Two-Step | E50: 0.25 | F50: A 2.5V 12b 54 Msample/s 0.25 µm CMOS ADC in 1 mm² | G50: Background digital offset extraction and analog compensation remove offset of the critical analog components. The calibrated two-step ADC achieves -70 dB THD in the Nyquist band with a 2.5 V supply. The ADC in 0.25 μm CMOS measures 1.0 mm² and dissipates 295 mW | H50: Hendrik van der Ploeg, Gian Hoogzaad, Henk A. H. Termeer, Maarten Vertregt, and Raf L. J. Roovers, | I50: 10.1109/ISSCC.2001.912574 | J50: =IF(I50<>"?", HYPERLINK(CONCATENATE("https://doi.org/",I50)), "") -> https://doi.org/10.1109/ISSCC.2001.912574 | K50: SNDR estimated assuming equal contribution of distortion and thermal noise | L50: 2.5 | P50: 1 | R50: 27000000 | S50: 67 | V50: 70 | X50: =+IF(ISNUMBER($S50),$S50,MIN($V50,$T50,$U50,$W50)) -> 67 | Y50: 0.295 | Z50: 54000000 | AA50: 1 | AB50: =Z50/AA50 -> 54000000 | AD50: =Y50/AB50*1000000000000 -> 5462.963 | AE50: =IF(ISNUMBER($Q50), $AD50*1000/2^(($Q50-1.76)/6.02), "") | AF50: =$AD50*1000/2^(($X50-1.76)/6.02) -> 2986.092 | AG50: =IF(ISNUMBER($Q50), $Q50+10*LOG10($AB50/2/$Y50), "") | AH50: =$X50+10*LOG10($AB50/2/$Y50) -> 146.61542 | AI50: =AF50/AB50 -> 5.5298e-05 | AJ50: =AH50+10*LOG10(AB50) -> 223.93936
A51: 2001 | B51: 8.5 | C51: NQ | D51: Pipe | E51: 0.35 | F51: A 3V 340mW 14b 75MSPS CMOS ADC with 85dB SFDR at Nyquist | G51: A 14 b multi-bit ADC with a switched-capacitor pipeline architecture achieves 0.6 LSB DNL and 2 LSB INL without calibration. Typical SNR is 73 dB, while SFDR is >85 dB for input frequency up to Nyquist. The 7.8 mm² ADC in 0.35 μm double-poly triple-metal process operates with a 2.7 V to 3.6 V power supply, and consumes 340 mW at 3 V | H51: Dan Kelly, Will Yang, Iuri Mehr, Mark Sayuk, and Larry Singer, | I51: 10.1109/ISSCC.2001.912575 | J51: =IF(I51<>"?", HYPERLINK(CONCATENATE("https://doi.org/",I51)), "") -> https://doi.org/10.1109/ISSCC.2001.912575 | L51: 3 | P51: 7.8 | R51: 37500000 | S51: 72.8 | W51: 86 | X51: =+IF(ISNUMBER($S51),$S51,MIN($V51,$T51,$U51,$W51)) -> 72.8 | Y51: 0.318 | Z51: 75000000 | AA51: 1 | AB51: =Z51/AA51 -> 75000000 | AD51: =Y51/AB51*1000000000000 -> 4240 | AE51: =IF(ISNUMBER($Q51), $AD51*1000/2^(($Q51-1.76)/6.02), "") | AF51: =$AD51*1000/2^(($X51-1.76)/6.02) -> 1188.5348 | AG51: =IF(ISNUMBER($Q51), $Q51+10*LOG10($AB51/2/$Y51), "") | AH51: =$X51+10*LOG10($AB51/2/$Y51) -> 153.51604 | AI51: =AF51/AB51 -> 1.584713e-05 | AJ51: =AH51+10*LOG10(AB51) -> 232.26665
A52: 2001 | B52: 8.6 | C52: NQ | D52: Pipe | E52: 0.60 BiCMOS | F52: A 14b 40 Msample/s pipelined ADC with DFCA | G52: A DAC and feedback capacitor averaging (DFCA) technique used in a pipelined ADC achieves 84 dB SFDR and 74 dB SNR. Also external mismatch noise cancellation digitally improves the SNR. Excluding output drivers, the 0.6 μm double-poly BiCMOS ADC dissipates 860 mW from 3.3 V supply | H52: Yu, P.C.; Shehata, S.; Joharapurkar, A.; Chugh, P.; Bugeja, A.R.; Xiaohong Du; Sung-Ung Kwak; Papantonopoulous, Y.; Kuyel, T. | I52: 10.1109/ISSCC.2001.912576 | J52: =IF(I52<>"?", HYPERLINK(CONCATENATE("https://doi.org/",I52)), "") -> https://doi.org/10.1109/ISSCC.2001.912576 | L52: 3.3 | P52: 31.35 | R52: 20000000 | T52: 74 | W52: 84 | X52: =+IF(ISNUMBER($S52),$S52,MIN($V52,$T52,$U52,$W52)) -> 74 | Y52: 0.86 | Z52: 40000000 | AA52: 1 | AB52: =Z52/AA52 -> 40000000 | AD52: =Y52/AB52*1000000000000 -> 21500 | AE52: =IF(ISNUMBER($Q52), $AD52*1000/2^(($Q52-1.76)/6.02), "") | AF52: =$AD52*1000/2^(($X52-1.76)/6.02) -> 5249.0234 | AG52: =IF(ISNUMBER($Q52), $Q52+10*LOG10($AB52/2/$Y52), "") | AH52: =$X52+10*LOG10($AB52/2/$Y52) -> 147.66532 | AI52: =AF52/AB52 -> 0.00013122559 | AJ52: =AH52+10*LOG10(AB52) -> 223.68592
A53: 2002 | B53: 10.1 | C53: NQ | D53: Pipe, TI | E53: 0.35 | F53: A 4GSample/s 8b ADC in 0.35µm CMOS | G53: A 4 Gsample/s 8b ADC in 0.35 µm CMOS achieves accuracy of 7 effective bits at DC and 6.1 effective bits for 1 GHz input, while dissipating 4.6 W. It uses 32 current-mode pipelines driven by 32 interleaved clocks with 1.1 ps RMS accuracy | H53: Ken Poulton, Robert Neff, Art Muto, Wei Liu, Andy Burstein, and Mehrdad Heshami | I53: 10.1109/ISSCC.2002.992988 | J53: =IF(I53<>"?", HYPERLINK(CONCATENATE("https://doi.org/",I53)), "") -> https://doi.org/10.1109/ISSCC.2002.992988 | P53: 28.8456 | Q53: =7*6.02+1.76 -> 43.9 | R53: 1000000000 | S53: =6.02*6.2+1.76 -> 39.084 | X53: =+IF(ISNUMBER($S53),$S53,MIN($V53,$T53,$U53,$W53)) -> 39.084 | Y53: 4.6 | Z53: 4000000000 | AA53: 1 | AB53: =Z53/AA53 -> 4000000000 | AD53: =Y53/AB53*1000000000000 -> 1150 | AE53: =IF(ISNUMBER($Q53), $AD53*1000/2^(($Q53-1.76)/6.02), "") -> 8984.375 | AF53: =$AD53*1000/2^(($X53-1.76)/6.02) -> 15642.705 | AG53: =IF(ISNUMBER($Q53), $Q53+10*LOG10($AB53/2/$Y53), "") -> 130.28272 | AH53: =$X53+10*LOG10($AB53/2/$Y53) -> 125.46672 | AI53: =AF53/AB53 -> 3.9106764e-06 | AJ53: =AH53+10*LOG10(AB53) -> 221.48732
A54: 2002 | B54: 10.2 | C54: NQ | D54: Flash | E54: 0.18 | F54: A 6b 1.6GSample/s flash ADC in 0.18µm CMOS Using averaging termination | G54: A 1.6 Gsample/s 6b flash analog-to-digital converter in 0.18 µm CMOS is for storage read channels. The array of amplifiers and averaging resistors is terminated with less overrange while maintaining full-scale linearity. Consuming 340 mW, it achieves 5.7 | H54: Peter Scholtens and Maarten Vertregt, | I54: 10.1109/ISSCC.2002.992989 | J54: =IF(I54<>"?", HYPERLINK(CONCATENATE("https://doi.org/",I54)), "") -> https://doi.org/10.1109/ISSCC.2002.992989 | P54: 0.12 | R54: 660000000 | S54: =5*6.02+1.76 -> 31.86 | X54: =+IF(ISNUMBER($S54),$S54,MIN($V54,$T54,$U54,$W54)) -> 31.86 | Y54: 0.34 | Z54: 1600000000 | AA54: 1.2121212 | AB54: =Z54/AA54 -> 1320000000 | AD54: =Y54/AB54*1000000000000 -> 257.57576 | AE54: =IF(ISNUMBER($Q54), $AD54*1000/2^(($Q54-1.76)/6.02), "") | AF54: =$AD54*1000/2^(($X54-1.76)/6.02) -> 8049.2424 | AG54: =IF(ISNUMBER($Q54), $Q54+10*LOG10($AB54/2/$Y54), "") | AH54: =$X54+10*LOG10($AB54/2/$Y54) -> 124.74065 | AI54: =AF54/AB54 -> 6.0979109e-06 | AJ54: =AH54+10*LOG10(AB54) -> 215.94639
A55: 2002 | B55: 10.3 | C55: NQ | D55: Folding | E55: 0.18 | F55: A 7b 450MSample/s 50mW CMOS ADC in 0.3mm² | G55: A 7b 450MSample/s CMOS ADC in 0.18µm technology is used for the embedded digital read channel system in DVD SOC. A dynamic comparator and an interpolation circuit composed of gate-width-weighted transistors consumes 50mW and occupies 0.3mm² | H55: Koji Sushihara and Akira Matsuzawa | I55: 10.1109/ISSCC.2002.992990 | J55: =IF(I55<>"?", HYPERLINK(CONCATENATE("https://doi.org/",I55)), "") -> https://doi.org/10.1109/ISSCC.2002.992990 | P55: 0.3 | R55: 225000000 | S55: 36 | X55: =+IF(ISNUMBER($S55),$S55,MIN($V55,$T55,$U55,$W55)) -> 36 | Y55: 0.05 | Z55: 450000000 | AA55: 1 | AB55: =Z55/AA55 -> 450000000 | AD55: =Y55/AB55*1000000000000 -> 111.11111 | AE55: =IF(ISNUMBER($Q55), $AD55*1000/2^(($Q55-1.76)/6.02), "") | AF55: =$AD55*1000/2^(($X55-1.76)/6.02) -> 2155.6929 | AG55: =IF(ISNUMBER($Q55), $Q55+10*LOG10($AB55/2/$Y55), "") | AH55: =$X55+10*LOG10($AB55/2/$Y55) -> 132.53213 | AI55: =AF55/AB55 -> 4.7904286e-06 | AJ55: =AH55+10*LOG10(AB55) -> 219.06425
A56: 2002 | B56: 10.4 | C56: NQ | D56: Pipe, TI | E56: 0.35 | F56: A 10b 120MSample/s time-interleaved analog-to-digital converter with digital background calibration | G56: Digital calibration using adaptive signal processing corrects offset mismatch, gain mismatch, and sample-time error between time-interleaved channels in a 10b 120MSample/s pipelined ADC. With background calibration, peak SNDR is 56.8dB and power dissipati | H56: Shafiq M. Jamal, Daihong Fu, Paul J. Hurst, and Stephen H. Lewis, | I56: 10.1109/ISSCC.2002.992991 | J56: =IF(I56<>"?", HYPERLINK(CONCATENATE("https://doi.org/",I56)), "") -> https://doi.org/10.1109/ISSCC.2002.992991 | K56: No HF data, fin=990kHz | P56: 12.5 | R56: 1000000 | S56: 56.8 | V56: 62.4 | W56: 70.2 | X56: =+IF(ISNUMBER($S56),$S56,MIN($V56,$T56,$U56,$W56)) -> 56.8 | Y56: 0.234 | Z56: 120000000 | AA56: 1 | AB56: =Z56/AA56 -> 120000000 | AD56: =Y56/AB56*1000000000000 -> 1950 | AE56: =IF(ISNUMBER($Q56), $AD56*1000/2^(($Q56-1.76)/6.02), "") | AF56: =$AD56*1000/2^(($X56-1.76)/6.02) -> 3449.5335 | AG56: =IF(ISNUMBER($Q56), $Q56+10*LOG10($AB56/2/$Y56), "") | AH56: =$X56+10*LOG10($AB56/2/$Y56) -> 140.88935 | AI56: =AF56/AB56 -> 2.8746112e-05 | AJ56: =AH56+10*LOG10(AB56) -> 221.68117
A57: 2002 | B57: 10.5 | C57: NQ | D57: Pipe | E57: 0.3 | F57: A 16mW 30MSample/s 10b pipelined A/D converter using a pseudo-differential architecture | G57: The authors present a 16 mW 2 V 30 MSample/s 10 b pipelined A/D converter in 0.3 µm CMOS technology which uses a pseudo-differential architecture and a capacitor cross-coupled S/H stage. SNDR and the SFDR at 30 MHz input are 54 dB and 67 dB, respectively | H57: Daisuke Miyazaki, Masanori Furuta, and Shoji Kawahito | I57: 10.1109/ISSCC.2002.992180 | J57: =IF(I57<>"?", HYPERLINK(CONCATENATE("https://doi.org/",I57)), "") -> https://doi.org/10.1109/ISSCC.2002.992180 | P57: 3.12 | R57: 15000000 | S57: 54 | W57: 67 | X57: =+IF(ISNUMBER($S57),$S57,MIN($V57,$T57,$U57,$W57)) -> 54 | Y57: 0.016 | Z57: 30000000 | AA57: 1 | AB57: =Z57/AA57 -> 30000000 | AD57: =Y57/AB57*1000000000000 -> 533.33333 | AE57: =IF(ISNUMBER($Q57), $AD57*1000/2^(($Q57-1.76)/6.02), "") | AF57: =$AD57*1000/2^(($X57-1.76)/6.02) -> 1302.3821 | AG57: =IF(ISNUMBER($Q57), $Q57+10*LOG10($AB57/2/$Y57), "") | AH57: =$X57+10*LOG10($AB57/2/$Y57) -> 143.71971 | AI57: =AF57/AB57 -> 4.3412738e-05 | AJ57: =AH57+10*LOG10(AB57) -> 218.49093
A58: 2002 | B58: 10.6 | C58: NQ | D58: SAR | E58: 0.13 | F58: A 1.2V 10b 20MSample/s non-binary successive approximation ADC in 0.13µm CMOS | G58: A successive-approximation ADC with non-binary code achieves 55dB SNR at sampling frequencies up to 20MHz. The converter, with on-chip driver for analog input and reference input, measures 0.08mm² in a standard 0.13µm CMOS process and consumes 12mW from a | H58: Franz Kuttner | I58: 10.1109/ISSCC.2002.992993 | J58: =IF(I58<>"?", HYPERLINK(CONCATENATE("https://doi.org/",I58)), "") -> https://doi.org/10.1109/ISSCC.2002.992993 | P58: 0.08 | R58: 10000000 | S58: 55 | T58: 55 | X58: =+IF(ISNUMBER($S58),$S58,MIN($V58,$T58,$U58,$W58)) -> 55 | Y58: 0.012 | Z58: 20000000 | AA58: 1 | AB58: =Z58/AA58 -> 20000000 | AD58: =Y58/AB58*1000000000000 -> 600 | AE58: =IF(ISNUMBER($Q58), $AD58*1000/2^(($Q58-1.76)/6.02), "") | AF58: =$AD58*1000/2^(($X58-1.76)/6.02) -> 1305.828 | AG58: =IF(ISNUMBER($Q58), $Q58+10*LOG10($AB58/2/$Y58), "") | AH58: =$X58+10*LOG10($AB58/2/$Y58) -> 144.20819 | AI58: =AF58/AB58 -> 6.5291399e-05 | AJ58: =AH58+10*LOG10(AB58) -> 217.21849
A59: 2002 | B59: 13.1 | C59: OS | D59: SDCT, BP | E59: 0.65 | F59: A 1 MHz-bandwidth second-order continuous-time quadrature bandpass sigma-delta modulator for low-IF radio receivers | G59: A 2nd-order continuous-time quadrature bandpass ΣΔ modulator with 1 MHz IF clocked at 100 MHz digitizes I and Q inputs with SNDR of 56.2 dB for 1 MHz bandwidth inputs. The 0.65 μm BiCMOS chip consumes 21.8 mW at 2.7 V, and operates with a clock-frequency range of 25-100 MHz | H59: Henkel, F.; Langmann, U.; Hanke, A.; Heinen, S.; Wagner, E. | I59: 10.1109/ISSCC.2002.993012 | J59: =IF(I59<>"?", HYPERLINK(CONCATENATE("https://doi.org/",I59)), "") -> https://doi.org/10.1109/ISSCC.2002.993012 | P59: 6 | R59: 1000000 | S59: 56.2 | X59: =+IF(ISNUMBER($S59),$S59,MIN($V59,$T59,$U59,$W59)) -> 56.2 | Y59: 0.0218 | Z59: 100000000 | AA59: 50 | AB59: =Z59/AA59 -> 2000000 | AC59: 1000000 | AD59: =Y59/AB59*1000000000000 -> 10900 | AE59: =IF(ISNUMBER($Q59), $AD59*1000/2^(($Q59-1.76)/6.02), "") | AF59: =$AD59*1000/2^(($X59-1.76)/6.02) -> 20661.186 | AG59: =IF(ISNUMBER($Q59), $Q59+10*LOG10($AB59/2/$Y59), "") | AH59: =$X59+10*LOG10($AB59/2/$Y59) -> 132.81544 | AI59: =AF59/AB59 -> 0.010330593 | AJ59: =AH59+10*LOG10(AB59) -> 195.82574
A60: 2002 | B60: 13.2 | C60: OS | D60: SDCT, SDSC, BP | E60: 0.35 BiCMOS | F60: A 50mW Bandpass ΣΔ ADC with 333kHz BW and 90dB DR | G60: A mixer plus multi-bit bandpass ΣΔ ADC achieves 89 dB and 77 dB SNR in 35 kHz and 333 kHz bandwidths at 273 MHz IF while consuming 16 mA from a 3 V supply. The 6 th-order ADC combines continuous-time LC and active RC resonators with a discrete-time switched-capacitor resonator, and includes an AGC capability. The IC is fabricated in a 0.35 μm BiCMOS process | H60: Schreier, R.; Lloyd, J.; Singer, L.; Paterson, D.; Timko, M.; Hensley, M.; Patterson, G.; Behel, K.; Zhou, J.; Martin, W.J.; | I60: 10.1109/ISSCC.2002.993013 | J60: =IF(I60<>"?", HYPERLINK(CONCATENATE("https://doi.org/",I60)), "") -> https://doi.org/10.1109/ISSCC.2002.993013 | L60: 3 | P60: 5 | R60: 330000 | S60: 81 | T60: 81 | U60: 90 | W60: 103 | X60: =+IF(ISNUMBER($S60),$S60,MIN($V60,$T60,$U60,$W60)) -> 81 | Y60: 0.05 | Z60: 32000000 | AA60: 48.484848 | AB60: =Z60/AA60 -> 660000 | AC60: 273000000 | AD60: =Y60/AB60*1000000000000 -> 75757.576 | AE60: =IF(ISNUMBER($Q60), $AD60*1000/2^(($Q60-1.76)/6.02), "") | AF60: =$AD60*1000/2^(($X60-1.76)/6.02) -> 8260.9737 | AG60: =IF(ISNUMBER($Q60), $Q60+10*LOG10($AB60/2/$Y60), "") | AH60: =$X60+10*LOG10($AB60/2/$Y60) -> 149.19544 | AI60: =AF60/AB60 -> 0.012516627 | AJ60: =AH60+10*LOG10(AB60) -> 207.39088
A61: 2002 | B61: 13.3 | C61: OS | D61: SDSC, BP | E61: 0.35 | F61: A dual-mode 80 MHz bandpass ΔΣ modulator for a GSM/WCDMA IF-receiver | G61: The authors present a band-pass modulator operating at 80 MHz which combines frequency down-conversion with A/D conversion. The two SC resonators are implemented using a single opamp. A single-bit quantizer and feedback is used for GSM, but 4 b quantizer is used for WCDMA. Measured peak SNRs are 80 dB for 270 kHz B/W (GSM), and 48 dB for 3.84 MHz B/W (WCDMA) | H61: Salo, T.; Hollman, T.; Lindfors, S.; Halonen, K. | I61: 10.1109/ISSCC.2002.993014 | J61: =IF(I61<>"?", HYPERLINK(CONCATENATE("https://doi.org/",I61)), "") -> https://doi.org/10.1109/ISSCC.2002.993014 | P61: 0.79 | R61: 3840000 | S61: 48 | T61: 48 | U61: 50 | X61: =+IF(ISNUMBER($S61),$S61,MIN($V61,$T61,$U61,$W61)) -> 48 | Y61: 0.038 | Z61: 80000000 | AA61: 10.416667 | AB61: =Z61/AA61 -> 7680000 | AC61: 20000000 | AD61: =Y61/AB61*1000000000000 -> 4947.9167 | AE61: =IF(ISNUMBER($Q61), $AD61*1000/2^(($Q61-1.76)/6.02), "") | AF61: =$AD61*1000/2^(($X61-1.76)/6.02) -> 24109.71 | AG61: =IF(ISNUMBER($Q61), $Q61+10*LOG10($AB61/2/$Y61), "") | AH61: =$X61+10*LOG10($AB61/2/$Y61) -> 128.04548 | AI61: =AF61/AB61 -> 0.0031392851 | AJ61: =AH61+10*LOG10(AB61) -> 196.89909
A62: 2002 | B62: 13.4 | C62: OS | D62: SDSC | E62: 0.18 | F62: A 1.8 V 14 b ΔΣ A/D converter with 4MSamples/s conversion | G62: A fifth-order single-stage ΔΣ modulator achieves 14 b resolution with 8× OSR and 4 MHz conversion bandwidth in a 1.8 V 0.18 μm CMOS process. The DC gain of the internal op amps is 43 dB. It occupies 1.3×2.2 mm² and consumes 102 mW analog power and 47 mW digital power | H62: Ruoxin Jiang; Fiez, T.S. | I62: 10.1109/ISSCC.2002.993015 | J62: =IF(I62<>"?", HYPERLINK(CONCATENATE("https://doi.org/",I62)), "") -> https://doi.org/10.1109/ISSCC.2002.993015 | P62: 2.86 | R62: 2000000 | S62: 82 | W62: 103 | X62: =+IF(ISNUMBER($S62),$S62,MIN($V62,$T62,$U62,$W62)) -> 82 | Y62: 0.102 | Z62: 32000000 | AA62: 8 | AB62: =Z62/AA62 -> 4000000 | AD62: =Y62/AB62*1000000000000 -> 25500 | AE62: =IF(ISNUMBER($Q62), $AD62*1000/2^(($Q62-1.76)/6.02), "") | AF62: =$AD62*1000/2^(($X62-1.76)/6.02) -> 2478.2229 | AG62: =IF(ISNUMBER($Q62), $Q62+10*LOG10($AB62/2/$Y62), "") | AH62: =$X62+10*LOG10($AB62/2/$Y62) -> 154.9243 | AI62: =AF62/AB62 -> 0.00061955573 | AJ62: =AH62+10*LOG10(AB62) -> 220.9449
A63: 2002 | B63: 13.5 | C63: OS | D63: SDCT | E63: 0.18 | F63: A 3.3 mW ΣΔ modulator for UMTS in 0.18 μm CMOS with 70 dB dynamic range in 2 MHz bandwidth | G63: The authors present a 4th-order continuous-time ΣΔ modulator with 1.5 b quantizer and feedback DAC for a UMTS receiver. The modulator has 70 dB DNR in a 2 MHz band and -74 dB THD at full scale. An IC which includes two modulators, a PLL, and an oscillator dissipates 11.5 mW at 1.8 V. Active area is 0.41 mm² in a 0.18 μm, 1-poly 5-metal-layer CMOS technology | H63: van Veldhoven, R.; Philips, K.; Minnis, B. | I63: 10.1109/ISSCC.2002.993016 | J63: =IF(I63<>"?", HYPERLINK(CONCATENATE("https://doi.org/",I63)), "") -> https://doi.org/10.1109/ISSCC.2002.993016 | P63: 0.41 | R63: 2000000 | S63: 70 | U63: 70 | V63: 74 | X63: =+IF(ISNUMBER($S63),$S63,MIN($V63,$T63,$U63,$W63)) -> 70 | Y63: 0.0033 | Z63: 153600000 | AA63: 38.4 | AB63: =Z63/AA63 -> 4000000 | AD63: =Y63/AB63*1000000000000 -> 825 | AE63: =IF(ISNUMBER($Q63), $AD63*1000/2^(($Q63-1.76)/6.02), "") | AF63: =$AD63*1000/2^(($X63-1.76)/6.02) -> 319.23752 | AG63: =IF(ISNUMBER($Q63), $Q63+10*LOG10($AB63/2/$Y63), "") | AH63: =$X63+10*LOG10($AB63/2/$Y63) -> 157.82516 | AI63: =AF63/AB63 -> 7.9809381e-05 | AJ63: =AH63+10*LOG10(AB63) -> 223.84576
A64: 2002 | B64: 13.6 | C64: OS | D64: SDSC | E64: 0.18 | F64: A 64 MHz ΣΔ ADC with 105 dB IM3 distortion using a linearized replica sampling network | G64: The authors present a ΣΔ ADC with 105 dB distortion up to 1.5 MHz signal bandwidth, which uses a linear sampling network in a single-bit feedback 2-1-1 mash cascade modulator architecture. Operating at 64 MHz clock frequency, the measured SNR in a 1.1 MHz bandwidth is 88 dB. The area, including bypass capacitors, is 2.6 mm², in a 0.18 μm 1.8 V/3.3 V SP5M digital CMOS process. The power consumed is 230 mW, including references and decimation filter | H64: Gupta, S.K.; Brooks, T.L.; Fong, V. | I64: 10.1109/ISSCC.2002.993017 | J64: =IF(I64<>"?", HYPERLINK(CONCATENATE("https://doi.org/",I64)), "") -> https://doi.org/10.1109/ISSCC.2002.993017 | P64: 2.6 | R64: 962000 | S64: 88 | W64: 106 | X64: =+IF(ISNUMBER($S64),$S64,MIN($V64,$T64,$U64,$W64)) -> 88 | Y64: 0.23 | Z64: 64000000 | AA64: 33.264033 | AB64: =Z64/AA64 -> 1924000 | AD64: =Y64/AB64*1000000000000 -> 119542.62 | AE64: =IF(ISNUMBER($Q64), $AD64*1000/2^(($Q64-1.76)/6.02), "") | AF64: =$AD64*1000/2^(($X64-1.76)/6.02) -> 5822.2797 | AG64: =IF(ISNUMBER($Q64), $Q64+10*LOG10($AB64/2/$Y64), "") | AH64: =$X64+10*LOG10($AB64/2/$Y64) -> 154.21447 | AI64: =AF64/AB64 -> 0.0030261329 | AJ64: =AH64+10*LOG10(AB64) -> 217.05652
A65: 2002 | B65: 18.1 | C65: OS | D65: SDSC | E65: 0.13 | F65: A 1.5 V 2.4/2.9 mW 79/50 dB DR ΣΔ modulator for GSM/WCDMA in a 0.13 μm digital process | G65: A 2nd order multi-level ΣΔ A/D converter for low-power multi-standard wireless receivers, in a single-poly 0.13 μm digital CMOS process, has 79/50 dB dynamic range for GSM/WCDMA. The 0.2 mm² chip consumes 2.4/2.9 mW at 1.5 V | H65: Gomez, G.; Haroun, B. | I65: 10.1109/ISSCC.2002.993054 | J65: =IF(I65<>"?", HYPERLINK(CONCATENATE("https://doi.org/",I65)), "") -> https://doi.org/10.1109/ISSCC.2002.993054 | K65: Data for WCDMA | P65: 0.2 | R65: 2000000 | S65: 49 | U65: 50 | X65: =+IF(ISNUMBER($S65),$S65,MIN($V65,$T65,$U65,$W65)) -> 49 | Y65: 0.0029 | Z65: 46000000 | AA65: 11.5 | AB65: =Z65/AA65 -> 4000000 | AD65: =Y65/AB65*1000000000000 -> 725 | AE65: =IF(ISNUMBER($Q65), $AD65*1000/2^(($Q65-1.76)/6.02), "") | AF65: =$AD65*1000/2^(($X65-1.76)/6.02) -> 3148.4922 | AG65: =IF(ISNUMBER($Q65), $Q65+10*LOG10($AB65/2/$Y65), "") | AH65: =$X65+10*LOG10($AB65/2/$Y65) -> 137.38632 | AI65: =AF65/AB65 -> 0.00078712306 | AJ65: =AH65+10*LOG10(AB65) -> 203.40692
A66: 2002 | B66: 18.2 | C66: NQ | D66: Flash | E66: 0.13 | F66: An embedded 0.8 V/480 µW 6b/22 MHz flash ADC in 0.13 µm digital CMOS process using nonlinear double-interpolation technique | G66: For high-data-rate wireless communication, a 0.8 V 480 µW 6b 22 MSample/s flash-interpolation ADC is fabricated in 0.13 µm digital CMOS. The circuit achieves 33 dB SNDR and 47 dB SFDR using a nonlinear double-interpolation technique | H66: Lin, J.; Haroun, B. | I66: 10.1109/ISSCC.2002.993055 | J66: =IF(I66<>"?", HYPERLINK(CONCATENATE("https://doi.org/",I66)), "") -> https://doi.org/10.1109/ISSCC.2002.993055 | P66: 0.3 | R66: 11000000 | S66: 33 | W66: 47 | X66: =+IF(ISNUMBER($S66),$S66,MIN($V66,$T66,$U66,$W66)) -> 33 | Y66: 0.00046 | Z66: 22000000 | AA66: 1 | AB66: =Z66/AA66 -> 22000000 | AD66: =Y66/AB66*1000000000000 -> 20.909091 | AE66: =IF(ISNUMBER($Q66), $AD66*1000/2^(($Q66-1.76)/6.02), "") | AF66: =$AD66*1000/2^(($X66-1.76)/6.02) -> 573.03281 | AG66: =IF(ISNUMBER($Q66), $Q66+10*LOG10($AB66/2/$Y66), "") | AH66: =$X66+10*LOG10($AB66/2/$Y66) -> 136.78635 | AI66: =AF66/AB66 -> 2.6046946e-05 | AJ66: =AH66+10*LOG10(AB66) -> 210.21058
A67: 2002 | B67: 18.3 | C67: OS | D67: SDSC | E67: 0.18 | F67: A 0.7V MOSFET-only switched-opamp ΣΔ modulator | G67: A 0.7V MOSFET-only switched-opamp ΣΔ modulator for speech applications achieves 67dB SNDR, and 75dB dynamic range. The circuit, occupying 0.08mm² in 0.18μm CMOS, does not use voltage boosting or low-VT devices. All capacitors are compensated MOS devices | H67: Sauerbrey, J.; Tille, T.; Schmitt-Landsiedel, D.; Thewes, R. | I67: 10.1109/ISSCC.2002.993056 | J67: =IF(I67<>"?", HYPERLINK(CONCATENATE("https://doi.org/",I67)), "") -> https://doi.org/10.1109/ISSCC.2002.993056 | P67: 0.08 | R67: 8000 | S67: 67 | U67: 75 | X67: =+IF(ISNUMBER($S67),$S67,MIN($V67,$T67,$U67,$W67)) -> 67 | Y67: 0.0001 | Z67: 1024000 | AA67: 64 | AB67: =Z67/AA67 -> 16000 | AD67: =Y67/AB67*1000000000000 -> 6250 | AE67: =IF(ISNUMBER($Q67), $AD67*1000/2^(($Q67-1.76)/6.02), "") | AF67: =$AD67*1000/2^(($X67-1.76)/6.02) -> 3416.2917 | AG67: =IF(ISNUMBER($Q67), $Q67+10*LOG10($AB67/2/$Y67), "") | AH67: =$X67+10*LOG10($AB67/2/$Y67) -> 146.0309 | AI67: =AF67/AB67 -> 0.21351823 | AJ67: =AH67+10*LOG10(AB67) -> 188.0721
A68: 2002 | B68: 18.4 | C68: NQ | D68: Pipe | E68: 0.6 | F68: A 30mW 12b 21MSample/s pipelined CMOS ADC | G68: A 0.6µm double-poly CMOS 12b ADC uses a number of different techniques to obtain low power. The ADC achieves 68dB SNR at 21 MSample/s, consuming 30mW at 2.7V. Die area is 2.56mm² | H68: Kulhalli, S.; Penkota, V.; Asv, R. | I68: 10.1109/ISSCC.2002.993057 | J68: =IF(I68<>"?", HYPERLINK(CONCATENATE("https://doi.org/",I68)), "") -> https://doi.org/10.1109/ISSCC.2002.993057 | K68: LF data only | P68: 2.56 | R68: 10000 | T68: 68.2 | X68: =+IF(ISNUMBER($S68),$S68,MIN($V68,$T68,$U68,$W68)) -> 68.2 | Y68: 0.03 | Z68: 21000000 | AA68: 1 | AB68: =Z68/AA68 -> 21000000 | AD68: =Y68/AB68*1000000000000 -> 1428.5714 | AE68: =IF(ISNUMBER($Q68), $AD68*1000/2^(($Q68-1.76)/6.02), "") | AF68: =$AD68*1000/2^(($X68-1.76)/6.02) -> 680.09708 | AG68: =IF(ISNUMBER($Q68), $Q68+10*LOG10($AB68/2/$Y68), "") | AH68: =$X68+10*LOG10($AB68/2/$Y68) -> 153.64068 | AI68: =AF68/AB68 -> 3.2385575e-05 | AJ68: =AH68+10*LOG10(AB68) -> 226.86287
A69: 2002 | B69: 18.5 | C69: NQ | D69: Pipe | E69: 0.35 BiCMOS | F69: A self-calibrated pipeline ADC with 200MHz IF-sampling frontend | G69: A 13b 50MSample/s pipeline ADC with digital self-calibration and IF-sampling frontend, using a 0.35µm BiCMOS process, achieves 76.5dB SFDR at 194MHz input. The chip occupies 6mm² and dissipates 715mW from a 2.9V supply | H69: Waltari, M.; Sumanen, L.; Korhonen, T.; Halonen, K. | I69: 10.1109/ISSCC.2002.993058 | J69: =IF(I69<>"?", HYPERLINK(CONCATENATE("https://doi.org/",I69)), "") -> https://doi.org/10.1109/ISSCC.2002.993058 | K69: Broken chip, SNDR is an optimistic estimate | L69: 2.9 | P69: 6 | R69: 25000000 | S69: 70 | W69: 76.5 | X69: =+IF(ISNUMBER($S69),$S69,MIN($V69,$T69,$U69,$W69)) -> 70 | Y69: 0.715 | Z69: 50000000 | AA69: 1 | AB69: =Z69/AA69 -> 50000000 | AD69: =Y69/AB69*1000000000000 -> 14300 | AE69: =IF(ISNUMBER($Q69), $AD69*1000/2^(($Q69-1.76)/6.02), "") | AF69: =$AD69*1000/2^(($X69-1.76)/6.02) -> 5533.4504 | AG69: =IF(ISNUMBER($Q69), $Q69+10*LOG10($AB69/2/$Y69), "") | AH69: =$X69+10*LOG10($AB69/2/$Y69) -> 145.43634 | AI69: =AF69/AB69 -> 0.00011066901 | AJ69: =AH69+10*LOG10(AB69) -> 222.42604
A70: 2002 | B70: 18.6 | C70: OS | D70: SDSC | E70: 0.25 | F70: A 33mW 14b 2.5MSample/s ΣΔ A/D converter in 0.25μm digital CMOS | G70: The IC consists of a 5th-order single-loop tri-level ΣΔ modulator and a multistage digital filter. Measured dynamic range is 86dB over 1 MHz bandwidth. With 79dB peak SNDR, the chip consumes 33mW and occupies 1.5mm² | H70: Reutemann, R.; Balmelli, P.; Qiuting Huang | I70: 10.1109/ISSCC.2002.993059 | J70: =IF(I70<>"?", HYPERLINK(CONCATENATE("https://doi.org/",I70)), "") -> https://doi.org/10.1109/ISSCC.2002.993059 | P70: 1.5 | R70: 1000000 | S70: 79 | T70: 84 | U70: 86 | X70: =+IF(ISNUMBER($S70),$S70,MIN($V70,$T70,$U70,$W70)) -> 79 | Y70: 0.033 | Z70: 80000000 | AA70: 40 | AB70: =Z70/AA70 -> 2000000 | AD70: =Y70/AB70*1000000000000 -> 16500 | AE70: =IF(ISNUMBER($Q70), $AD70*1000/2^(($Q70-1.76)/6.02), "") | AF70: =$AD70*1000/2^(($X70-1.76)/6.02) -> 2265.161 | AG70: =IF(ISNUMBER($Q70), $Q70+10*LOG10($AB70/2/$Y70), "") | AH70: =$X70+10*LOG10($AB70/2/$Y70) -> 153.81486 | AI70: =AF70/AB70 -> 0.0011325805 | AJ70: =AH70+10*LOG10(AB70) -> 216.82516
A71: 2002 | B71: 23.5 | C71: OS | D71: SDSC | E71: 0.35 | F71: A 10µV-offset 8kHz bandwidth 4th-order chopped ΣΔ A/D converter for battery management | G71: A chopped 4th-order continuous-time 1 bit ΣΔ A/D converter with 10 µV offset and 8 kHz bandwidth has been designed for battery current measurement. Chopping at 16 kHz, the circuit has a 0.1 V input range, a 68 dB SNR, and a 1 MHz output bit rate. Area is 0.45x0.4mm² in 0.35μm CMOS. Current consumption is 30μA at 2.5-4V. | H71: Blanken, P.G.; Menten, S.E.J. | I71: 10.1109/ISSCC.2002.993095 | J71: =IF(I71<>"?", HYPERLINK(CONCATENATE("https://doi.org/",I71)), "") -> https://doi.org/10.1109/ISSCC.2002.993095 | P71: 0.18 | R71: 8000 | T71: 68 | X71: =+IF(ISNUMBER($S71),$S71,MIN($V71,$T71,$U71,$W71)) -> 68 | Y71: 0.0001 | Z71: 1000000 | AA71: 62.5 | AB71: =Z71/AA71 -> 16000 | AD71: =Y71/AB71*1000000000000 -> 6250 | AE71: =IF(ISNUMBER($Q71), $AD71*1000/2^(($Q71-1.76)/6.02), "") | AF71: =$AD71*1000/2^(($X71-1.76)/6.02) -> 3044.7383 | AG71: =IF(ISNUMBER($Q71), $Q71+10*LOG10($AB71/2/$Y71), "") | AH71: =$X71+10*LOG10($AB71/2/$Y71) -> 147.0309 | AI71: =AF71/AB71 -> 0.19029614 | AJ71: =AH71+10*LOG10(AB71) -> 189.0721
A72: 2003 | B72: 3.1 | C72: OS | D72: SDSC | E72: 0.13 | F72: A 1.5V 1mA 80dB passive ΣΔ ADC in 0.13μm digital CMOS process | G72: A passive switched-capacitor ΣΔ ADC consisting of only switches, capacitors and a comparator, is implemented in a 0.13μm digital CMOS process. This high-speed low-voltage architecture is used in a zero-IF GSM transceiver and has a measured peak SNDR of 67dB over a bandwidth of 100kHz with a SFDR of 75dB and a dynamic range of 72dB. The ADC consumes 1mA from a 1.5V power supply at a clock rate of 104MHz. | H72: Feng Chen; Ramaswamy, S.; Bakkaloglu, B. | I72: 10.1109/ISSCC.2003.1234204 | J72: =IF(I72<>"?", HYPERLINK(CONCATENATE("https://doi.org/",I72)), "") -> https://doi.org/10.1109/ISSCC.2003.1234204 | K72: Data for WCDMA | L72: 1.5 | P72: 0.1225 | R72: 2000000 | S72: 45.2 | U72: 50.3 | X72: =+IF(ISNUMBER($S72),$S72,MIN($V72,$T72,$U72,$W72)) -> 45.2 | Y72: 0.0013 | Z72: 104000000 | AA72: 26 | AB72: =Z72/AA72 -> 4000000 | AD72: =Y72/AB72*1000000000000 -> 325 | AE72: =IF(ISNUMBER($Q72), $AD72*1000/2^(($Q72-1.76)/6.02), "") | AF72: =$AD72*1000/2^(($X72-1.76)/6.02) -> 2186.0843 | AG72: =IF(ISNUMBER($Q72), $Q72+10*LOG10($AB72/2/$Y72), "") | AH72: =$X72+10*LOG10($AB72/2/$Y72) -> 137.07087 | AI72: =AF72/AB72 -> 0.00054652109 | AJ72: =AH72+10*LOG10(AB72) -> 203.09147
A73: 2003 | B73: 3.2 | C73: OS | D73: SDSC | E73: 0.35 | F73: A 114 dB 68 mW chopper-stabilized stereo multi-bit audio A/D converter | G73: A fifth-order single-loop seventeen level ΣΔ modulator with an input feed-forward gain stage and second-order mismatch shaping logic achieves 114 dB dynamic range and -105 dB THD over the 20 kHz audio band. This stereo ADC occupies 5.62 mm² active area in a 0.35 μm 2P 3M CMOS process and dissipates only 55 mW power in the analog circuits. | H73: YuQing Yang; Chokhawala, A.; Alexander, M.; Melanson, J.; Hester, D. | I73: 10.1109/ISSCC.2003.1234205 | J73: =IF(I73<>"?", HYPERLINK(CONCATENATE("https://doi.org/",I73)), "") -> https://doi.org/10.1109/ISSCC.2003.1234205 | K73: A-weighted DR=114dB --> 111dB linear DR | P73: 5.62 | R73: 20000 | S73: 105 | U73: 111 | X73: =+IF(ISNUMBER($S73),$S73,MIN($V73,$T73,$U73,$W73)) -> 105 | Y73: 0.055 | Z73: =AB73*AA73 -> 5120000 | AA73: 128 | AB73: 40000 | AD73: =Y73/AB73*1000000000000 -> 1375000 | AE73: =IF(ISNUMBER($Q73), $AD73*1000/2^(($Q73-1.76)/6.02), "") | AF73: =$AD73*1000/2^(($X73-1.76)/6.02) -> 9457.76 | AG73: =IF(ISNUMBER($Q73), $Q73+10*LOG10($AB73/2/$Y73), "") | AH73: =$X73+10*LOG10($AB73/2/$Y73) -> 160.60667 | AI73: =AF73/AB73 -> 0.236444 | AJ73: =AH73+10*LOG10(AB73) -> 206.62727
A74: 2003 | B74: 3.3 | C74: OS | D74: SDSC | E74: 0.13 | F74: A 1.2-V dual-mode WCDMA/GPRS ΣΔ modulator | G74: A dual-mode ΣΔ modulator is designed to meet the specifications of a WCDMA/GPRS receiver and is composed of a single-bit second-order modulator followed by a multi-bit stage that adapts performance to broadband signals. The modulator achieves 82dB and 70dB of dynamic range over bandwidths of 100kHz and 1.92MHz, respectively, and dissipates 4.3mW from a 1.2V supply. The circuit is implemented in 0.13μm CMOS technology and occupies an active area of 0.2mm². | H74: Dezzani, A.; Andre, E. | I74: 10.1109/ISSCC.2003.1234206 | J74: =IF(I74<>"?", HYPERLINK(CONCATENATE("https://doi.org/",I74)), "") -> https://doi.org/10.1109/ISSCC.2003.1234206 | K74: Data for WCDMA | L74: 1.2 | P74: 0.2 | R74: 1920000 | S74: 64 | U74: 70 | X74: =+IF(ISNUMBER($S74),$S74,MIN($V74,$T74,$U74,$W74)) -> 64 | Y74: 0.0021 | Z74: 38400000 | AA74: 10 | AB74: =Z74/AA74 -> 3840000 | AD74: =Y74/AB74*1000000000000 -> 546.875 | AE74: =IF(ISNUMBER($Q74), $AD74*1000/2^(($Q74-1.76)/6.02), "") | AF74: =$AD74*1000/2^(($X74-1.76)/6.02) -> 422.25806 | AG74: =IF(ISNUMBER($Q74), $Q74+10*LOG10($AB74/2/$Y74), "") | AH74: =$X74+10*LOG10($AB74/2/$Y74) -> 153.61082 | AI74: =AF74/AB74 -> 0.00010996304 | AJ74: =AH74+10*LOG10(AB74) -> 219.45413
A75: 2003 | B75: 3.4 | C75: OS | D75: SDCT, Complex, BP | E75: 0.18 | F75: A tri-mode continuous-time ΣΔ modulator with switched-capacitor feedback DAC for a GSM-EDGE/CDMA2000/UMTS receiver | G75: Complex continuous-time fifth-order ΣΔ modulator with 1b quantizer and switched-capacitor feedback DAC for a GSM/CDMA2000/UMTS receiver achieves a dynamic range of 92/83/74dB in 200/1228/3840kHz. Power consumption of one modulator is 3.8/4.1/4.5mW at 1.8V. Processed in 0.18μm CMOS, the 0.55mm² IC includes a PLL, two oscillators and a bandgap reference. | H75: van Veldhoven, R. | I75: 10.1109/ISSCC.2003.1234207 | J75: =IF(I75<>"?", HYPERLINK(CONCATENATE("https://doi.org/",I75)), "") -> https://doi.org/10.1109/ISSCC.2003.1234207 | K75: Data for CDMA | P75: 0.55 | R75: 1230000 | T75: 83 | U75: 83 | X75: =+IF(ISNUMBER($S75),$S75,MIN($V75,$T75,$U75,$W75)) -> 83 | Y75: 0.0041 | Z75: 76800000 | AA75: 31.219512 | AB75: =Z75/AA75 -> 2460000 | AC75: 100000 | AD75: =Y75/AB75*1000000000000 -> 1666.6667 | AE75: =IF(ISNUMBER($Q75), $AD75*1000/2^(($Q75-1.76)/6.02), "") | AF75: =$AD75*1000/2^(($X75-1.76)/6.02) -> 144.35903 | AG75: =IF(ISNUMBER($Q75), $Q75+10*LOG10($AB75/2/$Y75), "") | AH75: =$X75+10*LOG10($AB75/2/$Y75) -> 167.77121 | AI75: =AF75/AB75 -> 5.8682533e-05 | AJ75: =AH75+10*LOG10(AB75) -> 231.68056
A76: 2003 | B76: 3.5 | C76: OS | D76: SDCT | E76: 0.5 | F76: A continuous-time ΣΔ modulator with 88dB dynamic range and 1.1MHz signal bandwidth | G76: A baseband continuous-time multi-bit ΣΔ modulator achieves 88dB dynamic range over a 1.1MHz signal bandwidth consuming 62mW from a 3.3V supply. Excess loop delay encountered in conventional continuous-time modulators is eliminated by the proposed architecture. Clock-jitter sensitivity is considerably reduced compared with prior designs. | H76: Yan, S.; Sanchez-Sinencio, E. | I76: 10.1109/ISSCC.2003.1234208 | J76: =IF(I76<>"?", HYPERLINK(CONCATENATE("https://doi.org/",I76)), "") -> https://doi.org/10.1109/ISSCC.2003.1234208 | L76: 3.3 | P76: 5.76 | R76: 1100000 | S76: 83 | T76: 84 | U76: 88 | X76: =+IF(ISNUMBER($S76),$S76,MIN($V76,$T76,$U76,$W76)) -> 83 | Y76: 0.062 | Z76: 35200000 | AA76: 16 | AB76: =Z76/AA76 -> 2200000 | AD76: =Y76/AB76*1000000000000 -> 28181.818 | AE76: =IF(ISNUMBER($Q76), $AD76*1000/2^(($Q76-1.76)/6.02), "") | AF76: =$AD76*1000/2^(($X76-1.76)/6.02) -> 2440.98 | AG76: =IF(ISNUMBER($Q76), $Q76+10*LOG10($AB76/2/$Y76), "") | AH76: =$X76+10*LOG10($AB76/2/$Y76) -> 155.49001 | AI76: =AF76/AB76 -> 0.0011095364 | AJ76: =AH76+10*LOG10(AB76) -> 218.91424
A77: 2003 | B77: 3.6 | C77: OS | D77: SDCT, Complex, BP | E77: 0.18 | F77: A 4.4mW 76dB complex ΣΔ ADC for Bluetooth receivers | G77: A ΣΔ ADC with a fifth-order continuous-time complex loop filter achieves 76dB of DNR in a 1MHz channel. The input impedance is less than 400Ω and allows operation with a current-mode RF front-end. Image rejection is over 50dB, and IM3 distortion is below -82dBc. The circuit dissipates 4.4mW and is implemented in 0.18μm CMOS. | H77: Philips, K. | I77: 10.1109/ISSCC.2003.1234209 | J77: =IF(I77<>"?", HYPERLINK(CONCATENATE("https://doi.org/",I77)), "") -> https://doi.org/10.1109/ISSCC.2003.1234209 | P77: 0.22 | R77: 1000000 | S77: 75.5 | U77: 76 | X77: =+IF(ISNUMBER($S77),$S77,MIN($V77,$T77,$U77,$W77)) -> 75.5 | Y77: 0.0047 | Z77: 64000000 | AA77: 32 | AB77: =Z77/AA77 -> 2000000 | AC77: 500000 | AD77: =Y77/AB77*1000000000000 -> 2350 | AE77: =IF(ISNUMBER($Q77), $AD77*1000/2^(($Q77-1.76)/6.02), "") | AF77: =$AD77*1000/2^(($X77-1.76)/6.02) -> 482.72572 | AG77: =IF(ISNUMBER($Q77), $Q77+10*LOG10($AB77/2/$Y77), "") | AH77: =$X77+10*LOG10($AB77/2/$Y77) -> 158.77902 | AI77: =AF77/AB77 -> 0.00024136286 | AJ77: =AH77+10*LOG10(AB77) -> 221.78932
A78: 2003 | B78: 3.7 | C78: OS | D78: SDSC | E78: 0.13 | F78: A dual channel ΣΔ ADC with 40MHz aggregate signal bandwidth | G78: A dual-channel ΣΔ ADC has been integrated in 0.13μm CMOS technology with an oversampling ratio of 4. The ADC employs a cascade of low-pass and band-pass modulators and achieves an aggregate quadrature signal bandwidth of 40MHz at a sampling frequency of 160MS/s and 54dB dynamic range while dissipating 175mW from a 2.5V supply. | H78: Tabatabaei, A.; Onodera, K.; Zargari, M.; Samavati, H.; Su, D.K. | I78: 10.1109/ISSCC.2003.1234210 | J78: =IF(I78<>"?", HYPERLINK(CONCATENATE("https://doi.org/",I78)), "") -> https://doi.org/10.1109/ISSCC.2003.1234210 | L78: 2.5 | P78: 2.4 | R78: =AB78/2 -> 20000000 | S78: 50 | U78: 53 | X78: =+IF(ISNUMBER($S78),$S78,MIN($V78,$T78,$U78,$W78)) -> 50 | Y78: =0.106/2 -> 0.053 | Z78: 160000000 | AA78: 4 | AB78: =Z78/AA78 -> 40000000 | AD78: =Y78/AB78*1000000000000 -> 1325 | AE78: =IF(ISNUMBER($Q78), $AD78*1000/2^(($Q78-1.76)/6.02), "") | AF78: =$AD78*1000/2^(($X78-1.76)/6.02) -> 5128.3247 | AG78: =IF(ISNUMBER($Q78), $Q78+10*LOG10($AB78/2/$Y78), "") | AH78: =$X78+10*LOG10($AB78/2/$Y78) -> 135.76754 | AI78: =AF78/AB78 -> 0.00012820812 | AJ78: =AH78+10*LOG10(AB78) -> 211.78814
A79: 2003 | B79: 18.1 | C79: NQ | D79: Pipe, TI | E79: 0.18 | F79: A 20GS/s 8b ADC with a 1MB memory in 0.18µm CMOS | G79: A 20 GS/s 8-bit ADC achieves a bandwidth of 6 GHz in 0.18 μm CMOS. The implementation uses 80 time-interleaved current-mode pipeline sub-ADCs and stores data at 20 GB/s into a 1 MB on-chip memory. The ADC is packaged with a BiCMOS input buffer chip in a 438-ball BGA, and total power consumption is 10 W. | H79: Ken Poulton, Robert Neff, Brian Setterberg, Bernd Wuppermann, Tom Kopley, Robert Jewett, Jorge Pernillo, Charles Tan, and Allen Montijo | I79: 10.1109/ISSCC.2003.1234315 | J79: =IF(I79<>"?", HYPERLINK(CONCATENATE("https://doi.org/",I79)), "") -> https://doi.org/10.1109/ISSCC.2003.1234315 | O79: 4 | P79: =14*14 -> 196 | Q79: =6.5*6.02+1.76 -> 40.89 | R79: 6000000000 | S79: =4.6*6.02+1.76 -> 29.452 | X79: =+IF(ISNUMBER($S79),$S79,MIN($V79,$T79,$U79,$W79)) -> 29.452 | Y79: 10 | Z79: 20000000000 | AA79: 1 | AB79: =Z79/AA79 -> 20000000000 | AD79: =Y79/AB79*1000000000000 -> 500 | AE79: =IF(ISNUMBER($Q79), $AD79*1000/2^(($Q79-1.76)/6.02), "") -> 5524.2717 | AF79: =$AD79*1000/2^(($X79-1.76)/6.02) -> 20617.311 | AG79: =IF(ISNUMBER($Q79), $Q79+10*LOG10($AB79/2/$Y79), "") -> 130.89 | AH79: =$X79+10*LOG10($AB79/2/$Y79) -> 119.452 | AI79: =AF79/AB79 -> 1.0308656e-06 | AJ79: =AH79+10*LOG10(AB79) -> 222.4623
A80: 2003 | B80: 18.3 | C80: NQ | D80: Flash, TI | E80: 0.18 | F80: A 2GS/s 6b ADC in 0.18µm CMOS | G80: A 2 GS/s 6-bit ADC with time-interleaving is demonstrated in 0.18 μm CMOS. Three cross-connected and pre-distorted reference voltages improve the averaging performance. Circuit techniques enabling an SNDR of 30 dB at Nyquist input frequency and a FOM of 3.5 pJ per conversion step are discussed, and experimental results validating the simulated performance metrics are presented. | H80: Xicheng Jiang, Zhengyu Wang, and M. Frank Chang, | I80: 10.1109/ISSCC.2003.1234317 | J80: =IF(I80<>"?", HYPERLINK(CONCATENATE("https://doi.org/",I80)), "") -> https://doi.org/10.1109/ISSCC.2003.1234317 | P80: 0.5 | R80: 1000000000 | S80: 30 | W80: 35 | X80: =+IF(ISNUMBER($S80),$S80,MIN($V80,$T80,$U80,$W80)) -> 30 | Y80: 0.31 | Z80: 2000000000 | AA80: 1 | AB80: =Z80/AA80 -> 2000000000 | AD80: =Y80/AB80*1000000000000 -> 155 | AE80: =IF(ISNUMBER($Q80), $AD80*1000/2^(($Q80-1.76)/6.02), "") | AF80: =$AD80*1000/2^(($X80-1.76)/6.02) -> 6000.549 | AG80: =IF(ISNUMBER($Q80), $Q80+10*LOG10($AB80/2/$Y80), "") | AH80: =$X80+10*LOG10($AB80/2/$Y80) -> 125.08638 | AI80: =AF80/AB80 -> 3.0002745e-06 | AJ80: =AH80+10*LOG10(AB80) -> 218.09668
A81: 2003 | B81: 18.4 | C81: NQ | D81: Pipe | E81: 0.18 | F81: A 69mW 10b 80MS/s pipelined CMOS ADC | G81: A 10 b 80 MHz pipelined ADC with an active area of 1.85 mm² is realized in a 0.18 μm dual gate oxidation CMOS process and achieves 72.8 dBc SFDR, 57.92 dB SNR, and 9.29 ENOB for a 100 MHz input at full sampling rate. The ADC shares an amplifier between two successive pipeline stages in order to achieve a power consumption of 69 mW at 3 V. | H81: Byung-Moo Min, Peter Kim, David Boisvert, and Arlo Aude | I81: 10.1109/ISSCC.2003.1234318 | J81: =IF(I81<>"?", HYPERLINK(CONCATENATE("https://doi.org/",I81)), "") -> https://doi.org/10.1109/ISSCC.2003.1234318 | P81: 1.85 | R81: 40000000 | S81: =9.38*6.02+1.76 -> 58.2276 | T81: 58.9 | V81: 68.4 | W81: 70.6 | X81: =+IF(ISNUMBER($S81),$S81,MIN($V81,$T81,$U81,$W81)) -> 58.2276 | Y81: 0.069 | Z81: 80000000 | AA81: 1 | AB81: =Z81/AA81 -> 80000000 | AD81: =Y81/AB81*1000000000000 -> 862.5 | AE81: =IF(ISNUMBER($Q81), $AD81*1000/2^(($Q81-1.76)/6.02), "") | AF81: =$AD81*1000/2^(($X81-1.76)/6.02) -> 1294.4872 | AG81: =IF(ISNUMBER($Q81), $Q81+10*LOG10($AB81/2/$Y81), "") | AH81: =$X81+10*LOG10($AB81/2/$Y81) -> 145.85971 | AI81: =AF81/AB81 -> 1.6181089e-05 | AJ81: =AH81+10*LOG10(AB81) -> 224.89061
A82: 2003 | B82: 18.5 | C82: NQ | D82: Pipe | E82: 0.18 | F82: A 10b 150MS/s 123mW 0.18µm CMOS pipelined ADC | G82: A 10 b 150 MHz multi-bit-per-stage single-channel CMOS pipelined ADC, incorporating temperature- and supply-insensitive CMOS references and improved gate-bootstrapping techniques for a wideband SHA, achieves a SNDR of 52 dB and SFDR of 65 dB at 150 MS/s. The ADC, fabricated in 0.18 μm CMOS, occupies an active die area of 2.2 mm² and consumes 123 mW at 1.8 V. | H82: Sang-Min Yoo, Jong-Bum Park, Hee-Suk Yang, Hyuen-Hee Bae, Kyoung-Ho Moon, Ho-Jin Park, Seung-Hoon Lee, and Jae-Hwui Kim, | I82: 10.1109/ISSCC.2003.1234319 | J82: =IF(I82<>"?", HYPERLINK(CONCATENATE("https://doi.org/",I82)), "") -> https://doi.org/10.1109/ISSCC.2003.1234319 | L82: 1.8 | P82: 2.2 | R82: 75000000 | S82: 52 | W82: 65 | X82: =+IF(ISNUMBER($S82),$S82,MIN($V82,$T82,$U82,$W82)) -> 52 | Y82: 0.123 | Z82: 150000000 | AA82: 1 | AB82: =Z82/AA82 -> 150000000 | AD82: =Y82/AB82*1000000000000 -> 820 | AE82: =IF(ISNUMBER($Q82), $AD82*1000/2^(($Q82-1.76)/6.02), "") | AF82: =$AD82*1000/2^(($X82-1.76)/6.02) -> 2520.9459 | AG82: =IF(ISNUMBER($Q82), $Q82+10*LOG10($AB82/2/$Y82), "") | AH82: =$X82+10*LOG10($AB82/2/$Y82) -> 139.85156 | AI82: =AF82/AB82 -> 1.6806306e-05 | AJ82: =AH82+10*LOG10(AB82) -> 221.61247
A83: 2003 | B83: 18.6 | C83: NQ | D83: Pipe | E83: 0.35 | F83: A 12b 75MS/s pipelined ADC using open-loop residue amplification | G83: The multi-bit first stage of a 12 b 75 MS/s pipelined ADC uses an open-loop gain stage to achieve more than 60% residue amplifier power savings over a conventional implementation. Statistical background calibration removes linear and nonlinear residue errors in the digital domain. The prototype IC achieves 68.2 dB SNR, -76 dB THD, occupies 7.9 mm² in 0.35 μm CMOS and consumes 290 mW at 3 V. | H83: Boris Murmann and Bernhard E. Boser | I83: 10.1109/ISSCC.2003.1234320 | J83: =IF(I83<>"?", HYPERLINK(CONCATENATE("https://doi.org/",I83)), "") -> https://doi.org/10.1109/ISSCC.2003.1234320 | P83: 7.9 | R83: 37500000 | S83: 67 | W83: 76 | X83: =+IF(ISNUMBER($S83),$S83,MIN($V83,$T83,$U83,$W83)) -> 67 | Y83: 0.29 | Z83: 75000000 | AA83: 1 | AB83: =Z83/AA83 -> 75000000 | AD83: =Y83/AB83*1000000000000 -> 3866.6667 | AE83: =IF(ISNUMBER($Q83), $AD83*1000/2^(($Q83-1.76)/6.02), "") | AF83: =$AD83*1000/2^(($X83-1.76)/6.02) -> 2113.5458 | AG83: =IF(ISNUMBER($Q83), $Q83+10*LOG10($AB83/2/$Y83), "") | AH83: =$X83+10*LOG10($AB83/2/$Y83) -> 148.11633 | AI83: =AF83/AB83 -> 2.8180611e-05 | AJ83: =AH83+10*LOG10(AB83) -> 226.86695
A84: 2003 | B84: 18.7 | C84: NQ | D84: Pipe | E84: 0.35 BiCMOS | F84: Impact of dielectric relaxation on a 14b pipeline ADC in 3V SiGe BiCMOS | G84: Dielectric relaxation in PECVD SiN capacitors of a 45 GHz 0.4 μm SiGe BiCMOS process degrades performance even at low frequencies. In the design of pipelined 14 b 70 MS/s ADC, the effects of dielectric relaxation are identified via behavioral/circuit simulations and ad-hoc tests. After LPCVD oxide capacitors are introduced, a 5.3×5.3 mm² test chip delivers 72 dB SNR, 81 dBc SFDR, and 11.5 ENOB at 70 MS/s with a 1 MHz input. The IC dissipates 1 W from 3.3 V. | H84: Alfio Zanchi, Frank Tsay, and Ioannis Papantonopoulos | I84: 10.1109/ISSCC.2003.1234321 | J84: =IF(I84<>"?", HYPERLINK(CONCATENATE("https://doi.org/",I84)), "") -> https://doi.org/10.1109/ISSCC.2003.1234321 | P84: 25 | R84: 35000000 | S84: =11.8*6.02+1.76 -> 72.796 | W84: 81 | X84: =+IF(ISNUMBER($S84),$S84,MIN($V84,$T84,$U84,$W84)) -> 72.796 | Y84: 1 | Z84: 70000000 | AA84: 1 | AB84: =Z84/AA84 -> 70000000 | AD84: =Y84/AB84*1000000000000 -> 14285.714 | AE84: =IF(ISNUMBER($Q84), $AD84*1000/2^(($Q84-1.76)/6.02), "") | AF84: =$AD84*1000/2^(($X84-1.76)/6.02) -> 4006.3419 | AG84: =IF(ISNUMBER($Q84), $Q84+10*LOG10($AB84/2/$Y84), "") | AH84: =$X84+10*LOG10($AB84/2/$Y84) -> 148.23668 | AI84: =AF84/AB84 -> 5.7233456e-05 | AJ84: =AH84+10*LOG10(AB84) -> 226.68766
A85: 2003 | B85: 23.6 | C85: OS | D85: SDCT | E85: 0.25 | F85: A 700/900mW/channel CMOS dual analog front-end IC for VDSL with integrated 11.5/14.5dBm line drivers | G85: A dual-channel analog front-end for ANSI/ETSI standards compliant VDSL in 0.25/0.5μm 1P 5M CMOS is presented. The chip includes a non-linearity cancelling multi-path line driver achieving -76dBc 3rd harmonic distortion at 12MHz, a 75mW continuous-time multi-bit 3rd-order self-calibrating ΣΔ ADC, a 14b current-steering DAC with PSD mask post filter, a 0-35dB variable-gain amplifier with adjustable hybrid, and a 12ps jitter LC PLL. | H85: Moyal, M.; Groepl, M.; Werker, H.; Mitteregger, G.; Schambacher, J. | I85: 10.1109/ISSCC.2003.1234364 | J85: =IF(I85<>"?", HYPERLINK(CONCATENATE("https://doi.org/",I85)), "") -> https://doi.org/10.1109/ISSCC.2003.1234364 | P85: 31 | R85: 12000000 | T85: 79 | X85: =+IF(ISNUMBER($S85),$S85,MIN($V85,$T85,$U85,$W85)) -> 79 | Y85: 0.075 | Z85: 240000000 | AA85: 10 | AB85: =Z85/AA85 -> 24000000 | AD85: =Y85/AB85*1000000000000 -> 3125 | AE85: =IF(ISNUMBER($Q85), $AD85*1000/2^(($Q85-1.76)/6.02), "") | AF85: =$AD85*1000/2^(($X85-1.76)/6.02) -> 429.00777 | AG85: =IF(ISNUMBER($Q85), $Q85+10*LOG10($AB85/2/$Y85), "") | AH85: =$X85+10*LOG10($AB85/2/$Y85) -> 161.0412 | AI85: =AF85/AB85 -> 1.7875324e-05 | AJ85: =AH85+10*LOG10(AB85) -> 234.84331
A86: 2004 | B86: 4.1 | C86: OS | D86: SDCT | E86: 0.18 | F86: A cascaded continuous-time ΣΔ modulator with 67dB dynamic range in 10MHz bandwidth | G86: A 2-2 cascaded ΣΔ modulator with continuous-time loop filters and 4b quantizers is presented. The dynamic range is 67dB in a 10MHz bandwidth at a 160MS/s with a full-scale input range of 200mVrms. Inherent anti-aliasing filtering is over 50dB. The 0.18μm CMOS chip measures 1.7mm² and draws 68mA from a 1.8V supply. | H86: Breems, L.J. | I86: 10.1109/ISSCC.2004.1332599 | J86: =IF(I86<>"?", HYPERLINK(CONCATENATE("https://doi.org/",I86)), "") -> https://doi.org/10.1109/ISSCC.2004.1332599 | L86: 1.8 | P86: 1.7 | R86: 10000000 | T86: 63 | U86: 67 | X86: =+IF(ISNUMBER($S86),$S86,MIN($V86,$T86,$U86,$W86)) -> 63 | Y86: =0.068*1.8 -> 0.1224 | Z86: 160000000 | AA86: 8 | AB86: =Z86/AA86 -> 20000000 | AD86: =Y86/AB86*1000000000000 -> 6120 | AE86: =IF(ISNUMBER($Q86), $AD86*1000/2^(($Q86-1.76)/6.02), "") | AF86: =$AD86*1000/2^(($X86-1.76)/6.02) -> 5302.0801 | AG86: =IF(ISNUMBER($Q86), $Q86+10*LOG10($AB86/2/$Y86), "") | AH86: =$X86+10*LOG10($AB86/2/$Y86) -> 142.12219 | AI86: =AF86/AB86 -> 0.000265104 | AJ86: =AH86+10*LOG10(AB86) -> 215.13249
A87: 2004 | B87: 4.2 | C87: OS | D87: SDSC | E87: 0.18 | F87: A 25 MS/s 14 b 200 mW ΣΔ modulator in 0.18 μm CMOS | G87: Sampled at 200 MHz, a 5th-order 4 b-quantizer single-loop ΣΔ modulator achieves a 25 MS/s conversion rate with 84 dB DR and 82 dB SNR, a performance suitable for VDSL. Implemented in 0.18 μm CMOS, the 0.95 mm² chip has a power consumption of 200 mW from a 1.8 V supply. | H87: Balmelli, P.; Qiuting Huang | I87: 10.1109/ISSCC.2004.1332600 | J87: =IF(I87<>"?", HYPERLINK(CONCATENATE("https://doi.org/",I87)), "") -> https://doi.org/10.1109/ISSCC.2004.1332600 | L87: 1.8 | P87: 0.95 | R87: 12500000 | S87: 72 | T87: 82 | U87: 84 | X87: =+IF(ISNUMBER($S87),$S87,MIN($V87,$T87,$U87,$W87)) -> 72 | Y87: 0.2 | Z87: 200000000 | AA87: 8 | AB87: =Z87/AA87 -> 25000000 | AD87: =Y87/AB87*1000000000000 -> 8000 | AE87: =IF(ISNUMBER($Q87), $AD87*1000/2^(($Q87-1.76)/6.02), "") | AF87: =$AD87*1000/2^(($X87-1.76)/6.02) -> 2458.8951 | AG87: =IF(ISNUMBER($Q87), $Q87+10*LOG10($AB87/2/$Y87), "") | AH87: =$X87+10*LOG10($AB87/2/$Y87) -> 149.9588 | AI87: =AF87/AB87 -> 9.8355805e-05 | AJ87: =AH87+10*LOG10(AB87) -> 223.9382
A88: 2004 | B88: 4.3 | C88: OS | D88: SDSC | E88: 0.18 | F88: ΣΔ ADC with finite impulse response feedback DAC | G88: A continuous-time 1 b ΣΔ ADC with a finite impulse response DAC in the feedback path is presented. The FIRDAC reduces the susceptibility to clock jitter by 18 dB while maintaining linearity. S/N ratio is 77 dB in a 1 MHz bandwidth, and IM2 and IM3 are 77 dB and 82 dB, respectively. The 0.18 μm CMOS chip consumes 6.0 mW. | H88: Putter, B.M. | I88: 10.1109/ISSCC.2004.1332601 | J88: =IF(I88<>"?", HYPERLINK(CONCATENATE("https://doi.org/",I88)), "") -> https://doi.org/10.1109/ISSCC.2004.1332601 | P88: 0.2 | R88: 1100000 | S88: =12.5*6.02+1.76 -> 77.01 | T88: 77.3 | X88: =+IF(ISNUMBER($S88),$S88,MIN($V88,$T88,$U88,$W88)) -> 77.01 | Y88: 0.006 | Z88: 281600000 | AA88: 128 | AB88: =Z88/AA88 -> 2200000 | AD88: =Y88/AB88*1000000000000 -> 2727.2727 | AE88: =IF(ISNUMBER($Q88), $AD88*1000/2^(($Q88-1.76)/6.02), "") | AF88: =$AD88*1000/2^(($X88-1.76)/6.02) -> 470.81861 | AG88: =IF(ISNUMBER($Q88), $Q88+10*LOG10($AB88/2/$Y88), "") | AH88: =$X88+10*LOG10($AB88/2/$Y88) -> 159.64241 | AI88: =AF88/AB88 -> 0.00021400846 | AJ88: =AH88+10*LOG10(AB88) -> 223.06664
A89: 2004 | B89: 4.4 | C89: OS | D89: SDCT | E89: 0.13 | F89: A 0.9 V 1.5 mW continuous-time ΔΣ modulator for WCDMA | G89: A second-order continuous-time ΔΣ modulator for a WCDMA RX is implemented with inverter-based OTAs, enabling operation at a voltage of 0.9 V. The OTAs are balanced by using CMFB. The modulator consumes only 1.5 mW and occupies 0.12 mm² in a 0.13 μm CMOS process. SNDR is 50.9 dB over a bandwidth of 1.92 MHz. | H89: Ueno, T.; Itakura, T. | I89: 10.1109/ISSCC.2004.1332602 | J89: =IF(I89<>"?", HYPERLINK(CONCATENATE("https://doi.org/",I89)), "") -> https://doi.org/10.1109/ISSCC.2004.1332602 | P89: 0.12 | R89: 1920000 | S89: 50.9 | T89: 53.2 | U89: 54 | X89: =+IF(ISNUMBER($S89),$S89,MIN($V89,$T89,$U89,$W89)) -> 50.9 | Y89: =0.0015*0.9 -> 0.00135 | Z89: 61440000 | AA89: 16 | AB89: =Z89/AA89 -> 3840000 | AD89: =Y89/AB89*1000000000000 -> 351.5625 | AE89: =IF(ISNUMBER($Q89), $AD89*1000/2^(($Q89-1.76)/6.02), "") | AF89: =$AD89*1000/2^(($X89-1.76)/6.02) -> 1226.7546 | AG89: =IF(ISNUMBER($Q89), $Q89+10*LOG10($AB89/2/$Y89), "") | AH89: =$X89+10*LOG10($AB89/2/$Y89) -> 142.42967 | AI89: =AF89/AB89 -> 0.00031946734 | AJ89: =AH89+10*LOG10(AB89) -> 208.27299
A90: 2004 | B90: 4.5 | C90: OS | D90: SDSC | E90: 0.09 | F90: A 1 V 88 dB 20 kHz ΣΔ modulator in 90 nm CMOS | G90: A third-order single-loop SC ΣΔ modulator is realized in a standard 90 nm digital CMOS technology. The modulator achieves 88 dB dynamic range for a 20 kHz signal bandwidth with an OSR of 100. Power consumption is 140 μW from a 1 V supply, and the chip core size is 0.18 mm². | H90: Yao, L.; Steyaert, M.; Sansen, W. | I90: 10.1109/ISSCC.2004.1332603 | J90: =IF(I90<>"?", HYPERLINK(CONCATENATE("https://doi.org/",I90)), "") -> https://doi.org/10.1109/ISSCC.2004.1332603 | L90: 1 | P90: 0.18 | R90: 20000 | S90: 81 | T90: 85 | U90: 88 | X90: =+IF(ISNUMBER($S90),$S90,MIN($V90,$T90,$U90,$W90)) -> 81 | Y90: 0.00014 | Z90: 4000000 | AA90: 100 | AB90: =Z90/AA90 -> 40000 | AD90: =Y90/AB90*1000000000000 -> 3500 | AE90: =IF(ISNUMBER($Q90), $AD90*1000/2^(($Q90-1.76)/6.02), "") | AF90: =$AD90*1000/2^(($X90-1.76)/6.02) -> 381.65699 | AG90: =IF(ISNUMBER($Q90), $Q90+10*LOG10($AB90/2/$Y90), "") | AH90: =$X90+10*LOG10($AB90/2/$Y90) -> 162.54902 | AI90: =AF90/AB90 -> 0.0095414247 | AJ90: =AH90+10*LOG10(AB90) -> 208.56962
A91: 2004 | B91: 4.6 | C91: OS | D91: SDSC | E91: 0.13 | F91: A power optimized 14-bit SC ΔΣ modulator for ADSL CO applications | G91: A switched-capacitor multi-bit ΔΣ ADC including a reference-voltage buffer is implemented in 0.13 μm CMOS. The single loop 3 b modulator features 14 b and 13 b dynamic range over 276 kHz and 1.1 MHz signal bandwidths, respectively. Clocked at 105 MHz, the ADC core consumes 8 mW from a 1.5 V supply. | H91: Gaggl, R.; Inversi, M.; Wiesbauer, A. | I91: 10.1109/ISSCC.2004.1332604 | J91: =IF(I91<>"?", HYPERLINK(CONCATENATE("https://doi.org/",I91)), "") -> https://doi.org/10.1109/ISSCC.2004.1332604 | K91: Data for BW=1.1MHz | L91: 1.5 | R91: 1100000 | S91: 76 | T91: 78 | U91: 82 | X91: =+IF(ISNUMBER($S91),$S91,MIN($V91,$T91,$U91,$W91)) -> 76 | Y91: 0.015 | Z91: 105000000 | AA91: 47.727273 | AB91: =Z91/AA91 -> 2200000 | AD91: =Y91/AB91*1000000000000 -> 6818.1818 | AE91: =IF(ISNUMBER($Q91), $AD91*1000/2^(($Q91-1.76)/6.02), "") | AF91: =$AD91*1000/2^(($X91-1.76)/6.02) -> 1322.2046 | AG91: =IF(ISNUMBER($Q91), $Q91+10*LOG10($AB91/2/$Y91), "") | AH91: =$X91+10*LOG10($AB91/2/$Y91) -> 154.65301 | AI91: =AF91/AB91 -> 0.00060100209 | AJ91: =AH91+10*LOG10(AB91) -> 218.07724
A92: 2004 | B92: 4.7 | C92: OS | D92: SDSC, BP | E92: 0.18 | F92: A mirror image free two-path bandpass ΣΔ modulator with 72 dB SNR and 86 dB SFDR | G92: A cross-coupled two-path ΣΔ architecture generates transmission zeros at 1/3 of the clock frequency, thereby achieving a mirror image free response. The chip uses 0.18 μm CMOS technology and is clocked at 2×60 MHz with a 40 MHz IF. The modulator achieves an 86 dB SFDR with a 2.5 MHz bandwidth and consumes 150 mW from a 1.8 V supply. | H92: Ying, F.; Maloberti, F. | I92: 10.1109/ISSCC.2004.1332605 | J92: =IF(I92<>"?", HYPERLINK(CONCATENATE("https://doi.org/",I92)), "") -> https://doi.org/10.1109/ISSCC.2004.1332605 | L92: 1.8 | P92: 1.1 | R92: 2500000 | T92: 72 | W92: 86 | X92: =+IF(ISNUMBER($S92),$S92,MIN($V92,$T92,$U92,$W92)) -> 72 | Y92: 0.15 | Z92: 120000000 | AA92: 24 | AB92: =Z92/AA92 -> 5000000 | AC92: 40000000 | AD92: =Y92/AB92*1000000000000 -> 30000 | AE92: =IF(ISNUMBER($Q92), $AD92*1000/2^(($Q92-1.76)/6.02), "") | AF92: =$AD92*1000/2^(($X92-1.76)/6.02) -> 9220.8567 | AG92: =IF(ISNUMBER($Q92), $Q92+10*LOG10($AB92/2/$Y92), "") | AH92: =$X92+10*LOG10($AB92/2/$Y92) -> 144.21849 | AI92: =AF92/AB92 -> 0.0018441713 | AJ92: =AH92+10*LOG10(AB92) -> 211.20819
A93: 2004 | B93: 4.8 | C93: OS | D93: SDCT | E93: 0.18 | F93: A 2 mW 89 dB DR continuous-time ΣΔ ADC with increased immunity to wide-band interferers | G93: A continuous-time ΣΔ ADC with merged channel filter and programmable-gain functionality is presented. Interferers above full-scale can be applied without jeopardizing reception of weak desired signals. The merged design occupies 0.14 mm² in 0.18 μm CMOS, consumes 2 mW, and achieves 89 dB of dynamic range (DR) in a 1 MHz bandwidth. | H93: Philips, K.; Nuijten, P.A.C.M.; Roovers, R.; Munoz, F.; Tejero, M.; Torralba, A. | I93: 10.1109/ISSCC.2004.1332606 | J93: =IF(I93<>"?", HYPERLINK(CONCATENATE("https://doi.org/",I93)), "") -> https://doi.org/10.1109/ISSCC.2004.1332606 | K93: DR=89dB, DRinst=68dB | P93: 0.14 | R93: 1000000 | S93: 65 | U93: 68 | X93: =+IF(ISNUMBER($S93),$S93,MIN($V93,$T93,$U93,$W93)) -> 65 | Y93: =0.00115*1.8 -> 0.00207 | Z93: 64000000 | AA93: 32 | AB93: =Z93/AA93 -> 2000000 | AD93: =Y93/AB93*1000000000000 -> 1035 | AE93: =IF(ISNUMBER($Q93), $AD93*1000/2^(($Q93-1.76)/6.02), "") | AF93: =$AD93*1000/2^(($X93-1.76)/6.02) -> 712.23817 | AG93: =IF(ISNUMBER($Q93), $Q93+10*LOG10($AB93/2/$Y93), "") | AH93: =$X93+10*LOG10($AB93/2/$Y93) -> 151.8403 | AI93: =AF93/AB93 -> 0.00035611909 | AJ93: =AH93+10*LOG10(AB93) -> 214.8506
A94: 2004 | B94: 14.1 | C94: NQ | D94: Folding, TI | E94: 0.18 | F94: A 1.8V 1.6GS/s 8b self-calibrating folding ADC with 7.26 ENOB at Nyquist frequency | G94: A 1.8V folding-interpolating ADC in 0.18μm CMOS uses small device sizes to achieve a conversion rate exceeding 1.6GS/s. The inherent mismatch offsets are calibrated transparently, and at 1.6GS/s the ADC achieves 0.15LSB DNL, 0.35LSB INL, 7.5 ENOB at 100MHz input, and 7.26 ENOB at Nyquist. | H94: Robert Taft, Chris Menkus, Maria Rosaria Tursi, Ols Hidri, and Valerie Pons | I94: 10.1109/ISSCC.2004.1332689 | J94: =IF(I94<>"?", HYPERLINK(CONCATENATE("https://doi.org/",I94)), "") -> https://doi.org/10.1109/ISSCC.2004.1332689 | P94: 8 | R94: 800000000 | T94: 45.8 | V94: 56 | W94: 55 | X94: =+IF(ISNUMBER($S94),$S94,MIN($V94,$T94,$U94,$W94)) -> 45.8 | Y94: =1.8*(501+204)*0.001 -> 1.269 | Z94: =1600000000 -> 1600000000 | AA94: 1 | AB94: =Z94/AA94 -> 1600000000 | AD94: =Y94/AB94*1000000000000 -> 793.125 | AE94: =IF(ISNUMBER($Q94), $AD94*1000/2^(($Q94-1.76)/6.02), "") | AF94: =$AD94*1000/2^(($X94-1.76)/6.02) -> 4978.7716 | AG94: =IF(ISNUMBER($Q94), $Q94+10*LOG10($AB94/2/$Y94), "") | AH94: =$X94+10*LOG10($AB94/2/$Y94) -> 133.79628 | AI94: =AF94/AB94 -> 3.1117322e-06 | AJ94: =AH94+10*LOG10(AB94) -> 225.83748
A95: 2004 | B95: 14.2 | C95: NQ | D95: Folding | E95: 0.18 | F95: An 8b 600MS/s 200mW CMOS folding A/D converter using an amplifier preset technique | G95: An 8b CMOS folding ADC with resistive averaging and interpolation exhibits 7.5 ENOB and a maximum sample frequency of 600MS/s while dissipating only 200mW. The ADC utilizes preset switches at the outputs of the pre-amplifiers. Chip area is 0.2mm², and supply voltage is 3.3/1.8V in 0.35/0.18μm CMOS. | H95: Govert Geelen and Edward Paulus | I95: 10.1109/ISSCC.2004.1332690 | J95: =IF(I95<>"?", HYPERLINK(CONCATENATE("https://doi.org/",I95)), "") -> https://doi.org/10.1109/ISSCC.2004.1332690 | L95: 3.3 | M95: 1.8 | P95: 0.2 | R95: 300000000 | S95: =7.5*6.02+1.76 -> 46.91 | X95: =+IF(ISNUMBER($S95),$S95,MIN($V95,$T95,$U95,$W95)) -> 46.91 | Y95: 0.2 | Z95: 600000000 | AA95: 1 | AB95: =Z95/AA95 -> 600000000 | AD95: =Y95/AB95*1000000000000 -> 333.33333 | AE95: =IF(ISNUMBER($Q95), $AD95*1000/2^(($Q95-1.76)/6.02), "") | AF95: =$AD95*1000/2^(($X95-1.76)/6.02) -> 1841.4239 | AG95: =IF(ISNUMBER($Q95), $Q95+10*LOG10($AB95/2/$Y95), "") | AH95: =$X95+10*LOG10($AB95/2/$Y95) -> 138.67091 | AI95: =AF95/AB95 -> 3.0690398e-06 | AJ95: =AH95+10*LOG10(AB95) -> 226.45243
A96: 2004 | B96: 14.3 | C96: NQ | D96: Pipe | E96: 0.13 | F96: A 1.2V 220MS/s 10b pipeline ADC implemented in 0.13µm digital CMOS | G96: A 10b pipeline ADC fabricated in a 0.13μm pure digital CMOS process is presented. The supply voltage is 1.2V and the conversion rate is 120MS/s. The ADC maintains its performance down to 0.9V supply voltage and up to 220MS/s at a signal swing near full scale. Power consumption at 220MS/s is 135mW. | H96: Bjørnar Hernes, Atle Briskemyr, Terje N. Andersen, Frode Telstø, Thomas E. Bonnerud, and Øystein Moldsvor, | I96: 10.1109/ISSCC.2004.1332691 | J96: =IF(I96<>"?", HYPERLINK(CONCATENATE("https://doi.org/",I96)), "") -> https://doi.org/10.1109/ISSCC.2004.1332691 | L96: 0.9 | P96: 1.3 | R96: 110000000 | S96: 51 | X96: =+IF(ISNUMBER($S96),$S96,MIN($V96,$T96,$U96,$W96)) -> 51 | Y96: 0.135 | Z96: 220000000 | AA96: 1 | AB96: =Z96/AA96 -> 220000000 | AD96: =Y96/AB96*1000000000000 -> 613.63636 | AE96: =IF(ISNUMBER($Q96), $AD96*1000/2^(($Q96-1.76)/6.02), "") | AF96: =$AD96*1000/2^(($X96-1.76)/6.02) -> 2116.7313 | AG96: =IF(ISNUMBER($Q96), $Q96+10*LOG10($AB96/2/$Y96), "") | AH96: =$X96+10*LOG10($AB96/2/$Y96) -> 140.11059 | AI96: =AF96/AB96 -> 9.6215061e-06 | AJ96: =AH96+10*LOG10(AB96) -> 223.53482
A97: 2004 | B97: 14.4 | C97: NQ | D97: Pipe, TI | E97: 0.18 | F97: A 150MS/s 8b 71mW time-interleaved ADC in 0.18µm CMOS | G97: This paper presents a 150 MS/s 8 bit time-interleaved ADC which has been built in 0.18 μm CMOS. Segmentation of the track-and-hold into separate circuits, driving the 1st stage comparators and two interleaved residue paths, together with signal scaling, results in a 45.4 dB SNDR for an 80 MHz input frequency, while dissipating 71 mW from a 1.8 V supply. | H97: Sotirios Limotyrakis, Scott D. Kulchycki, David Su, and Bruce A. Wooley, | I97: 10.1109/ISSCC.2004.1332692 | J97: =IF(I97<>"?", HYPERLINK(CONCATENATE("https://doi.org/",I97)), "") -> https://doi.org/10.1109/ISSCC.2004.1332692 | L97: 1.8 | P97: 1.8 | R97: 75000000 | S97: 45.4 | W97: 52.5 | X97: =+IF(ISNUMBER($S97),$S97,MIN($V97,$T97,$U97,$W97)) -> 45.4 | Y97: 0.071 | Z97: 150000000 | AA97: 1 | AB97: =Z97/AA97 -> 150000000 | AD97: =Y97/AB97*1000000000000 -> 473.33333 | AE97: =IF(ISNUMBER($Q97), $AD97*1000/2^(($Q97-1.76)/6.02), "") | AF97: =$AD97*1000/2^(($X97-1.76)/6.02) -> 3111.3556 | AG97: =IF(ISNUMBER($Q97), $Q97+10*LOG10($AB97/2/$Y97), "") | AH97: =$X97+10*LOG10($AB97/2/$Y97) -> 135.63803 | AI97: =AF97/AB97 -> 2.074237e-05 | AJ97: =AH97+10*LOG10(AB97) -> 217.39894
A98: 2004 | B98: 14.5 | C98: NQ | D98: Two-Step | E98: 0.13 | F98: A 21mW 8b 125MS/s ADC occupying 0.09mm² in 0.13µm CMOS | G98: An 8b subranging ADC uses interpolation, averaging, offset compensation and pipelining techniques to accomplish 7.6b ENOB at 125MS/s. The 0.13μm CMOS ADC occupies 0.09mm² and consumes 21 mW. | H98: Jan Mulder, Christopher M. Ward, Chi-Hung Lin, Dave Kruse, Jan R. Westra, Marcel L. Lugthart, Erol Arslan, Rudy J. van de Plassche, Klaas Bult, and Frank M. L. van der Goes, | I98: 10.1109/ISSCC.2004.1332693 | J98: =IF(I98<>"?", HYPERLINK(CONCATENATE("https://doi.org/",I98)), "") -> https://doi.org/10.1109/ISSCC.2004.1332693 | P98: 0.09 | R98: 62500000 | S98: =7.6*6.02+1.76 -> 47.512 | X98: =+IF(ISNUMBER($S98),$S98,MIN($V98,$T98,$U98,$W98)) -> 47.512 | Y98: 0.021 | Z98: 125000000 | AA98: 1 | AB98: =Z98/AA98 -> 125000000 | AD98: =Y98/AB98*1000000000000 -> 168 | AE98: =IF(ISNUMBER($Q98), $AD98*1000/2^(($Q98-1.76)/6.02), "") | AF98: =$AD98*1000/2^(($X98-1.76)/6.02) -> 865.92707 | AG98: =IF(ISNUMBER($Q98), $Q98+10*LOG10($AB98/2/$Y98), "") | AH98: =$X98+10*LOG10($AB98/2/$Y98) -> 142.24861 | AI98: =AF98/AB98 -> 6.9274165e-06 | AJ98: =AH98+10*LOG10(AB98) -> 223.21771
A99: 2004 | B99: 14.6 | C99: NQ | D99: Flash | E99: 0.12 SiGe | F99: A 3b 40GS/s ADC-DAC in 0.12µm SiGe | G99: A 3b SiGe ADC-DAC produces a conversion rate of 40GS/s with >200 dynamic range over 12GHz bandwidth for receiver exciter applications. The 40GHz design and test methodology, as well as a new wideband quantizer front end, are described. | H99: William Cheng, Wais Ali, Moon-Jung Choi, Kanon Liu, Tammy Tat, Don Devendorf, Lloyd Linder, and Ronald Stevens, | I99: 10.1109/ISSCC.2004.1332694 | J99: =IF(I99<>"?", HYPERLINK(CONCATENATE("https://doi.org/",I99)), "") -> https://doi.org/10.1109/ISSCC.2004.1332694 | P99: 3.96 | R99: 13000000000 | S99: 20 | X99: =+IF(ISNUMBER($S99),$S99,MIN($V99,$T99,$U99,$W99)) -> 20 | Y99: 3.8 | Z99: 40000000000 | AA99: 1 | AB99: =Z99/AA99 -> 40000000000 | AD99: =Y99/AB99*1000000000000 -> 95 | AE99: =IF(ISNUMBER($Q99), $AD99*1000/2^(($Q99-1.76)/6.02), "") | AF99: =$AD99*1000/2^(($X99-1.76)/6.02) -> 11631.42 | AG99: =IF(ISNUMBER($Q99), $Q99+10*LOG10($AB99/2/$Y99), "") | AH99: =$X99+10*LOG10($AB99/2/$Y99) -> 117.21246 | AI99: =AF99/AB99 -> 2.9078549e-07 | AJ99: =AH99+10*LOG10(AB99) -> 223.23306
A100: 2004 | B100: 14.7 | C100: NQ | D100: SAR, TI | E100: 0.09 | F100: A 6b 600MHz 10mW ADC array in digital 90nm CMOS | G100: A 6b converter array operates at a 600MHz clock frequency with input signals up to 600MHz and only 10mW power consumption. The array consists of 8 interleaved successive approximation converters implemented in a 90nm digital CMOS technology. | H100: Dieter Draxelmayr | I100: 10.1109/ISSCC.2004.1332695 | J100: =IF(I100<>"?", HYPERLINK(CONCATENATE("https://doi.org/",I100)), "") -> https://doi.org/10.1109/ISSCC.2004.1332695 | R100: 300000000 | S100: 31 | X100: =+IF(ISNUMBER($S100),$S100,MIN($V100,$T100,$U100,$W100)) -> 31 | Y100: 0.01 | Z100: 600000000 | AA100: 1 | AB100: =Z100/AA100 -> 600000000 | AD100: =Y100/AB100*1000000000000 -> 16.666667 | AE100: =IF(ISNUMBER($Q100), $AD100*1000/2^(($Q100-1.76)/6.02), "") | AF100: =$AD100*1000/2^(($X100-1.76)/6.02) -> 575.04662 | AG100: =IF(ISNUMBER($Q100), $Q100+10*LOG10($AB100/2/$Y100), "") | AH100: =$X100+10*LOG10($AB100/2/$Y100) -> 135.77121 | AI100: =AF100/AB100 -> 9.5841104e-07 | AJ100: =AH100+10*LOG10(AB100) -> 223.55273
...

Sheet VLSI
A1: YEAR | B1: ID | C1: TYPE | D1: ARCHITECTURE | E1: TECHNOLOGY | F1: TITLE | G1: ABSTRACT | H1: AUTHORS | I1: DOI | J1: LINK | K1: COMMENTS | L1: VSUP1 [V] | M1: VSUP2 [V] | N1: VSUP3 [V] | O1: Csamp [pF] | P1: AREA [mm^2] | Q1: SNDR_lf [dB] | R1: fin_hf [Hz] | S1: SNDR_hf [dB] | T1: SNR [dB] | U1: DR [dB] | V1: -THD [dB] | W1: SFDR [dB] | X1: SNDR_plot [dB] | Y1: P [W] | Z1: fs [Hz] | AA1: OSR | AB1: fsnyq [Hz] | AC1: fcenter [Hz] | AD1: P/fsnyq [pJ] | AE1: FOMW_lf [fJ/conv-step] | AF1: FOMW_hf [fJ/conv-step] | AG1: FOMS_lf [dB] | AH1: FOMS_hf [dB] | AI1: FOMW_hf/fsnyq | AJ1: FOMS,hf+10log(fsnyq)
A2: 1997 | B2: 3.2 | C2: OS | D2: SDCT | E2: 0.5 | F2: 1.2-V, 16-bit Audio A/D Converter With Suppressed Latch Error Noise | G2: We have improved the noise-shaping signal flow in order to solve the latch error problem at low voltage supply and have fabricated a 1.2-V, 16-bit swing-suppression A/D converter for audio. The converter achieves S/(N+THD) of 91.5 dB, DR of 94.0 dB, and low power consumption of 6.5 mW. | H2: Matsuya, Y. Terada, J. | I2: 10.1109/VLSIC.1997.623781 | J2: =IF(I2<>"?", HYPERLINK(CONCATENATE("https://doi.org/",I2)), "") -> https://doi.org/10.1109/VLSIC.1997.623781 | L2: 1.2 | R2: 20000 | S2: 91.5 | T2: 92 | U2: 94 | X2: =+IF(ISNUMBER($S2),$S2,MIN($V2,$T2,$U2,$W2)) -> 91.5 | Y2: 0.0065 | Z2: 6140000 | AA2: 153.5 | AB2: =Z2/AA2 -> 40000 | AD2: =Y2/AB2*1000000000000 -> 162500 | AE2: =IF(ISNUMBER($Q2),$AD2*1000/2^(($Q2-1.76)/6.02), "") | AF2: =$AD2*1000/2^(($X2-1.76)/6.02) -> 5289.3977 | AG2: =IF(ISNUMBER($Q2), $Q2+10*LOG10($AB2/2/$Y2), "") | AH2: =$X2+10*LOG10($AB2/2/$Y2) -> 156.38117 | AI2: =AF2/AB2 -> 0.13223494 | AJ2: =AH2+10*LOG10(AB2) -> 202.40177
A3: 1997 | B3: 3.4 | C3: NQ | D3: Folding, TI | E3: Bipolar | F3: An 8-GSa/s 8-bit ADC System | G3: We report on an analog to digital converter (ADC) system with 8 bit resolution and a sample rate of 8 GSa/s. The system is composed of 2 thick-fh hybrid substrates, each holding a silicon bipolar ADC chip and a custom CMOS memory chip. Each ADC chip contains two differential track and hold circuits and two folding and interpolating 2 GSa/s flash digitizers. The custom memory chip accepts data at 2 GSa/s on each of two input ports, and stores the data in a 256 Kbit S U M . The ADC system uses time interleaving of 4 paths to reach 8 GSa/s and combines hardware dither with software calibration techniques to achieve 7.6 effective bits at low frequencies and 5.3 effective bits at 2 GHz input. | H3: K. Poulton, K.L. Knudsen, J. Kerley, J. Kang, J. Tani, E. Cornish, M. VanGrouw | I3: 10.1109/VLSIC.1997.623783 | J3: =IF(I3<>"?", HYPERLINK(CONCATENATE("https://doi.org/",I3)), "") -> https://doi.org/10.1109/VLSIC.1997.623783 | K3: Software calibration | P3: 29.68 | Q3: =7.5*6.02+1.76 -> 46.91 | R3: 4000000000 | S3: =3.7*6.02+1.76 -> 24.034 | X3: =+IF(ISNUMBER($S3),$S3,MIN($V3,$T3,$U3,$W3)) -> 24.034 | Y3: 12.5 | Z3: 8000000000 | AA3: 1 | AB3: =Z3/AA3 -> 8000000000 | AD3: =Y3/AB3*1000000000000 -> 1562.5 | AE3: =IF(ISNUMBER($Q3),$AD3*1000/2^(($Q3-1.76)/6.02), "") -> 8631.6746 | AF3: =$AD3*1000/2^(($X3-1.76)/6.02) -> 120228.95 | AG3: =IF(ISNUMBER($Q3), $Q3+10*LOG10($AB3/2/$Y3), "") -> 131.9615 | AH3: =$X3+10*LOG10($AB3/2/$Y3) -> 109.0855 | AI3: =AF3/AB3 -> 1.5028618e-05 | AJ3: =AH3+10*LOG10(AB3) -> 208.1164
A4: 1998 | B4: 14.2 | C4: NQ | D4: Pipe | E4: 0.6 | F4: A 1.5 V, 10-bit, 14 MS/s CMOS pipeline analog-to-digital converter | G4: A 1.5 V, 10-bit, 14.3 MS/s pipeline analog-to-digital converter was implemented in a 0.6 μm CMOS technology. Emphasis was placed on observing device reliability constraints at low voltage. MOS switches were implemented without low-threshold devices by using a bootstrapping technique that does not subject the devices to large terminal voltages. The converter achieved a peak SNDR of 58.5 dB, maximum DNL of 0.51 LSB, maximum INL of 0.66 LSB and a power consumption of 36 mW | H4: A.M. Abo, P.R. Gray | I4: 10.1109/VLSIC.1998.688071 | J4: =IF(I4<>"?", HYPERLINK(CONCATENATE("https://doi.org/",I4)), "") -> https://doi.org/10.1109/VLSIC.1998.688071 | L4: 1.5 | P4: 5.75 | R4: =14300000/2 -> 7150000 | S4: 58.5 | X4: =+IF(ISNUMBER($S4),$S4,MIN($V4,$T4,$U4,$W4)) -> 58.5 | Y4: 0.036 | Z4: 14300000 | AA4: 1 | AB4: =Z4/AA4 -> 14300000 | AD4: =Y4/AB4*1000000000000 -> 2517.4825 | AE4: =IF(ISNUMBER($Q4),$AD4*1000/2^(($Q4-1.76)/6.02), "") | AF4: =$AD4*1000/2^(($X4-1.76)/6.02) -> 3661.7083 | AG4: =IF(ISNUMBER($Q4), $Q4+10*LOG10($AB4/2/$Y4), "") | AH4: =$X4+10*LOG10($AB4/2/$Y4) -> 141.48004 | AI4: =AF4/AB4 -> 0.00025606352 | AJ4: =AH4+10*LOG10(AB4) -> 213.0334
A5: 1998 | B5: 14.3 | C5: NQ | D5: Two-Step, Pipe | E5: 0.25 BiCMOS | F5: A 2.5 V 100 MS/s 8 bit ADC using pre-linearization input buffer andlevel up DAC/subtractor | G5: This paper describes a 2.5 V 100 MS/s 8 bit subranging Analog-to-Digital Converter (ADC). To achieve such low voltage operation and high-speed conversion rate at the same time, a “pre-linearization input buffer” and “level up DAC/subtractor” have been newly developed. These circuits prevent voltage drops on the internal analog signal path and make the supply voltage reduction possible. The ADC also uses a simple encoder scheme “noise immunity encoder” that is resistant to bubbling error for thermometer code | H5: Sugawara, M. Yoshida, H. Mitsuishi, M. Nakamura, S. Nakaigawa, S. Kunisaki, Y. Suzuki, H. | I5: 10.1109/VLSIC.1998.688073 | J5: =IF(I5<>"?", HYPERLINK(CONCATENATE("https://doi.org/",I5)), "") -> https://doi.org/10.1109/VLSIC.1998.688073 | L5: 2.5 | P5: 3.3 | R5: =100000000/2 -> 50000000 | S5: 43.3 | X5: =+IF(ISNUMBER($S5),$S5,MIN($V5,$T5,$U5,$W5)) -> 43.3 | Y5: 0.18 | Z5: 100000000 | AA5: 1 | AB5: =Z5/AA5 -> 100000000 | AD5: =Y5/AB5*1000000000000 -> 1800 | AE5: =IF(ISNUMBER($Q5),$AD5*1000/2^(($Q5-1.76)/6.02), "") | AF5: =$AD5*1000/2^(($X5-1.76)/6.02) -> 15068.344 | AG5: =IF(ISNUMBER($Q5), $Q5+10*LOG10($AB5/2/$Y5), "") | AH5: =$X5+10*LOG10($AB5/2/$Y5) -> 127.73697 | AI5: =AF5/AB5 -> 0.00015068344 | AJ5: =AH5+10*LOG10(AB5) -> 207.73697
A6: 1998 | B6: 14.4 | C6: OS | D6: SDCT, BP | E6: 0.5 SiGe | F6: A 4 GHz fourth-order SiGe HBT band pass ΔΣ modulator | G6: Test results for a fourth-order band pass (BP) ΔΣ modulator (ΔΣM) are presented. The 0.5 μm SiGe HBT design uses active LC resonators with Q enhancement and return-to-zero latches to drive the feedback DACs. The packaged circuit consumes 350 mW from a single 5 V supply when clocking at 4 GHz. Measured results indicate a maximum SNR of 53 dB, SFDR of 69 dB, and a dynamic range of 62 dB, all in a 4 MHz bandwidth | H6: Weinan Gao Cherry, J.A. Snelgrove, W.M. | I6: 10.1109/VLSIC.1998.688074 | J6: =IF(I6<>"?", HYPERLINK(CONCATENATE("https://doi.org/",I6)), "") -> https://doi.org/10.1109/VLSIC.1998.688074 | L6: 5 | P6: 1.24 | R6: 4000000 | T6: 53 | U6: 62 | W6: 69 | X6: =+IF(ISNUMBER($S6),$S6,MIN($V6,$T6,$U6,$W6)) -> 53 | Y6: 0.35 | Z6: 4000000000 | AA6: 500 | AB6: =Z6/AA6 -> 8000000 | AC6: 1000000000 | AD6: =Y6/AB6*1000000000000 -> 43750 | AE6: =IF(ISNUMBER($Q6),$AD6*1000/2^(($Q6-1.76)/6.02), "") | AF6: =$AD6*1000/2^(($X6-1.76)/6.02) -> 119873.38 | AG6: =IF(ISNUMBER($Q6), $Q6+10*LOG10($AB6/2/$Y6), "") | AH6: =$X6+10*LOG10($AB6/2/$Y6) -> 123.57992 | AI6: =AF6/AB6 -> 0.014984172 | AJ6: =AH6+10*LOG10(AB6) -> 192.61082
A7: 1999 | B7: 8.2 | C7: NQ | D7: Pipe | E7: Bipolar | F7: An 8 b 500 MS/s full Nyquist cascade A/D converter | G7: An 8 b 500 MS/s one-bit-per-stage cascade A/D converter (ADC) has been developed. We achieved 500 MHz one-clock conversion of all the cascade stages with a novel error suppression technique. The measured SNDR is 47 dB (7.6 effective bits) at a 100 kHz input, keeping more than 45 dB (7.2 effective bits) up to the Nyquist frequency. The power dissipation and the active area of the ADC core, including a 1.5 GHz bandwidth sample-and-hold amplifier, are 950 mW from a +2 V/-3.3 V supply and 5.5 mm², respectively | H7: K. Irie, N. Kusayanagi, T. Kawachi, T. Nishibu, Y. Matsumori | I7: 10.1109/VLSIC.1999.797241 | J7: =IF(I7<>"?", HYPERLINK(CONCATENATE("https://doi.org/",I7)), "") -> https://doi.org/10.1109/VLSIC.1999.797241 | L7: 2 | M7: -3.3 | P7: 5.5 | R7: 250000000 | S7: 45 | X7: =+IF(ISNUMBER($S7),$S7,MIN($V7,$T7,$U7,$W7)) -> 45 | Y7: 0.95 | Z7: 500000000 | AA7: 1 | AB7: =Z7/AA7 -> 500000000 | AD7: =Y7/AB7*1000000000000 -> 1900 | AE7: =IF(ISNUMBER($Q7),$AD7*1000/2^(($Q7-1.76)/6.02), "") | AF7: =$AD7*1000/2^(($X7-1.76)/6.02) -> 13077.904 | AG7: =IF(ISNUMBER($Q7), $Q7+10*LOG10($AB7/2/$Y7), "") | AH7: =$X7+10*LOG10($AB7/2/$Y7) -> 129.20216 | AI7: =AF7/AB7 -> 2.6155808e-05 | AJ7: =AH7+10*LOG10(AB7) -> 216.19186
A8: 1999 | B8: 8.3 | C8: NQ | D8: Flash | E8: 0.35 | F8: A 1 V 6 b 50 MHz current-interpolating CMOS ADC | G8: A current-interpolation technique is used to implement a 6 b 50 MHz ADC operable with a single battery cell as low as 0.9 V without charge pumping. The prototype chip, fabricated in a 0.35 μm standard digital process, occupies an area of 2.4 mm×2 mm, and consumes 10 mW each in analog and digital supplies, respectively | H8: Bang-Sup Song Myung-Jun Choe Rakers, P. Gillig, S. | I8: 10.1109/VLSIC.1999.797242 | J8: =IF(I8<>"?", HYPERLINK(CONCATENATE("https://doi.org/",I8)), "") -> https://doi.org/10.1109/VLSIC.1999.797242 | P8: 4.8 | R8: 25000000 | S8: 33.5 | X8: =+IF(ISNUMBER($S8),$S8,MIN($V8,$T8,$U8,$W8)) -> 33.5 | Y8: 0.02 | Z8: 50000000 | AA8: 1 | AB8: =Z8/AA8 -> 50000000 | AD8: =Y8/AB8*1000000000000 -> 400 | AE8: =IF(ISNUMBER($Q8),$AD8*1000/2^(($Q8-1.76)/6.02), "") | AF8: =$AD8*1000/2^(($X8-1.76)/6.02) -> 10349.082 | AG8: =IF(ISNUMBER($Q8), $Q8+10*LOG10($AB8/2/$Y8), "") | AH8: =$X8+10*LOG10($AB8/2/$Y8) -> 124.4691 | AI8: =AF8/AB8 -> 0.00020698165 | AJ8: =AH8+10*LOG10(AB8) -> 201.4588
A9: 1999 | B9: 8.4 | C9: NQ | D9: Pipe, Folding | E9: 0.5 | F9: An 8 b 100 MSample/s CMOS pipelined folding ADC | G9: When applied to folding ADCs, pipelining relieves the wide bandwidth requirement of the folding amplifier. A pipelined folding ADC prototyped using a 0.5 μm CMOS process exhibits a DNL of ±0.4 LSB and an INL of ±1.3 LSB at 100 MSample/s. The chip occupies 1.4 mm×1.2 mm in active area and consumes 165 mW at 5 V | H9: Myung-Jun Choe Bang-Sup Song Bacrania, K. | I9: 10.1109/VLSIC.1999.797243 | J9: =IF(I9<>"?", HYPERLINK(CONCATENATE("https://doi.org/",I9)), "") -> https://doi.org/10.1109/VLSIC.1999.797243 | P9: 1.68 | R9: 50000000 | S9: 42.3 | T9: 46.5 | X9: =+IF(ISNUMBER($S9),$S9,MIN($V9,$T9,$U9,$W9)) -> 42.3 | Y9: 0.165 | Z9: 100000000 | AA9: 1 | AB9: =Z9/AA9 -> 100000000 | AD9: =Y9/AB9*1000000000000 -> 1650 | AE9: =IF(ISNUMBER($Q9),$AD9*1000/2^(($Q9-1.76)/6.02), "") | AF9: =$AD9*1000/2^(($X9-1.76)/6.02) -> 15498.224 | AG9: =IF(ISNUMBER($Q9), $Q9+10*LOG10($AB9/2/$Y9), "") | AH9: =$X9+10*LOG10($AB9/2/$Y9) -> 127.11486 | AI9: =AF9/AB9 -> 0.00015498224 | AJ9: =AH9+10*LOG10(AB9) -> 207.11486
A10: 2000 | B10: 11.1 | C10: OS | D10: SDSC | E10: 0.25 | F10: A 50-mW 14-bit 2.5-MS/s Σ-Δ modulator in a 0.25 μm digital CMOS technology | G10: A 5th-order single-loop Σ-Δ modulator has been implemented in a 0.25 μm digital CMOS process, where the supply voltage is only 2.5 V and the capacitor option is not available. A tri-level quantizer is used to improve loop stability. The sampling frequency of the modulator is 80 MHz and the oversampling ratio is 32. Measured over a 1 MHz signal bandwidth, dynamic range is 86 dB, peak SNR is 80 dB and peak SNDR is 78 dB. The modulator consumes only 50 mW | H10: Balmelli, P. Qiuting Huang Piazza, F. | I10: 10.1109/VLSIC.2000.852873 | J10: =IF(I10<>"?", HYPERLINK(CONCATENATE("https://doi.org/",I10)), "") -> https://doi.org/10.1109/VLSIC.2000.852873 | L10: 2.5 | P10: 1.1 | R10: 1000000 | S10: 78 | T10: 80 | X10: =+IF(ISNUMBER($S10),$S10,MIN($V10,$T10,$U10,$W10)) -> 78 | Y10: 0.05 | Z10: 80000000 | AA10: 40 | AB10: =Z10/AA10 -> 2000000 | AD10: =Y10/AB10*1000000000000 -> 25000 | AE10: =IF(ISNUMBER($Q10),$AD10*1000/2^(($Q10-1.76)/6.02), "") | AF10: =$AD10*1000/2^(($X10-1.76)/6.02) -> 3850.8813 | AG10: =IF(ISNUMBER($Q10), $Q10+10*LOG10($AB10/2/$Y10), "") | AH10: =$X10+10*LOG10($AB10/2/$Y10) -> 151.0103 | AI10: =AF10/AB10 -> 0.0019254406 | AJ10: =AH10+10*LOG10(AB10) -> 214.0206
A11: 2000 | B11: 16.1 | C11: NQ | D11: Pipe | E11: 0.6 BiCMOS | F11: A 12 b 105 Msample/s, 850 mW analog to digital converter | G11: This analog-to-digital converter achieves a minimum sampling rate of 105 Msample/S at a total power dissipation of 850 mW while achieving 11.0 effective number of bits (SNR=68 dB) and an SFDR of >80 dB for sampling analog input frequencies up to 70 MHz. The converter uses a switched capacitor multi-bit per stage architecture and incorporates an on-chip differential input buffer, a dedicated track/hold amplifier and an internally compensated wideband differential reference amplifier. The converter is fabricated on a 0.6 μm BiCMOS process | H11: Michalski, C. | I11: 10.1109/VLSIC.2000.852892 | J11: =IF(I11<>"?", HYPERLINK(CONCATENATE("https://doi.org/",I11)), "") -> https://doi.org/10.1109/VLSIC.2000.852892 | R11: =105000000/2 -> 52500000 | T11: 68 | W11: 78 | X11: =+IF(ISNUMBER($S11),$S11,MIN($V11,$T11,$U11,$W11)) -> 68 | Y11: 0.85 | Z11: =105000000 -> 105000000 | AA11: 1 | AB11: =Z11/AA11 -> 105000000 | AD11: =Y11/AB11*1000000000000 -> 8095.2381 | AE11: =IF(ISNUMBER($Q11),$AD11*1000/2^(($Q11-1.76)/6.02), "") | AF11: =$AD11*1000/2^(($X11-1.76)/6.02) -> 3943.661 | AG11: =IF(ISNUMBER($Q11), $Q11+10*LOG10($AB11/2/$Y11), "") | AH11: =$X11+10*LOG10($AB11/2/$Y11) -> 145.9074 | AI11: =AF11/AB11 -> 3.7558676e-05 | AJ11: =AH11+10*LOG10(AB11) -> 226.1193
A12: 2000 | B12: 16.2 | C12: NQ | D12: Folding | E12: 0.35 | F12: An 8-bit 125 MS/s CMOS folding ADC for Gigabit Ethernet LSI | G12: An 8-bit 125 MS/s CMOS folding ADC using an equalizing technique is presented, which reduces the settling time of the analog folding processor to obtain a higher sampling rate. The prototype chip, fabricated in a 0.35 μm triple metal digital CMOS process, occupies an area of 0.8 mm² and consumes 110 mW achieving 6.4 effective bits for a Nyquist input signal | H12: Kwangho Yoon Jeongho Lee Deog-Kyoon Jeong Wonchan Kim | I12: 10.1109/VLSIC.2000.852893 | J12: =IF(I12<>"?", HYPERLINK(CONCATENATE("https://doi.org/",I12)), "") -> https://doi.org/10.1109/VLSIC.2000.852893 | P12: 0.8 | R12: =125000000/2 -> 62500000 | S12: 40.2 | X12: =+IF(ISNUMBER($S12),$S12,MIN($V12,$T12,$U12,$W12)) -> 40.2 | Y12: 0.11 | Z12: =125000000 -> 125000000 | AA12: 1 | AB12: =Z12/AA12 -> 125000000 | AD12: =Y12/AB12*1000000000000 -> 880 | AE12: =IF(ISNUMBER($Q12),$AD12*1000/2^(($Q12-1.76)/6.02), "") | AF12: =$AD12*1000/2^(($X12-1.76)/6.02) -> 10526.673 | AG12: =IF(ISNUMBER($Q12), $Q12+10*LOG10($AB12/2/$Y12), "") | AH12: =$X12+10*LOG10($AB12/2/$Y12) -> 127.74487 | AI12: =AF12/AB12 -> 8.4213385e-05 | AJ12: =AH12+10*LOG10(AB12) -> 208.71397
A13: 2001 | B13: 19.2 | C13: NQ | D13: Folding | E13: 0.18 | F13: An 8-bit 30 MS/s 18 mW ADC with 1.8 V single power supply | G13: This paper describes an 8-bit 30 MS/s 18 mW ADC (Analog-to-Digital Converter) with 1.8 V single power supply for battery powered systems. A folding and interpolation architecture with the auto-zeroed amplifiers is newly developed to achieve the low power consumption and the low power supply voltage. A pipelining technique is also introduced to realize that conversion rate with low power consumption. A test chip of the ADC is fabricated in a 0.18 μm CMOS process. The experimental results at 30 MS/s shows DNL less than +/$0.5 LSB, INL less than +/- 1.0 LSB and SNDR more than 45 dB with 3 MHz input frequency | H13: Sigenobu, T. Ito, M. Miki, T. | I13: 10.1109/VLSIC.2001.934241 | J13: =IF(I13<>"?", HYPERLINK(CONCATENATE("https://doi.org/",I13)), "") -> https://doi.org/10.1109/VLSIC.2001.934241 | L13: 1.8 | P13: 0.96 | R13: 15000000 | S13: 45 | X13: =+IF(ISNUMBER($S13),$S13,MIN($V13,$T13,$U13,$W13)) -> 45 | Y13: 0.018 | Z13: 30000000 | AA13: 1 | AB13: =Z13/AA13 -> 30000000 | AD13: =Y13/AB13*1000000000000 -> 600 | AE13: =IF(ISNUMBER($Q13),$AD13*1000/2^(($Q13-1.76)/6.02), "") | AF13: =$AD13*1000/2^(($X13-1.76)/6.02) -> 4129.8645 | AG13: =IF(ISNUMBER($Q13), $Q13+10*LOG10($AB13/2/$Y13), "") | AH13: =$X13+10*LOG10($AB13/2/$Y13) -> 134.20819 | AI13: =AF13/AB13 -> 0.00013766215 | AJ13: =AH13+10*LOG10(AB13) -> 208.9794
A14: 2001 | B14: 19.3 | C14: NQ | D14: Pipe | E14: 0.35 | F14: A 12-bit mismatch-shaped pipeline A/D converter | G14: This paper presents pipeline A/D converters with improved linearity. The linearity improvement is achieved through a combination of oversampling and mismatch shaping, which modulates the distortion energy out-of-band. A 77 dB SFDR is achieved at an oversampling ratio of 4 and a sampling rate of 51 Msample/s, which is a 12 dB improvement compared to a converter with no mismatch shaping. These results were obtained from a test chip fabricated in a 0.35 μm CMOS process | H14: Shabra, A. Hae-Seung Lee | I14: 10.1109/VLSIC.2001.934241 | J14: =IF(I14<>"?", HYPERLINK(CONCATENATE("https://doi.org/",I14)), "") -> https://doi.org/10.1109/VLSIC.2001.934241 | R14: =51000000/2 -> 25500000 | S14: 67 | V14: 75 | W14: 77 | X14: =+IF(ISNUMBER($S14),$S14,MIN($V14,$T14,$U14,$W14)) -> 67 | Y14: =(435+165)*0.001 -> 0.6 | Z14: =51000000 -> 51000000 | AA14: 1 | AB14: =Z14/AA14 -> 51000000 | AD14: =Y14/AB14*1000000000000 -> 11764.706 | AE14: =IF(ISNUMBER($Q14),$AD14*1000/2^(($Q14-1.76)/6.02), "") | AF14: =$AD14*1000/2^(($X14-1.76)/6.02) -> 6430.6668 | AG14: =IF(ISNUMBER($Q14), $Q14+10*LOG10($AB14/2/$Y14), "") | AH14: =$X14+10*LOG10($AB14/2/$Y14) -> 143.28389 | AI14: =AF14/AB14 -> 0.00012609151 | AJ14: =AH14+10*LOG10(AB14) -> 220.35959
A15: 2002 | B15: 23.1 | C15: NQ | D15: Flash | E15: 0.18 | F15: A 6bit 400Msps 70mW ADC using interpolated parallel scheme | G15: The design of a low power 6bit, 400Msps, 1.8V CMOS ADC is presented. This ADC is based on interpolated parallel architecture in which the transistor sizes are optimized to achieve the required linearity and simultaneously minimize the power consumption. When operated at 400Msps with 1.8/2.4V power supply the ADC dissipates 70mW. The ADC is fabricated in a 0.18µm CMOS process. | H15: Ono, K. Shimizu, H. Ogawa, J. Takeda, M. Yano, M. | I15: 10.1109/VLSIC.2002.1015116 | J15: =IF(I15<>"?", HYPERLINK(CONCATENATE("https://doi.org/",I15)), "") -> https://doi.org/10.1109/VLSIC.2002.1015116 | L15: 2.4 | M15: 1.8 | P15: 0.2688 | R15: 200000000 | S15: 31 | T15: 35 | X15: =+IF(ISNUMBER($S15),$S15,MIN($V15,$T15,$U15,$W15)) -> 31 | Y15: 0.07 | Z15: 400000000 | AA15: 1 | AB15: =Z15/AA15 -> 400000000 | AD15: =Y15/AB15*1000000000000 -> 175 | AE15: =IF(ISNUMBER($Q15),$AD15*1000/2^(($Q15-1.76)/6.02), "") | AF15: =$AD15*1000/2^(($X15-1.76)/6.02) -> 6037.9895 | AG15: =IF(ISNUMBER($Q15), $Q15+10*LOG10($AB15/2/$Y15), "") | AH15: =$X15+10*LOG10($AB15/2/$Y15) -> 125.55932 | AI15: =AF15/AB15 -> 1.5094974e-05 | AJ15: =AH15+10*LOG10(AB15) -> 211.57992
A16: 2002 | B16: 23.2 | C16: NQ | D16: Folding | E16: 0.12 | F16: A 1.2 V 10-b 100-MSamples/s A/D converter in 0.12µm CMOS | G16: A CMOS analog-to-digital converter (ADC) utilizing folding, averaging and distributed interpolation is described. Fabricated in a digital 0.12 µm CMOS process, the ADC occupies 0.32 mm² while dissipating 140 mW from a single 1.2 V supply. The experimental results show that the converter achieves 55dB SNR at sampling frequencies up to 100MHz. | H16: Blum, A.S. Engl, B.H. Eichfeld, H.P. Hagelauer, R. Abidi, A.A. | I16: 10.1109/VLSIC.2002.1015117 | J16: =IF(I16<>"?", HYPERLINK(CONCATENATE("https://doi.org/",I16)), "") -> https://doi.org/10.1109/VLSIC.2002.1015117 | L16: 1.2 | P16: 0.32 | R16: 50000000 | S16: =8.83*6.02+1.76 -> 54.9166 | X16: =+IF(ISNUMBER($S16),$S16,MIN($V16,$T16,$U16,$W16)) -> 54.9166 | Y16: 0.18 | Z16: 100000000 | AA16: 1 | AB16: =Z16/AA16 -> 100000000 | AD16: =Y16/AB16*1000000000000 -> 1800 | AE16: =IF(ISNUMBER($Q16),$AD16*1000/2^(($Q16-1.76)/6.02), "") | AF16: =$AD16*1000/2^(($X16-1.76)/6.02) -> 3955.2837 | AG16: =IF(ISNUMBER($Q16), $Q16+10*LOG10($AB16/2/$Y16), "") | AH16: =$X16+10*LOG10($AB16/2/$Y16) -> 139.35357 | AI16: =AF16/AB16 -> 3.9552837e-05 | AJ16: =AH16+10*LOG10(AB16) -> 219.35357
A17: 2003 | B17: 6.1 | C17: NQ | D17: Pipe | E17: 0.18 | F17: A 0.9 V 9 mW 1MSPS digitally calibrated ADC with 75 dB SFDR | G17: A low-voltage two-stage algorithmic ADC incorporating the Opamp-Reset Switching Technique (ORST) is presented. The low-voltage digital CMOS process compatible operation is achieved without the clock boosting/bootstrapping or switched-opamp. The ADC employs a highly linear input sampling circuit at the front-end, and the digital output is calibrated using a radix-based scheme. The prototype was fabricated in a 0.18-µm CMOS technology and the active die area is 1.2 mm⨉1.2 mm. The calibrated ADC demonstrates 75 dB SFDR at 0.9 V and 80 dB SFDR at 1.2 V. The total power consumption of the ADC is 9 mW at the clock frequency of 7 MHz (1MSPS). | H17: Dong-Young Chang; Gil-Cho Ahn; Un-Ku Moon; | I17: 10.1109/VLSIC.2003.1221164 | J17: =IF(I17<>"?", HYPERLINK(CONCATENATE("https://doi.org/",I17)), "") -> https://doi.org/10.1109/VLSIC.2003.1221164 | K17: Calibration | P17: 1.44 | R17: 500000 | S17: 55 | W17: 75 | X17: =+IF(ISNUMBER($S17),$S17,MIN($V17,$T17,$U17,$W17)) -> 55 | Y17: 0.009 | Z17: 1000000 | AA17: 1 | AB17: =Z17/AA17 -> 1000000 | AD17: =Y17/AB17*1000000000000 -> 9000 | AE17: =IF(ISNUMBER($Q17),$AD17*1000/2^(($Q17-1.76)/6.02), "") | AF17: =$AD17*1000/2^(($X17-1.76)/6.02) -> 19587.42 | AG17: =IF(ISNUMBER($Q17), $Q17+10*LOG10($AB17/2/$Y17), "") | AH17: =$X17+10*LOG10($AB17/2/$Y17) -> 132.44727 | AI17: =AF17/AB17 -> 0.01958742 | AJ17: =AH17+10*LOG10(AB17) -> 192.44727
A18: 2003 | B18: 6.2 | C18: OS | D18: SDSC | E18: 0.35 | F18: A 1.8 V, 1 MS/s, 85 dB SNR 2+2 mash ΣΔ modulator with ±0.9 V reference voltage | G18: A 1.8 V, 1 MS/s, 85 dB SNR 2+2 mash ΣΔ modulator with ±0.9 V reference voltage is realized by using the swing reduction structure. This structure limits the output swing of all the integrators within half the reference voltage. Thus, low voltage and high speed operation is possible with even high reference voltage without degrading the performance of the modulator. The circuit is fabricated in CMOS 0.35 µm process with chip size of 2.5⨉2.5 mm². | H18: Kye-Shin Lee Maloberti, F. | I18: 10.1109/VLSIC.2003.1221165 | J18: =IF(I18<>"?", HYPERLINK(CONCATENATE("https://doi.org/",I18)), "") -> https://doi.org/10.1109/VLSIC.2003.1221165 | P18: 6.25 | R18: 500000 | T18: 85.7 | U18: 87 | X18: =+IF(ISNUMBER($S18),$S18,MIN($V18,$T18,$U18,$W18)) -> 85.7 | Y18: 0.15 | Z18: 1000000 | AA18: 1 | AB18: =Z18/AA18 -> 1000000 | AD18: =Y18/AB18*1000000000000 -> 150000 | AE18: =IF(ISNUMBER($Q18),$AD18*1000/2^(($Q18-1.76)/6.02), "") | AF18: =$AD18*1000/2^(($X18-1.76)/6.02) -> 9520.7906 | AG18: =IF(ISNUMBER($Q18), $Q18+10*LOG10($AB18/2/$Y18), "") | AH18: =$X18+10*LOG10($AB18/2/$Y18) -> 150.92879 | AI18: =AF18/AB18 -> 0.0095207906 | AJ18: =AH18+10*LOG10(AB18) -> 210.92879
A19: 2003 | B19: 6.3 | C19: OS | D19: SDCT, Complex, BP | E19: 0.25 | F19: A Fourth Order Continuous-Time Complex Sigma-Delta ADC for Low-IF GSM and EDGE Receivers | G19: A low-power fourth order continuous-time complex ΣΔ ADC has been designed and fabricated for low-IF (LIF) GSM and EDGE receivers in a 0.25 µm CMOS technology. This ADC has a bandwidth of 270 kHz centered around-100 kHz. The dynamic range (DNR) is 82 dB at a sampling rate of 13 MHz even though the digital decimation filter and other blocks are active on the chip. The power consumption is 4.6 mW at 2 V supply. To our knowledge this ADC has the best performance, which has been reported so far with a complex ΣΔ ADC for LIF mode GSM and EDGE receivers. | H19: Farzad Esfahani, Philipp Basedau, Roland Ryter, Rolf Becker | I19: 10.1109/VLSIC.2003.1221166 | J19: =IF(I19<>"?", HYPERLINK(CONCATENATE("https://doi.org/",I19)), "") -> https://doi.org/10.1109/VLSIC.2003.1221166 | L19: 2 | P19: 0.3894 | R19: 270000 | S19: 78.4 | U19: 82 | X19: =+IF(ISNUMBER($S19),$S19,MIN($V19,$T19,$U19,$W19)) -> 78.4 | Y19: 0.0046 | Z19: 13000000 | AA19: 24.074074 | AB19: =Z19/AA19 -> 540000 | AC19: 100000 | AD19: =Y19/AB19*1000000000000 -> 8518.5185 | AE19: =IF(ISNUMBER($Q19),$AD19*1000/2^(($Q19-1.76)/6.02), "") | AF19: =$AD19*1000/2^(($X19-1.76)/6.02) -> 1253.0898 | AG19: =IF(ISNUMBER($Q19), $Q19+10*LOG10($AB19/2/$Y19), "") | AH19: =$X19+10*LOG10($AB19/2/$Y19) -> 156.08606 | AI19: =AF19/AB19 -> 0.0023205367 | AJ19: =AH19+10*LOG10(AB19) -> 213.41
A20: 2004 | B20: 6.1 | C20: NQ | D20: Algorithmic | E20: 0.13 | F20: A calibration-free 3V 16b 500kS/s 6mW 0.5mm² ADC with 0.13 µm CMOS | G20: A calibration-free 3V 6mW 16-bit 500kS/s cyclic ADC with an active die area of 0.5mm² is implemented in a 0.13 µm CMOS. The proposed converter adopts a 2.5-bit/stage cyclic architecture and capacitor layout scheme to achieve improved matching accuracy, the DNL and INL of ±0.90 LSB and ±6.1 LSB, respectively. | H20: Hee-Cheol Choi Seung-Bin You Ho-Young Lee Ho-Jin Park Jae-Whui Kim | I20: 10.1109/VLSIC.2004.1346509 | J20: =IF(I20<>"?", HYPERLINK(CONCATENATE("https://doi.org/",I20)), "") -> https://doi.org/10.1109/VLSIC.2004.1346509 | P20: 0.5 | R20: =500000/2 -> 250000 | S20: 77.4 | V20: 90.2 | X20: =+IF(ISNUMBER($S20),$S20,MIN($V20,$T20,$U20,$W20)) -> 77.4 | Y20: 0.006 | Z20: =500000 -> 500000 | AA20: 1 | AB20: =Z20/AA20 -> 500000 | AD20: =Y20/AB20*1000000000000 -> 12000 | AE20: =IF(ISNUMBER($Q20),$AD20*1000/2^(($Q20-1.76)/6.02), "") | AF20: =$AD20*1000/2^(($X20-1.76)/6.02) -> 1980.6346 | AG20: =IF(ISNUMBER($Q20), $Q20+10*LOG10($AB20/2/$Y20), "") | AH20: =$X20+10*LOG10($AB20/2/$Y20) -> 153.59789 | AI20: =AF20/AB20 -> 0.0039612692 | AJ20: =AH20+10*LOG10(AB20) -> 210.58759
A21: 2004 | B21: 6.2 | C21: OS | D21: SDSC | E21: 0.18 | F21: A third-order ΣΔ modulator in 0.18 µm CMOS with calibrated mixed-mode integrators | G21: A third-order EA modulator employing mixed-mode integrators has been designed and implemented in 0.18um CMOS process. Because the use of mixed-mode integrators allows a 12dB improvement in the dynamic range over conventional third-order architectures, the modulator can be driven with lower sampling frequency to achieve the same dynamic range. The modulator covers the dynamic range requirements of GSM and WCDMA applications with sampling frequencies of only 3.2MHz and 40MHz, respectively. The circuit occupies 0.7mm² silicon area. | H21: Jae Hoon Shim Beomsup Kim | I21: 10.1109/VLSIC.2004.1346510 | J21: =IF(I21<>"?", HYPERLINK(CONCATENATE("https://doi.org/",I21)), "") -> https://doi.org/10.1109/VLSIC.2004.1346510 | K21: GSM mode | P21: 0.7 | R21: 200000 | U21: 76 | X21: =+IF(ISNUMBER($S21),$S21,MIN($V21,$T21,$U21,$W21)) -> 76 | Y21: 0.004 | Z21: 3200000 | AA21: 8 | AB21: =Z21/AA21 -> 400000 | AD21: =Y21/AB21*1000000000000 -> 10000 | AE21: =IF(ISNUMBER($Q21),$AD21*1000/2^(($Q21-1.76)/6.02), "") | AF21: =$AD21*1000/2^(($X21-1.76)/6.02) -> 1939.2334 | AG21: =IF(ISNUMBER($Q21), $Q21+10*LOG10($AB21/2/$Y21), "") | AH21: =$X21+10*LOG10($AB21/2/$Y21) -> 152.9897 | AI21: =AF21/AB21 -> 0.0048480835 | AJ21: =AH21+10*LOG10(AB21) -> 209.0103
A22: 2004 | B22: 6.2 | C22: OS | D22: SDSC | E22: 0.18 | F22: A third-order ΣΔ modulator in 0.18 µm CMOS with calibrated mixed-mode integrators | G22: A third-order EA modulator employing mixed-mode integrators has been designed and implemented in 0.18um CMOS process. Because the use of mixed-mode integrators allows a 12dB improvement in the dynamic range over conventional third-order architectures, the modulator can be driven with lower sampling frequency to achieve the same dynamic range. The modulator covers the dynamic range requirements of GSM and WCDMA applications with sampling frequencies of only 3.2MHz and 40MHz, respectively. The circuit occupies 0.7mm² silicon area. | H22: =+IF(OR(ISBLANK(H21),ISERROR(H21)),"",H21) -> Jae Hoon Shim Beomsup Kim | I22: 10.1109/VLSIC.2004.1346510 | J22: =IF(I22<>"?", HYPERLINK(CONCATENATE("https://doi.org/",I22)), "") -> https://doi.org/10.1109/VLSIC.2004.1346510 | K22: WCDMA mode | P22: 0.7 | R22: 5000000 | U22: 55 | X22: =+IF(ISNUMBER($S22),$S22,MIN($V22,$T22,$U22,$W22)) -> 55 | Y22: 0.004 | Z22: 40000000 | AA22: 4 | AB22: =Z22/AA22 -> 10000000 | AD22: =Y22/AB22*1000000000000 -> 400 | AE22: =IF(ISNUMBER($Q22),$AD22*1000/2^(($Q22-1.76)/6.02), "") | AF22: =$AD22*1000/2^(($X22-1.76)/6.02) -> 870.55199 | AG22: =IF(ISNUMBER($Q22), $Q22+10*LOG10($AB22/2/$Y22), "") | AH22: =$X22+10*LOG10($AB22/2/$Y22) -> 145.9691 | AI22: =AF22/AB22 -> 8.7055199e-05 | AJ22: =AH22+10*LOG10(AB22) -> 215.9691
A23: 2004 | B23: 6.3 | C23: OS | D23: SDCT | E23: 0.13 | F23: A 12 bit Continuous-Time ΣΔ modulator with 400MHz clock and low jitter sensitivity in 0.13 µm CMOS | G23: A wide bandwidth Continuous-Time ΣΔ lowpass ADC with a 4-bit internal quantizer is presented. The converter is implemented in a pure digital 0.13 µm CMOS. It achieves 76dB Dynamic Range over 12MHz signal bandwidth tolerating up to 20ps RMS clock jitter. Operated at 400MHz the power consumption is 70mW from a 1.5V supply. The ADC has been designed to be tolerant to excess-loop delay and clock jitter. The 4th-order loop-filter is based on OpAmp-RC structure. | H23: Paton, S. Di Giandomenic, A. Hernandez, L. Wiesbauer, A. Potscher, T. Clara, M. | I23: 10.1109/VLSIC.2004.1346511 | J23: =IF(I23<>"?", HYPERLINK(CONCATENATE("https://doi.org/",I23)), "") -> https://doi.org/10.1109/VLSIC.2004.1346511 | L23: 1.5 | R23: 12000000 | S23: 61 | T23: 64 | U23: 76 | X23: =+IF(ISNUMBER($S23),$S23,MIN($V23,$T23,$U23,$W23)) -> 61 | Y23: 0.07 | Z23: 400000000 | AA23: 16.666667 | AB23: =Z23/AA23 -> 24000000 | AD23: =Y23/AB23*1000000000000 -> 2916.6667 | AE23: =IF(ISNUMBER($Q23),$AD23*1000/2^(($Q23-1.76)/6.02), "") | AF23: =$AD23*1000/2^(($X23-1.76)/6.02) -> 3181.2048 | AG23: =IF(ISNUMBER($Q23), $Q23+10*LOG10($AB23/2/$Y23), "") | AH23: =$X23+10*LOG10($AB23/2/$Y23) -> 143.34083 | AI23: =AF23/AB23 -> 0.0001325502 | AJ23: =AH23+10*LOG10(AB23) -> 217.14294
A24: 2004 | B24: 6.4 | C24: OS | D24: SDCT, BP | E24: 0.35 | F24: A 3.3-V 240-MS/s CMOS bandpass ΣΔ modulator using a fast-settling double-sampling SC filter | G24: A bandpass ΣΔ modulator is demonstrated to operate at a very high sampling rate of 240 MS/s by employing a proposed double-sampling switched-capacitor biquadratic filter architecture, which processes with a fast-settling feature. Implemented in a standard 0.35-µm CMOS process, the modulator achieves a peak SNDR of 72 dB, 55 dB and 52 dB at a bandwidth of 200 kHz, 1 MHz and 1.25 MHz for GSM, Bluetooth and CDMA2000 applications respectively while dissipating 37 mW and occupying a chip area of 1.2 mm². | H24: Cheung, V.S.L. Luong, H.C. | I24: 10.1109/VLSIC.2004.1346512 | J24: =IF(I24<>"?", HYPERLINK(CONCATENATE("https://doi.org/",I24)), "") -> https://doi.org/10.1109/VLSIC.2004.1346512 | P24: 1.2 | R24: 200000 | S24: 72 | X24: =+IF(ISNUMBER($S24),$S24,MIN($V24,$T24,$U24,$W24)) -> 72 | Y24: 0.037 | Z24: 240000000 | AA24: 600 | AB24: =Z24/AA24 -> 400000 | AC24: 60000000 | AD24: =Y24/AB24*1000000000000 -> 92500 | AE24: =IF(ISNUMBER($Q24),$AD24*1000/2^(($Q24-1.76)/6.02), "") | AF24: =$AD24*1000/2^(($X24-1.76)/6.02) -> 28430.975 | AG24: =IF(ISNUMBER($Q24), $Q24+10*LOG10($AB24/2/$Y24), "") | AH24: =$X24+10*LOG10($AB24/2/$Y24) -> 139.32828 | AI24: =AF24/AB24 -> 0.071077437 | AJ24: =AH24+10*LOG10(AB24) -> 195.34888
A25: 2004 | B25: 6.4 | C25: OS | D25: SDSC, BP | E25: 0.35 | F25: A 3.3-V 240-MS/s CMOS bandpass ΣΔ modulator using a fast-settling double-sampling SC filter | G25: A bandpass ΣΔ modulator is demonstrated to operate at a very high sampling rate of 240 MS/s by employing a proposed double-sampling switched-capacitor biquadratic filter architecture, which processes with a fast-settling feature. Implemented in a standard 0.35-µm CMOS process, the modulator achieves a peak SNDR of 72 dB, 55 dB and 52 dB at a bandwidth of 200 kHz, 1 MHz and 1.25 MHz for GSM, Bluetooth and CDMA2000 applications respectively while dissipating 37 mW and occupying a chip area of 1.2 mm². | H25: =+IF(OR(ISBLANK(H24),ISERROR(H24)),"",H24) -> Cheung, V.S.L. Luong, H.C. | I25: 10.1109/VLSIC.2004.1346512 | J25: =IF(I25<>"?", HYPERLINK(CONCATENATE("https://doi.org/",I25)), "") -> https://doi.org/10.1109/VLSIC.2004.1346512 | P25: 1.2 | R25: 1000000 | S25: 55 | X25: =+IF(ISNUMBER($S25),$S25,MIN($V25,$T25,$U25,$W25)) -> 55 | Y25: 0.037 | Z25: 240000000 | AA25: 120 | AB25: =Z25/AA25 -> 2000000 | AC25: 60000000 | AD25: =Y25/AB25*1000000000000 -> 18500 | AE25: =IF(ISNUMBER($Q25),$AD25*1000/2^(($Q25-1.76)/6.02), "") | AF25: =$AD25*1000/2^(($X25-1.76)/6.02) -> 40263.03 | AG25: =IF(ISNUMBER($Q25), $Q25+10*LOG10($AB25/2/$Y25), "") | AH25: =$X25+10*LOG10($AB25/2/$Y25) -> 129.31798 | AI25: =AF25/AB25 -> 0.020131515 | AJ25: =AH25+10*LOG10(AB25) -> 192.32828
A26: 2004 | B26: 6.4 | C26: OS | D26: SDSC, BP | E26: 0.35 | F26: A 3.3-V 240-MS/s CMOS bandpass ΣΔ modulator using a fast-settling double-sampling SC filter | G26: A bandpass ΣΔ modulator is demonstrated to operate at a very high sampling rate of 240 MS/s by employing a proposed double-sampling switched-capacitor biquadratic filter architecture, which processes with a fast-settling feature. Implemented in a standard 0.35-µm CMOS process, the modulator achieves a peak SNDR of 72 dB, 55 dB and 52 dB at a bandwidth of 200 kHz, 1 MHz and 1.25 MHz for GSM, Bluetooth and CDMA2000 applications respectively while dissipating 37 mW and occupying a chip area of 1.2 mm². | H26: =+IF(OR(ISBLANK(H25),ISERROR(H25)),"",H25) -> Cheung, V.S.L. Luong, H.C. | I26: 10.1109/VLSIC.2004.1346512 | J26: =IF(I26<>"?", HYPERLINK(CONCATENATE("https://doi.org/",I26)), "") -> https://doi.org/10.1109/VLSIC.2004.1346512 | P26: 1.2 | R26: 1250000 | S26: 52 | X26: =+IF(ISNUMBER($S26),$S26,MIN($V26,$T26,$U26,$W26)) -> 52 | Y26: 0.037 | Z26: 240000000 | AA26: 96 | AB26: =Z26/AA26 -> 2500000 | AC26: 60000000 | AD26: =Y26/AB26*1000000000000 -> 14800 | AE26: =IF(ISNUMBER($Q26),$AD26*1000/2^(($Q26-1.76)/6.02), "") | AF26: =$AD26*1000/2^(($X26-1.76)/6.02) -> 45499.999 | AG26: =IF(ISNUMBER($Q26), $Q26+10*LOG10($AB26/2/$Y26), "") | AH26: =$X26+10*LOG10($AB26/2/$Y26) -> 127.28708 | AI26: =AF26/AB26 -> 0.0182 | AJ26: =AH26+10*LOG10(AB26) -> 191.26648
A27: 2004 | B27: 25.1 | C27: NQ | D27: Flash | E27: 0.13 | F27: A 4GS/s 6b flash ADC in 0.13 µm CMOS | G27: A 4GS/s 6b flash ADC with 8b output is presented realized in a 0.13 µm standard CMOS technology. The outputs of 255 small-area comparators with comparatively large input offsets are averaged by a fault tolerant thermometer-to-binary converter. The ADC uses an on-chip low jitter VCO for clock provision and consumes 990mW at a single supply voltage of 1.5V. | H27: Paulus, C. Bluthgen, H.-M. Low, M. Sicheneder, E. Bruls, N. Courtois, A. Tiebout, M. Thewes, R. | I27: 10.1109/VLSIC.2004.1346637 | J27: =IF(I27<>"?", HYPERLINK(CONCATENATE("https://doi.org/",I27)), "") -> https://doi.org/10.1109/VLSIC.2004.1346637 | K27: SNDR, SNR not reported | L27: 1.5 | P27: 0.5 | R27: 2000000000 | W27: 30 | X27: =+IF(ISNUMBER($S27),$S27,MIN($V27,$T27,$U27,$W27)) -> 30 | Y27: 0.99 | Z27: 4000000000 | AA27: 1 | AB27: =Z27/AA27 -> 4000000000 | AD27: =Y27/AB27*1000000000000 -> 247.5 | AE27: =IF(ISNUMBER($Q27),$AD27*1000/2^(($Q27-1.76)/6.02), "") | AF27: =$AD27*1000/2^(($X27-1.76)/6.02) -> 9581.5218 | AG27: =IF(ISNUMBER($Q27), $Q27+10*LOG10($AB27/2/$Y27), "") | AH27: =$X27+10*LOG10($AB27/2/$Y27) -> 123.05395 | AI27: =AF27/AB27 -> 2.3953805e-06 | AJ27: =AH27+10*LOG10(AB27) -> 219.07455
A28: 2004 | B28: 25.2 | C28: NQ | D28: Folding | E28: 0.18 | F28: A 600 MSPS 8-bit folding ADC in 0.18 µm CMOS | G28: An 8-bit folding A/D converter (ADC) achieves signal-to-noise plus distortion ratio (SNDR) of 40 dB at 600 MSample/s (MSPS) for input signals up to 200 MHz in standard 0.18-µm CMOS. Distributed T/Hs at outputs of the first-stage pre-amplifiers are employed instead of a dedicated front-end T/H. Lateral capacitors are inserted between adjacent T/H outputs to average the random mismatches in charge injection and clock skew among the distributed T/Hs. The ADC consumes 0.5-mm² effective chip area and dissipates 207mW from a 1.8V supply. | H28: Zheng-Yu Wang Hui Pan Chung-Ming Chang Hai-Rong Yu Chang, M.F. | I28: 10.1109/VLSIC.2004.1346638 | J28: =IF(I28<>"?", HYPERLINK(CONCATENATE("https://doi.org/",I28)), "") -> https://doi.org/10.1109/VLSIC.2004.1346638 | L28: 1.8 | P28: 0.5 | R28: =600000000/2 -> 300000000 | S28: 40 | U28: =7.5*6.02+1.76 -> 46.91 | X28: =+IF(ISNUMBER($S28),$S28,MIN($V28,$T28,$U28,$W28)) -> 40 | Y28: 0.207 | Z28: =600000000 -> 600000000 | AA28: 1 | AB28: =Z28/AA28 -> 600000000 | AD28: =Y28/AB28*1000000000000 -> 345 | AE28: =IF(ISNUMBER($Q28),$AD28*1000/2^(($Q28-1.76)/6.02), "") | AF28: =$AD28*1000/2^(($X28-1.76)/6.02) -> 4223.0727 | AG28: =IF(ISNUMBER($Q28), $Q28+10*LOG10($AB28/2/$Y28), "") | AH28: =$X28+10*LOG10($AB28/2/$Y28) -> 131.61151 | AI28: =AF28/AB28 -> 7.0384545e-06 | AJ28: =AH28+10*LOG10(AB28) -> 219.39302
A29: 2004 | B29: 25.3 | C29: NQ | D29: Pipe | E29: 0.34 BiCMOS | F29: A highly integrated analog baseband transceiver featuring a 12-bit 180MSPS pipelined A/D converter for multi-channel wireless LAN | G29: This analog baseband transceiver features a 12-bit, 180MSPS pipelined ADC with -71dBFS THD and 61dB SNR sharing substrate with dual I/Q 10-bit 180MSPS D/A converters and low-jitter DLL/digital buffers. Fabricated in the IBM BiCMOS6HP process and packaged in a low-inductance 6-layer flip-chip, the ADC consumes a total of 1.2W at 3.3V. The converter utilizes 1.5b/stage switched-capacitor stages with a wide-band, high-gain opamp employing 2.5V bipolar devices, a dedicated track/hold amplifier, and a voltage reference without an amplifier. | H29: Gulati, K. Munoz, C. Seonghwan Cho Manganaro, G. Lugin, M. Peng, M. Pulincherry, A. Jipeng Li Bugeja, A. Chandrakasan, A. Shoemaker, D. | I29: 10.1109/VLSIC.2004.1346639 | J29: =IF(I29<>"?", HYPERLINK(CONCATENATE("https://doi.org/",I29)), "") -> https://doi.org/10.1109/VLSIC.2004.1346639 | L29: 3.3 | P29: 8 | R29: =180000000/2 -> 90000000 | S29: =9.74*6.02+1.76 -> 60.3948 | T29: 60.7 | V29: 72 | X29: =+IF(ISNUMBER($S29),$S29,MIN($V29,$T29,$U29,$W29)) -> 60.3948 | Y29: 1.2 | Z29: =180000000 -> 180000000 | AA29: 1 | AB29: =Z29/AA29 -> 180000000 | AD29: =Y29/AB29*1000000000000 -> 6666.6667 | AE29: =IF(ISNUMBER($Q29),$AD29*1000/2^(($Q29-1.76)/6.02), "") | AF29: =$AD29*1000/2^(($X29-1.76)/6.02) -> 7796.0853 | AG29: =IF(ISNUMBER($Q29), $Q29+10*LOG10($AB29/2/$Y29), "") | AH29: =$X29+10*LOG10($AB29/2/$Y29) -> 139.14541 | AI29: =AF29/AB29 -> 4.3311585e-05 | AJ29: =AH29+10*LOG10(AB29) -> 221.69814
A30: 2004 | B30: 25.4 | C30: NQ | D30: Pipe, TI, SwOpAmp | E30: 0.18 | F30: A 1.5-V 10-b 50 MS/s time-interleaved switched-opamp pipeline CMOS ADC with high energy efficiency | G30: A 1.5V 10-b 50MS/s 2-channel pipeline ADC is described. Amplifiers are efficiently shared between channels using low-voltage techniques to reduce the power supply. The selected resolution per stage avoids the need of scaling the stages, simplifying the implementation of a low-power design. Measurements from the prototypes fabricated in a 0.18 µm CMOS technology exhibit 10b DNL, 9.5b INL and 9.2 effective bits at Nyquist-rate. The chip occupies 1.3 mm² and dissipates only 29 mW at 1.5V. | H30: B. Vaz, J. Goes, N. Paulino | I30: 10.1109/VLSIC.2004.1346640 | J30: =IF(I30<>"?", HYPERLINK(CONCATENATE("https://doi.org/",I30)), "") -> https://doi.org/10.1109/VLSIC.2004.1346640 | L30: 1.5 | P30: 1.3 | R30: =50000000/2 -> 25000000 | S30: 57.2 | T30: 62 | V30: 60.3 | W30: 62.3 | X30: =+IF(ISNUMBER($S30),$S30,MIN($V30,$T30,$U30,$W30)) -> 57.2 | Y30: 0.029 | Z30: =50000000 -> 50000000 | AA30: 1 | AB30: =Z30/AA30 -> 50000000 | AD30: =Y30/AB30*1000000000000 -> 580 | AE30: =IF(ISNUMBER($Q30),$AD30*1000/2^(($Q30-1.76)/6.02), "") | AF30: =$AD30*1000/2^(($X30-1.76)/6.02) -> 979.83231 | AG30: =IF(ISNUMBER($Q30), $Q30+10*LOG10($AB30/2/$Y30), "") | AH30: =$X30+10*LOG10($AB30/2/$Y30) -> 146.55542 | AI30: =AF30/AB30 -> 1.9596646e-05 | AJ30: =AH30+10*LOG10(AB30) -> 223.54512
A31: 2004 | B31: 25.5 | C31: NQ | D31: Algorithmic | E31: 0.18 | F31: 0.9V 12mW 2MSPS algorithmic ADC with 81dB SFDR | G31: An ultra low-voltage CMOS two-stage algorithm ADC incorporating background digital calibration is presented. The adopted low-voltage circuit technique achieves high-accuracy high-speed clocking without the use of clock boosting or bootstrapping. A resistor-based input sampling branch demonstrates high linearity and inherent low-voltage operation. The proposed background calibration accounts for capacitor mismatches and finite opamp gain error in the MDAC stages via a novel digital correlation scheme involving a two-channel ADC architecture. The prototype ADC, fabricated in a 0.18 µm CMOS process, achieves 81 dB SFDR at 0.9V and 2MSPS (12MHz clock) after calibration. The ADC operates up to 5MSPS (30MHz clock) with 4dB degradation. The total power consumption is 12mW, and the active die area is 1.4 mm². | H31: J. Li, G.-C. Ahn, D.-Y. Chang, U.-K. Moon | I31: 10.1109/VLSIC.2004.1346641 | J31: =IF(I31<>"?", HYPERLINK(CONCATENATE("https://doi.org/",I31)), "") -> https://doi.org/10.1109/VLSIC.2004.1346641 | L31: 0.9 | P31: 1.4 | R31: 2000000 | S31: 55 | T31: 55 | W31: 81 | X31: =+IF(ISNUMBER($S31),$S31,MIN($V31,$T31,$U31,$W31)) -> 55 | Y31: 0.012 | Z31: 4000000 | AA31: 1 | AB31: =Z31/AA31 -> 4000000 | AD31: =Y31/AB31*1000000000000 -> 3000 | AE31: =IF(ISNUMBER($Q31),$AD31*1000/2^(($Q31-1.76)/6.02), "") | AF31: =$AD31*1000/2^(($X31-1.76)/6.02) -> 6529.1399 | AG31: =IF(ISNUMBER($Q31), $Q31+10*LOG10($AB31/2/$Y31), "") | AH31: =$X31+10*LOG10($AB31/2/$Y31) -> 137.21849 | AI31: =AF31/AB31 -> 0.001632285 | AJ31: =AH31+10*LOG10(AB31) -> 203.23909
A32: 2005 | B32: 12.2 | C32: OS | D32: SDSC | E32: 0.25 | F32: An energy-efficient analog front-end circuit for a sub-1V digital hearing aid chip | G32: A low-power, energy-efficient analog front-end circuit is proposed and implemented for a digital hearing aid chip. It adopts the combined-gain-control (CGC) technique for an accurate preamplification and the adaptive-SNR (ASNR) technique for an improvement of dynamic range with low power consumption. The proposed analog front-end achieves 87-dB peak SNR and dissipates 60-µW from a single 0.9-V supply. The core area is 0.5-mm² in a 0.25-µm standard CMOS technology. | H32: S. Kim, J.-Y. Lee, S.-J. Song, N. Cho, H.-J. Yoo | I32: 10.1109/VLSIC.2005.1469361 | J32: =IF(I32<>"?", HYPERLINK(CONCATENATE("https://doi.org/",I32)), "") -> https://doi.org/10.1109/VLSIC.2005.1469361 | K32: Type 1 | L32: 0.9 | P32: 0.5 | R32: 8000 | S32: 69 | T32: 72 | X32: =+IF(ISNUMBER($S32),$S32,MIN($V32,$T32,$U32,$W32)) -> 69 | Y32: 2.63e-05 | Z32: 1024000 | AA32: 64 | AB32: =Z32/AA32 -> 16000 | AD32: =Y32/AB32*1000000000000 -> 1643.75 | AE32: =IF(ISNUMBER($Q32),$AD32*1000/2^(($Q32-1.76)/6.02), "") | AF32: =$AD32*1000/2^(($X32-1.76)/6.02) -> 713.67541 | AG32: =IF(ISNUMBER($Q32), $Q32+10*LOG10($AB32/2/$Y32), "") | AH32: =$X32+10*LOG10($AB32/2/$Y32) -> 153.83134 | AI32: =AF32/AB32 -> 0.044604713 | AJ32: =AH32+10*LOG10(AB32) -> 195.87254
A33: 2005 | B33: 12.3 | C33: OS | D33: SDSC | E33: 0.13 | F33: A 1-V, 1-MS/s, 88-dB sigma-delta modulator in 0.13-µm digital CMOS technology | G33: A low-voltage switched-capacitor fourth-order Σ-Δ modulator using full feed-forward is introduced. It has two advantages: the unity signal transfer function and reduced signal swings inside the Σ-Δ loop. These features greatly relax the DC gain and output swing requirements for OTAs in the deep submicron CMOS Σ-Δ modulator. With careful signal scaling, signal swings inside the loop can be suppressed to less than 50% of the reference voltage, which is highly desirable by low-voltage designs. Implemented by a 0.13-µm pure digital CMOS technology, the Σ-Δ modulator achieves 1-MS/s conversion speed and 88-dB DR with 7.4-mW power dissipation under 1.0-V power supply voltage. | H33: Libin Yao Steyaert, M. Sansen, W. | I33: 10.1109/VLSIC.2005.1469362 | J33: =IF(I33<>"?", HYPERLINK(CONCATENATE("https://doi.org/",I33)), "") -> https://doi.org/10.1109/VLSIC.2005.1469362 | L33: 1 | P33: 0.6016 | R33: 500000 | U33: 88 | X33: =+IF(ISNUMBER($S33),$S33,MIN($V33,$T33,$U33,$W33)) -> 88 | Y33: 0.0074 | Z33: 64000000 | AA33: 64 | AB33: =Z33/AA33 -> 1000000 | AD33: =Y33/AB33*1000000000000 -> 7400 | AE33: =IF(ISNUMBER($Q33),$AD33*1000/2^(($Q33-1.76)/6.02), "") | AF33: =$AD33*1000/2^(($X33-1.76)/6.02) -> 360.4143 | AG33: =IF(ISNUMBER($Q33), $Q33+10*LOG10($AB33/2/$Y33), "") | AH33: =$X33+10*LOG10($AB33/2/$Y33) -> 166.29738 | AI33: =AF33/AB33 -> 0.0003604143 | AJ33: =AH33+10*LOG10(AB33) -> 226.29738
A34: 2005 | B34: 12.4 | C34: OS | D34: SDSC | E34: 0.35 | F34: On-line calibration and digital correction of multi-bit sigma-delta modulators | G34: This paper presents a new method for the on-line calibration of the elements of the digital-to-analog converter (DAC) used in the feedback loop of multi-bit sigma-delta (ΣΔ) modulators. The proposed method, with an extremely limited amount of additional circuitry, allows the mismatches among the elements of the DAC to be accurately measured and corrected in the digital domain, thus improving the linearity performance of the modulator. A switched-capacitor (SC) 4-bit ΣΔ modulator has been implemented to validate the proposed solution. The experimental results confirm that this method allows us to achieve an improvement in the spurious-free dynamic range as large as 26 dB. | H34: Fornasari, A. Borghetti, F. Malcovati, P. Maloberti, F. | I34: 10.1109/VLSIC.2005.1469363 | J34: =IF(I34<>"?", HYPERLINK(CONCATENATE("https://doi.org/",I34)), "") -> https://doi.org/10.1109/VLSIC.2005.1469363 | K34: Power not reported, cannot compute FOM | S34: 66.1 | W34: 87 | X34: 66.1 | Z34: 2300000 | AB34: 18000 | AD34: 10000000000 | AF34: 10000000000 | AH34: 1
A35: 2005 | B35: 21.1 | C35: NQ | D35: Pipe, TI | E35: 0.18 | F35: A 6GS/s, 4-bit receiver analog-to-digital converter with embedded DFE | G35: A 4-bit 6GS/s A/D converter is designed for a serial-link receiver and features an embedded adjustable one-tap DFE. Feedback-delay is relaxed through applying DFE to a 10-way interleaved pipelined architecture. Code-overlapping is used to remove residual ISI. Measured performance at 6GS/s shows 22.5dB of low-frequency input SNDR. DFE tap-coefficient is adjustable from 0 to 0.25 with 6-bits of programmable weight. The 1.8⨉1.6mm² chip is fabricated in 0.18µm CMOS technology and consumes 780mW at 1.8V power-supply. | H35: Varzaghani, A. Yang, C.-K.K. | I35: 10.1109/VLSIC.2005.1469396 | J35: =IF(I35<>"?", HYPERLINK(CONCATENATE("https://doi.org/",I35)), "") -> https://doi.org/10.1109/VLSIC.2005.1469396 | L35: 1.8 | P35: 2.88 | R35: 3000000000 | S35: 22.5 | X35: =+IF(ISNUMBER($S35),$S35,MIN($V35,$T35,$U35,$W35)) -> 22.5 | Y35: 0.78 | Z35: 6000000000 | AA35: 1 | AB35: =Z35/AA35 -> 6000000000 | AD35: =Y35/AB35*1000000000000 -> 130 | AE35: =IF(ISNUMBER($Q35),$AD35*1000/2^(($Q35-1.76)/6.02), "") | AF35: =$AD35*1000/2^(($X35-1.76)/6.02) -> 11935.483 | AG35: =IF(ISNUMBER($Q35), $Q35+10*LOG10($AB35/2/$Y35), "") | AH35: =$X35+10*LOG10($AB35/2/$Y35) -> 118.35027 | AI35: =AF35/AB35 -> 1.9892472e-06 | AJ35: =AH35+10*LOG10(AB35) -> 216.13178
A36: 2005 | B36: 21.2 | C36: NQ | D36: Pipe | E36: 0.18 | F36: A reconfigurable pipelined ADC in 0.18 µm CMOS | G36: A reconfigurable pipelined A/D converter has been implemented in a 0.18 µm RF-CMOS process. The ADC has eight configurations with a top performance of 10 bits resolution at 80 MSPS consuming 94mW. The reconfigurability is achieved by combining the cyclic and pipelined ADC architectures giving it a low level of complexity. In the conventional pipeline mode, the measured SFDR is 69 dBFS and the SNDR is 56.5 dBc for a 1.54 MHz single sinusoid tone input. | H36: Anderson, M. Norling, K. Dreyfert, A. Yuan, J. | I36: 10.1109/VLSIC.2005.1469397 | J36: =IF(I36<>"?", HYPERLINK(CONCATENATE("https://doi.org/",I36)), "") -> https://doi.org/10.1109/VLSIC.2005.1469397 | P36: 1.9 | R36: 5000000 | S36: 58.8 | T36: 59 | V36: 71.1 | W36: 76.3 | X36: =+IF(ISNUMBER($S36),$S36,MIN($V36,$T36,$U36,$W36)) -> 58.8 | Y36: 0.081 | Z36: 10000000 | AA36: 1 | AB36: =Z36/AA36 -> 10000000 | AD36: =Y36/AB36*1000000000000 -> 8100 | AE36: =IF(ISNUMBER($Q36),$AD36*1000/2^(($Q36-1.76)/6.02), "") | AF36: =$AD36*1000/2^(($X36-1.76)/6.02) -> 11381.534 | AG36: =IF(ISNUMBER($Q36), $Q36+10*LOG10($AB36/2/$Y36), "") | AH36: =$X36+10*LOG10($AB36/2/$Y36) -> 136.70485 | AI36: =AF36/AB36 -> 0.0011381534 | AJ36: =AH36+10*LOG10(AB36) -> 206.70485
A37: 2005 | B37: 21.2 | C37: NQ | D37: Pipe | E37: 0.18 | F37: A reconfigurable pipelined ADC in 0.18 µm CMOS | G37: A reconfigurable pipelined A/D converter has been implemented in a 0.18 µm RF-CMOS process. The ADC has eight configurations with a top performance of 10 bits resolution at 80 MSPS consuming 94mW. The reconfigurability is achieved by combining the cyclic and pipelined ADC architectures giving it a low level of complexity. In the conventional pipeline mode, the measured SFDR is 69 dBFS and the SNDR is 56.5 dBc for a 1.54 MHz single sinusoid tone input. | H37: =+IF(OR(ISBLANK(H36),ISERROR(H36)),"",H36) -> Anderson, M. Norling, K. Dreyfert, A. Yuan, J. | I37: 10.1109/VLSIC.2005.1469397 | J37: =IF(I37<>"?", HYPERLINK(CONCATENATE("https://doi.org/",I37)), "") -> https://doi.org/10.1109/VLSIC.2005.1469397 | P37: 1.9 | R37: 40000000 | S37: 56.5 | T37: 56.9 | V37: 67 | W37: 69.1 | X37: =+IF(ISNUMBER($S37),$S37,MIN($V37,$T37,$U37,$W37)) -> 56.5 | Y37: 0.094 | Z37: 80000000 | AA37: 1 | AB37: =Z37/AA37 -> 80000000 | AD37: =Y37/AB37*1000000000000 -> 1175 | AE37: =IF(ISNUMBER($Q37),$AD37*1000/2^(($Q37-1.76)/6.02), "") | AF37: =$AD37*1000/2^(($X37-1.76)/6.02) -> 2151.6177 | AG37: =IF(ISNUMBER($Q37), $Q37+10*LOG10($AB37/2/$Y37), "") | AH37: =$X37+10*LOG10($AB37/2/$Y37) -> 142.78932 | AI37: =AF37/AB37 -> 2.6895222e-05 | AJ37: =AH37+10*LOG10(AB37) -> 221.82022
A38: 2005 | B38: 21.3 | C38: NQ | D38: Pipe | E38: 0.18 | F38: A 14bit digitally self-calibrated pipelined ADC with adaptive bias optimization for arbitrary speeds up to 40MS/s | G38: A 14bit digitally self-calibrated pipelined ADC featuring the adaptive bias optimization is fabricated in a 0.18µm dual-gate CMOS and consumes 19.2, 33.7, 50.5 and 72.8mW respectively when operating at 10, 20, 30 and 40MS/s. In all the operating speeds with temperature variation up to 80°C, DNL is kept between ±0.60LSB. When operating at 20MS/s, it achieves 73.2dB SNR and 70.4dB SNDR. | H38: Matsui, H. Ueda, M. Daito, M. Iizuka, K. | I38: 10.1109/VLSIC.2005.1469398 | J38: =IF(I38<>"?", HYPERLINK(CONCATENATE("https://doi.org/",I38)), "") -> https://doi.org/10.1109/VLSIC.2005.1469398 | P38: 1.15 | R38: 10000000 | S38: 70.4 | T38: 73.2 | X38: =+IF(ISNUMBER($S38),$S38,MIN($V38,$T38,$U38,$W38)) -> 70.4 | Y38: 0.0337 | Z38: 20000000 | AA38: 1 | AB38: =Z38/AA38 -> 20000000 | AD38: =Y38/AB38*1000000000000 -> 1685 | AE38: =IF(ISNUMBER($Q38),$AD38*1000/2^(($Q38-1.76)/6.02), "") | AF38: =$AD38*1000/2^(($X38-1.76)/6.02) -> 622.66993 | AG38: =IF(ISNUMBER($Q38), $Q38+10*LOG10($AB38/2/$Y38), "") | AH38: =$X38+10*LOG10($AB38/2/$Y38) -> 155.1237 | AI38: =AF38/AB38 -> 3.1133497e-05 | AJ38: =AH38+10*LOG10(AB38) -> 228.134
A39: 2006 | B39: 6.2 | C39: NQ | D39: Algorithmic | E39: 0.13 | F39: A 12-Bit 32 µW Ratio-Independent Algorithmic ADC | G39: This paper describes a ratio-independent algorithmic ADC architecture that requires a single differential amplifier and a comparator. The prototype 12-bit, 41.67 kS/s ADC with an active die area of 0.055 mm² is implemented in a 0.13mum CMOS. The power dissipation is minimized using a dynamically biased operational amplifier. With a 32 muW power dissipation, the ADC achieves 80 dB SFDR and 60 dB SNDR, resulting in a power FOM of 0.9 pJ/conversion | H39: J. Jarvinen, M. Saukoski, K. Halonen | I39: 10.1109/VLSIC.2006.1705305 | J39: =IF(I39<>"?", HYPERLINK(CONCATENATE("https://doi.org/",I39)), "") -> https://doi.org/10.1109/VLSIC.2006.1705305 | P39: 0.055 | R39: =41670/2 -> 20835 | S39: 60 | W39: 80 | X39: =+IF(ISNUMBER($S39),$S39,MIN($V39,$T39,$U39,$W39)) -> 60 | Y39: 3.2e-05 | Z39: 41670 | AA39: 1 | AB39: =Z39/AA39 -> 41670 | AD39: =Y39/AB39*1000000000000 -> 767.93856 | AE39: =IF(ISNUMBER($Q39),$AD39*1000/2^(($Q39-1.76)/6.02), "") | AF39: =$AD39*1000/2^(($X39-1.76)/6.02) -> 939.80183 | AG39: =IF(ISNUMBER($Q39), $Q39+10*LOG10($AB39/2/$Y39), "") | AH39: =$X39+10*LOG10($AB39/2/$Y39) -> 148.13644 | AI39: =AF39/AB39 -> 0.02255344 | AJ39: =AH39+10*LOG10(AB39) -> 194.33467
A40: 2006 | B40: 6.3 | C40: NQ | D40: Algorithmic | E40: 0.13 | F40: A 10MS/s 11-b 0.19mm² Algorithmic ADC with Improved Clocking | G40: A 10Ms/s 11-b algorithmic ADC with an active area of 0.19mm² is presented. Using an improved clocking scheme, this design overcomes the speed limit of algorithmic ADCs. The proposed ADC employs amplifier sharing, DC offset cancellation, and input memory effect suppression to reduce area and power, and achieve high linearity. The ADC implemented in a 0.13mum thick gate-oxide CMOS process achieves 69dB SFDR, 58dB SNR, and 56dB SNDR, while consuming 3.5mA from 3V supply | H40: M. Kim P. Hanumolu U.-K. Moon | I40: 10.1109/VLSIC.2006.1705306 | J40: =IF(I40<>"?", HYPERLINK(CONCATENATE("https://doi.org/",I40)), "") -> https://doi.org/10.1109/VLSIC.2006.1705306 | L40: 3 | P40: 0.19 | R40: =10000000/2 -> 5000000 | S40: 56 | T40: 58 | W40: 69 | X40: =+IF(ISNUMBER($S40),$S40,MIN($V40,$T40,$U40,$W40)) -> 56 | Y40: 0.01 | Z40: 10000000 | AA40: 1 | AB40: =Z40/AA40 -> 10000000 | AD40: =Y40/AB40*1000000000000 -> 1000 | AE40: =IF(ISNUMBER($Q40),$AD40*1000/2^(($Q40-1.76)/6.02), "") | AF40: =$AD40*1000/2^(($X40-1.76)/6.02) -> 1939.6784 | AG40: =IF(ISNUMBER($Q40), $Q40+10*LOG10($AB40/2/$Y40), "") | AH40: =$X40+10*LOG10($AB40/2/$Y40) -> 142.9897 | AI40: =AF40/AB40 -> 0.00019396784 | AJ40: =AH40+10*LOG10(AB40) -> 212.9897
A41: 2006 | B41: 16.1 | C41: NQ | D41: Pipe | E41: 0.18 | F41: A 6-Bit 800-MS/s Pipelined A/D Converter with Open-Loop Amplifiers | G41: A 6-bit 800-MS/s Pipelined A/D converter (ADC) with voltage-mode open-loop amplifiers achieves SNDR and SFDR of 33.7 dB and 47.5 dB, respectively. Fabricated in a 0.18mum CMOS technology, the ADC consumes 105 mW from a 1.8-V power supply while the active area is only 0.5-mm² | H41: D.-L. Shen, T.-C. Lee | I41: 10.1109/VLSIC.2006.1705346 | J41: =IF(I41<>"?", HYPERLINK(CONCATENATE("https://doi.org/",I41)), "") -> https://doi.org/10.1109/VLSIC.2006.1705346 | L41: 1.8 | P41: 0.5 | R41: 400000000 | S41: 33.7 | W41: 47.5 | X41: =+IF(ISNUMBER($S41),$S41,MIN($V41,$T41,$U41,$W41)) -> 33.7 | Y41: 0.105 | Z41: 800000000 | AA41: 1 | AB41: =Z41/AA41 -> 800000000 | AD41: =Y41/AB41*1000000000000 -> 131.25 | AE41: =IF(ISNUMBER($Q41),$AD41*1000/2^(($Q41-1.76)/6.02), "") | AF41: =$AD41*1000/2^(($X41-1.76)/6.02) -> 3318.4873 | AG41: =IF(ISNUMBER($Q41), $Q41+10*LOG10($AB41/2/$Y41), "") | AH41: =$X41+10*LOG10($AB41/2/$Y41) -> 129.50871 | AI41: =AF41/AB41 -> 4.1481092e-06 | AJ41: =AH41+10*LOG10(AB41) -> 218.53961
A42: 2006 | B42: 16.2 | C42: NQ | D42: Pipe, SwOpAmp | E42: 0.18 | F42: A 1-V 100MS/s 8-bit CMOS Switched-Opamp Pipelined ADC Using Loading-Free Architecture | G42: A 1V, 8-bit dual-mode ADC is realized using multi-phase switched-opamp (SO) technique. Employing a proposed loading-free pipelined ADC architecture and a fast-wake-up dual-input-dual-output switchable opamp, the ADC achieves 100MS/s conversion rate, which is the fastest operation speed reported at 1-V supply, and comparable to many high-voltage switched-capacitor (SC) ADC. Implemented in a 0.18mum CMOS process, the ADC obtains a peak SNR of 45dB and SFDR of 52.6dB while dissipating only 30mW | H42: Y. Wu, V. Cheung, H. Luong | I42: 10.1109/VLSIC.2006.1705347 | J42: =IF(I42<>"?", HYPERLINK(CONCATENATE("https://doi.org/",I42)), "") -> https://doi.org/10.1109/VLSIC.2006.1705347 | K42: Double-sampling mode | L42: 1 | P42: 2.04 | R42: 50000000 | S42: 41.5 | T42: 45.2 | W42: 52.6 | X42: =+IF(ISNUMBER($S42),$S42,MIN($V42,$T42,$U42,$W42)) -> 41.5 | Y42: 0.03 | Z42: 100000000 | AA42: 1 | AB42: =Z42/AA42 -> 100000000 | AD42: =Y42/AB42*1000000000000 -> 300 | AE42: =IF(ISNUMBER($Q42),$AD42*1000/2^(($Q42-1.76)/6.02), "") | AF42: =$AD42*1000/2^(($X42-1.76)/6.02) -> 3089.7493 | AG42: =IF(ISNUMBER($Q42), $Q42+10*LOG10($AB42/2/$Y42), "") | AH42: =$X42+10*LOG10($AB42/2/$Y42) -> 133.71849 | AI42: =AF42/AB42 -> 3.0897493e-05 | AJ42: =AH42+10*LOG10(AB42) -> 213.71849
A43: =+IF(OR(ISBLANK(A42),ISERROR(A42)),"",A42) -> 2006 | B43: =+IF(OR(ISBLANK(B42),ISERROR(B42)),"",B42) -> 16.2 | C43: =+IF(OR(ISBLANK(C42),ISERROR(C42)),"",C42) -> NQ | D43: =+IF(OR(ISBLANK(D42),ISERROR(D42)),"",D42) -> Pipe, SwOpAmp | E43: =+IF(OR(ISBLANK(E42),ISERROR(E42)),"",E42) -> 0.18 | F43: A 1-V 100MS/s 8-bit CMOS Switched-Opamp Pipelined ADC Using Loading-Free Architecture | G43: A 1V, 8-bit dual-mode ADC is realized using multi-phase switched-opamp (SO) technique. Employing a proposed loading-free pipelined ADC architecture and a fast-wake-up dual-input-dual-output switchable opamp, the ADC achieves 100MS/s conversion rate, which is the fastest operation speed reported at 1-V supply, and comparable to many high-voltage switched-capacitor (SC) ADC. Implemented in a 0.18mum CMOS process, the ADC obtains a peak SNR of 45dB and SFDR of 52.6dB while dissipating only 30mW | H43: =+IF(OR(ISBLANK(H42),ISERROR(H42)),"",H42) -> Y. Wu, V. Cheung, H. Luong | I43: 10.1109/VLSIC.2006.1705347 | J43: =IF(I43<>"?", HYPERLINK(CONCATENATE("https://doi.org/",I43)), "") -> https://doi.org/10.1109/VLSIC.2006.1705347 | K43: Quadrature mode | L43: 1 | P43: 2.04 | R43: 20000000 | S43: 44.5 | T43: 46.5 | W43: 54.4 | X43: =+IF(ISNUMBER($S43),$S43,MIN($V43,$T43,$U43,$W43)) -> 44.5 | Y43: 0.03 | Z43: 40000000 | AA43: 1 | AB43: =Z43/AA43 -> 40000000 | AD43: =Y43/AB43*1000000000000 -> 750 | AE43: =IF(ISNUMBER($Q43),$AD43*1000/2^(($Q43-1.76)/6.02), "") | AF43: =$AD43*1000/2^(($X43-1.76)/6.02) -> 5468.2493 | AG43: =IF(ISNUMBER($Q43), $Q43+10*LOG10($AB43/2/$Y43), "") | AH43: =$X43+10*LOG10($AB43/2/$Y43) -> 132.73909 | AI43: =AF43/AB43 -> 0.00013670623 | AJ43: =AH43+10*LOG10(AB43) -> 208.75969
